Workbook

Sheet INFORMES
A1: SPRINT | B1: COD_INFORME | C1: DESC_INFORME | D1: TABLA | E1: F_INICIO | F1: F_FIN | G1: CARGA_TABLAS | H1: PUBLICACION | I1: FORMATO | J1: DESCRIPCION
A2: 1 | B2: 1.1 | C2: W-O - Rappel por Producción Resumen | D2: INYC_RPI_RESUMEN | E2: 20140101 | F2: 22000101 | G2: 1,2,3,4,5,6,7,8,9,10,11,12 | H2: 1,2,3,4,5,6,7,8,9,10,11,12 | I2: pdf | J2: RPI
A3: 1 | B3: 1.2 | C3: W-O - Rappel por Producción Detalle | D3: INYC_RPI_DETALLE | E3: 20140101 | F3: 20180101 | G3: 1,2,3,4,5,6,7,8,9,10,11,12 | H3: 1,2,3,4,5,6,7,8,9,10,11,12 | I3: excel | J3: RPI_DETALLE
A4: 2 | B4: 2.1 | C4: W-E - Rappel por Producción Resumen | D4: INYC_RAG_RESUMEN | E4: 20140101 | F4: 22000101 | G4: 1,2,3,4,5,6,7,8,9,10,11,12 | H4: 1,2,3,4,5,6,7,8,9,10,11,12 | I4: pdf | J4: RAG
A5: 2 | B5: 2.2 | C5: W-E - Rappel por Producción Detalle | D5: INYC_RAG_DETALLE | E5: 20140101 | F5: 20180101 | G5: 1,2,3,4,5,6,7,8,9,10,11,12 | H5: 1,2,3,4,5,6,7,8,9,10,11,12 | I5: excel | J5: RAG_DETALLE
A6: 0 | B6: 2.3 | C6: W-E - Rappel por producción Trimestral Resumen | D6: INYC_RAGT_RESUMEN | E6: 20190101 | F6: 22000101 | G6: 1,2,3,4,5,6,7,8,9,10,11,12 | H6: 1,2,3,4,5,6,7,8,9,10,11,12 | I6: pdf | J6: RAGT
A7: 2 | B7: 3.1 | C7: W-E - Rappel Producción Agentes Resumen | D7: INYC_RA_RESUMEN | E7: 20140101 | F7: 22000101 | G7: 1,2,3,4,5,6,7,8,9,10,11,12 | H7: 1,2,3,4,5,6,7,8,9,10,11,12 | I7: pdf | J7: RA
A8: 2 | B8: 3.2 | C8: W-E - Rappel Producción Agentes Detalle | D8: INYC_RA_DETALLE | E8: 20140101 | F8: 22000101 | G8: 1,2,3,4,5,6,7,8,9,10,11,12 | H8: 1,2,3,4,5,6,7,8,9,10,11,12 | I8: excel | J8: RA
A9: 2 | B9: 4.1 | C9: W-E - Ranking Concurso de Producción Anual | D9: INYC_CONCURSO | E9: 20140101 | F9: 22000101 | G9: 12 | H9: 12 | I9: pdf | J9: CONCURSO
A10: 2 | B10: 5.1 | C10: W-E - Incentivo Especial Anual | D10: INYC_INCENTIVO | E10: 20140101 | F10: 22000101 | G10: 12 | H10: 12 | I10: pdf | J10: INCENTIVO
A11: 2 | B11: 6.1 | C11: W-O - Rappel Producción Agentes Resumen | D11: INYC_RPA_RESUMEN | E11: 20140101 | F11: 22000101 | G11: 1,2,3,4,5,6,7,8,9,10,11,12 | H11: 1,2,3,4,5,6,7,8,9,10,11,12 | I11: pdf | J11: RPA
A12: 2 | B12: 6.2 | C12: W-O - Rappel Producción Agentes Detalle | D12: INYC_RPA_DETALLE | E12: 20140101 | F12: 22000101 | G12: 1,2,3,4,5,6,7,8,9,10,11,12 | H12: 1,2,3,4,5,6,7,8,9,10,11,12 | I12: excel | J12: RPA
A13: 3 | B13: 7.1 | C13: W-O - Diferenciales Resumen | D13: INYC_DIF_RESUMEN | E13: 20140101 | F13: 22000101 | G13: 1,2,3,4,5,6,7,8,9,10,11,12 | H13: 1,2,3,4,5,6,7,8,9,10,11,12 | I13: pdf | J13: DIF
A14: 3 | B14: 7.2 | C14: W-O - Diferenciales Detalle | D14: INYC_DIF_DETALLE | E14: 20140101 | F14: 20180101 | G14: 1,2,3,4,5,6,7,8,9,10,11,12 | H14: 1,2,3,4,5,6,7,8,9,10,11,12 | I14: excel | J14: DIF_DETALLE
A15: 3 | B15: 8.1 | C15: W-O - Incentivos por Cumplimiento de Objetivos y Liquidación a Cuenta Resumen | D15: INYC_COLC_RESUMEN | E15: 20140101 | F15: 22000101 | G15: 1,2,3,4,5,6,7,8,9,10,11,12 | H15: 3,6,9,12 | I15: pdf | J15: COLC
A16: 3 | B16: 8.2 | C16: W-O - Incentivos por Cumplimiento de Objetivos y Liquidación a Cuenta Detalle | D16: INYC_COLC_DETALLE | E16: 20140101 | F16: 20151001 | J16: OBSOLETO
A17: 3 | B17: 9.1 | C17: W-O - Compensación por Transporte Resumen | D17: INYC_CT_RESUMEN | E17: 20140101 | F17: 20151001 | J17: OBSOLETO
A18: 3 | B18: 9.2 | C18: W-O - Compensación por Transporte Detalle | D18: INYC_CT_DETALLE | E18: 20140101 | F18: 20151001 | J18: OBSOLETO
A19: 3 | B19: 10.1 | C19: W-O - Rappel Defensa Cartera Resumen | D19: INYC_RDC_RESUMEN | E19: 20140101 | F19: 22000101 | G19: 1,2,3,4,5,6,7,8,9,10,11,12 | H19: 1,2,3,4,5,6,7,8,9,10,11,12 | I19: pdf | J19: RDC
A20: 3 | B20: 10.2 | C20: W-O - Rappel Defensa Cartera Detalle | D20: INYC_RDC_DETALLE | E20: 20140101 | F20: 22000101 | G20: 1,2,3,4,5,6,7,8,9,10,11,12 | H20: 1,2,3,4,5,6,7,8,9,10,11,12 | I20: excel | J20: RDC
A21: 3 | B21: 11.1 | C21: W-O - Incentivo Rappel Especial Pre-Plan Resumen | D21: INYC_IPP_RESUMEN | E21: 20140101 | F21: 20170101 | J21: OBSOLETO
A22: 3 | B22: 12.1 | C22: W-O - Anulaciones de Primer Año Resumen | D22: INYC_AN1_RESUMEN | E22: 20170101 | F22: 22000101 | G22: 12 | H22: 12 | I22: pdf | J22: AN
A23: 3 | B23: 12.2 | C23: W-O - Anulaciones de Segundo Año Resumen | D23: INYC_AN2_RESUMEN | E23: 20170101 | F23: 22000101 | G23: 12 | H23: 12 | I23: pdf | J23: AN
A24: 3 | B24: 13.1 | C24: W-E - Diferenciales Resumen | D24: INYC_DIF_E_RESUMEN | E24: 20140101 | F24: 22000101 | G24: 1,2,3,4,5,6,7,8,9,10,11,12 | H24: 1,2,3,4,5,6,7,8,9,10,11,12 | I24: pdf | J24: DIF_E
A25: 3 | B25: 13.2 | C25: W-E - Diferenciales Detalle | D25: INYC_DIF_E_DETALLE | E25: 20140101 | F25: 20180101 | G25: 1,2,3,4,5,6,7,8,9,10,11,12 | H25: 1,2,3,4,5,6,7,8,9,10,11,12 | I25: excel | J25: DIF_E_DETALLE
A26: 3 | B26: 14.1 | C26: W-O - Producción Propia Agentes con Grupo Resumen | D26: INYC_PP_RESUMEN | E26: 20140101 | F26: 22000101 | G26: 1,2,3,4,5,6,7,8,9,10,11,12 | H26: 3,4,5,6,7,8,9,10,11,12 | I26: pdf | J26: PP
A27: 3 | B27: 14.2 | C27: W-O - Producción Propia Agentes con Grupo Detalle | D27: INYC_PP_DETALLE | E27: 20200101 | F27: 22000101 | G27: 1,2,3,4,5,6,7,8,9,10,11,12 | H27: 3,4,5,6,7,8,9,10,11,12 | I27: pdf | J27: PP
A28: 3 | B28: 15.1 | C28: W-O - Rappel Incremento de Prima y Pólizas | D28: INYC_RIN_RESUMEN | E28: 20140101 | F28: 22000101 | G28: 1.12 | H28: 1 | I28: pdf | J28: RIP
A29: 3 | B29: 16.1 | C29: W-O - Financiación Agentes Plan de Carrera Resumen | D29: INYC_FIN_RESUMEN | E29: 20140101 | F29: 20180201 | G29: 1,2,3,4,5,6,7,8,9,10,11,12 | H29: 1,2,3,4,5,6,7,8,9,10,11,12 | I29: pdf | J29: FIN
A30: 4 | B30: 17.1 | C30: W-O - Rappel Especial Resumen | D30: INYC_RE_RESUMEN | E30: 20140101 | F30: 22000101 | G30: 1,2,3,4,5,6,7,8,9,10,11,12 | H30: 1,2,3,4,5,6,7,8,9,10,11,12 | I30: pdf | J30: RE
A31: 4 | B31: 17.2 | C31: W-O - Rappel Especial Detalle | D31: INYC_RE_DETALLE | E31: 20140101 | F31: 22000101 | G31: 1,2,3,4,5,6,7,8,9,10,11,12 | H31: 1,2,3,4,5,6,7,8,9,10,11,12 | I31: excel | J31: RE
A32: 4 | B32: 18.1 | C32: W-O - Producción Comunidades Resumen | D32: INYC_COMU_RESUMEN | E32: 20140101 | F32: 20180101 | G32: 1,2,3,4,5,6,7,8,9,10,11,12 | H32: 6,7,8,9,10,11,12 | I32: pdf | J32: COMU
A33: 4 | B33: 19.1 | C33: W-O - Rappel Asistencias Resumen | D33: INYC_ASI_RESUMEN | E33: 20140101 | F33: 22000101 | G33: 1,2,3,4,5,6,7,8,9,10,11,12 | H33: 1,2,3,4,5,6,7,8,9,10,11,12 | I33: pdf | J33: ASI
A34: SOP-PE000104 | B34: 19.2 | C34: W-O - Rappel Asistencias Detalle | D34: INYC_ASI_DETALLE | E34: 20140101 | F34: 22000101 | G34: 1,2,3,4,5,6,7,8,9,10,11,12 | H34: 1,2,3,4,5,6,7,8,9,10,11,12 | I34: excel | J34: ASI
A35: 4 | B35: 20.1 | C35: W-E - Rappel Asistencias Resumen | D35: INYC_ASI_E_RESUMEN | E35: 20140101 | F35: 22000101 | G35: 1,2,3,4,5,6,7,8,9,10,11,12 | H35: 1,2,3,4,5,6,7,8,9,10,11,12 | I35: pdf | J35: ASI_E
A36: SOP-PE000104 | B36: 20.2 | C36: W-E - Rappel Asistencias Detalle | D36: INYC_ASI_E_DETALLE | E36: 20140101 | F36: 22000101 | G36: 1,2,3,4,5,6,7,8,9,10,11,12 | H36: 1,2,3,4,5,6,7,8,9,10,11,12 | I36: excel | J36: ASI_E
A37: 4 | B37: 21.1 | C37: W-O - Rappel Acción Comercial Hogar Resumen | D37: INYC_RACH_RESUMEN | E37: 20140101 | F37: 22000101 | G37: 2,3,4,5,6,7,9 | H37: 2,3,4,5,6,7,9 | I37: pdf | J37: RACH
A38: 4 | B38: 22.1 | C38: W-O - Mínimos Garantizados Resumen | D38: INYC_MIN_RESUMEN | E38: 20140101 | F38: 22000101 | G38: 1,2,3,4,5,6,7,8,9,10,11,12 | H38: 1,2,3,4,5,6,7,8,9,10,11,12 | I38: pdf | J38: MIN
A39: 4 | B39: 23.1 | C39: W-O - Rappel Actividad Agentes con Grupo -Liquidación a Cuenta- Resumen | D39: INYC_REA_RESUMEN | E39: 20140101 | F39: 22000101 | G39: 1,2,3,4,5,6,7,8,9,10,11,12 | H39: 3,6,9,12 | I39: pdf | J39: REA
A40: 4 | B40: 24.1 | C40: W-O - Rappel Incremento Pólizas en Cartera Resumen | D40: INYC_RIP_RESUMEN | E40: 20140101 | F40: 22000101 | G40: 1,2,3,4,5,6,7,8,9,10,11,12 | H40: 1,2,3,4,5,6,7,8,9,10,11,12 | I40: pdf | J40: RIN
A41: 4 | B41: 25.1 | C41: W-O - Premios Marketing | D41: INYC_PMK_RESUMEN | E41: 20140101 | F41: 20180101 | G41: 12 | H41: 12 | I41: pdf | J41: OBSOLETO
A42: 4 | B42: 26.1 | C42: W-O - Rappel Especial por Cumplimiento de Objetivo de Anulaciones Resumen | D42: INYC_RECOA_RESUMEN | E42: 20140101 | F42: 20180101 | G42: 3,6,9,12 | H42: 3,6,9,12 | I42: pdf | J42: RECOA
A43: 0 | B43: 27.1 | C43: W-O - Captación Agentes Resumen | D43: INYC_CAP_RESUMEN | E43: 20180101 | F43: 22000101 | G43: 1,2,3,4,5,6,7,8,9,10,11,12 | H43: 1,2,3,4,5,6,7,8,9,10,11,12 | I43: pdf | J43: CAP
A44: 0 | B44: 28.1 | C44: W-E - Campaña Comercial EA | D44: INYC_CC_E_RESUMEN | E44: 20181001 | F44: 22000101 | G44: 10,11,12,1 | H44: 10,11,12,1 | I44: pdf | J44: CC_E
A45: 0 | B45: 29.1 | C45: W-O - Campaña Personales Ocaso Resumen | D45: INYC_CPP_RESUMEN | E45: 20181101 | F45: 22000101 | G45: 11.12 | H45: 11.12 | I45: pdf | J45: CPP
A46: 0 | B46: 29.2 | C46: W-O - Campaña Personales Ocaso Detalle | D46: INYC_CPP_DETALLE | E46: 20181101 | F46: 22000101 | G46: 11.12 | H46: 11.12 | I46: excel | J46: CPP
A47: 0 | B47: 30.1 | C47: W-E - Captación Agentes Resumen | D47: INYC_CAP_E_RESUMEN | E47: 20190101 | F47: 22000202 | G47: 1,2,3,4,5,6,7,8,9,10,11,12 | H47: 1,2,3,4,5,6,7,8,9,10,11,12 | I47: pdf | J47: CAP_E
A48: 0 | B48: 31.1 | C48: W-E - Objetivos Agentes Grupo | D48: INYC_OBJ_E_RESUMEN | E48: 20190101 | F48: 22000202 | G48: 1,2,3,4,5,6,7,8,9,10,11,12 | H48: 1,2,3,4,5,6,7,8,9,10,11,12 | I48: pdf | J48: OBJ_E
A49: 0 | B49: 32.1 | C49: W-O - Rappel Producción Propia Ag. Grupo Resumen | D49: INYC_RPP_RESUMEN | E49: 20200601 | F49: 22000101 | G49: 1,2,3,4,5,6,7,8,9,10,11,12 | H49: 1,2,3,4,5,6,7,8,9,10,11,12 | I49: pdf | J49: RPP
A50: 0 | B50: 32.2 | C50: W-O - Rappel Producción Propia Ag. Grupo Detalle | D50: INYC_RPP_DETALLE | E50: 20200601 | F50: 20200101 | G50: 1,2,3,4,5,6,7,8,9,10,11,12 | H50: 1,2,3,4,5,6,7,8,9,10,11,12 | I50: excel | J50: RPP
A51: 0 | B51: 100.1 | C51: W-O - S4 Factura | D51: INYC_S4_FACTURA | E51: 20140101 | F51: 22000101 | G51: 1,2,3,4,5,6,7,8,9,10,11,12 | H51: 1,2,3,4,5,6,7,8,9,10,11,12 | I51: pdf | J51: S4
A52: 0 | B52: 100.2 | C52: W-O - S4 Detalle Pólizas | D52: INYC_S4_POLIZAS | E52: 20140101 | F52: 22000101 | G52: 1,2,3,4,5,6,7,8,9,10,11,12 | H52: 1,2,3,4,5,6,7,8,9,10,11,12 | I52: pdf | J52: S4
A53: 0 | B53: 100.3 | C53: W-O - S4 Detalle Productos | D53: INYC_S4_POLIZAS | E53: 20140101 | F53: 22000101 | G53: 1,2,3,4,5,6,7,8,9,10,11,12 | H53: 1,2,3,4,5,6,7,8,9,10,11,12 | I53: pdf | J53: S4
A54: 0 | B54: 101.1 | C54: W-O - S5 Factura | D54: INYC_S5_FACTURA | E54: 20140101 | F54: 22000101 | G54: 1,2,3,4,5,6,7,8,9,10,11,12 | H54: 1,2,3,4,5,6,7,8,9,10,11,12 | I54: pdf | J54: S5
A55: 0 | B55: 101.2 | C55: W-O - S5 Detalle Pólizas | D55: INYC_S5_POLIZAS | E55: 20140101 | F55: 22000101 | G55: 1,2,3,4,5,6,7,8,9,10,11,12 | H55: 1,2,3,4,5,6,7,8,9,10,11,12 | I55: pdf | J55: S5
A56: 0 | B56: 101.3 | C56: W-O - S5 Detalle Productos | D56: INYC_S5_POLIZAS | E56: 20140101 | F56: 22000101 | G56: 1,2,3,4,5,6,7,8,9,10,11,12 | H56: 1,2,3,4,5,6,7,8,9,10,11,12 | I56: pdf | J56: S5
A57: 0 | B57: 102.1 | C57: W-E - S4 Factura | D57: INYC_S4_E_FACTURA | E57: 20140101 | F57: 22000101 | G57: 1,2,3,4,5,6,7,8,9,10,11,12 | H57: 1,2,3,4,5,6,7,8,9,10,11,12 | I57: pdf | J57: S4_E
A58: 0 | B58: 102.2 | C58: W-E - S4 Detalle Pólizas | D58: INYC_S4_E_POLIZAS | E58: 20140101 | F58: 22000101 | G58: 1,2,3,4,5,6,7,8,9,10,11,12 | H58: 1,2,3,4,5,6,7,8,9,10,11,12 | I58: pdf | J58: S4_E
... A85: 0 | B85: 25.1 | C85: W-O - Incentivos Inspectores Comerciales | D85: INYC_RPI_RESUMEN | E85: 20140101 | F85: 22000101 | G85: DIARIO | H85: DIARIO | I85: pdf | J85: PEPI

Sheet INSERT INFORMES
A1: =IF(INFORMES!J2="OBSOLETO","","INSERT INTO INYCEXT.INYC_CONF_INFORMES (COD_INFORME,DESC_INFORME,TABLA,F_INICIO,F_FIN,CARGA_TABLAS,PUBLICACION,FORMATO,DESCRIPCION) VALUES ("&INFORMES!B2&",'"&INFORMES!C2&"','"&INFORMES!D2&"',TO_DATE('"&INFORMES!E2&"','yyyymmdd'),TO_DATE('"&INFORMES!F2&"','yyyymmdd'),'"&INFORMES!G2&"','"&INFORMES!H2&"','"&INFORMES!I2&"','"&INFORMES!J2&"');") -> INSERT INTO INYCEXT.INYC_CONF_INFORMES (COD_INFORME,DESC_INFORME,TABLA,F_INICIO,F_FIN,CARGA_TABLAS,PUBLICACION,FORMATO,DESCRIPCION) VALUES (1.1,'W-O - Rappel por Producción Resumen','INYC_RPI_RESUMEN',TO_DATE('20140101','yyyymmdd'),TO_DATE('22000101','yyyymmdd'),'1,2,3,4,5,6,7,8,9,10,11,12','1,2,3,4,5,6,7,8,9,10,11,12','pdf','RPI'); | B1: =IF(INFORMES!J2="OBSOLETO","","INSERT INTO INYCEXT.INYC_CONF_INFORMES@tc_link (COD_INFORME,DESC_INFORME,TABLA,F_INICIO,F_FIN,CARGA_TABLAS,PUBLICACION,FORMATO,DESCRIPCION) VALUES ("&INFORMES!B2&",'"&INFORMES!C2&"','"&INFORMES!D2&"',TO_DATE('"&INFORMES!E2&"','yyyymmdd'),TO_DATE('"&INFORMES!F2&"','yyyymmdd'),'"&INFORMES!G2&"','"&INFORMES!H2&"','"&INFORMES!I2&"','"&INFORMES!J2&"');") -> INSERT INTO INYCEXT.INYC_CONF_INFORMES@tc_link (COD_INFORME,DESC_INFORME,TABLA,F_INICIO,F_FIN,CARGA_TABLAS,PUBLICACION,FORMATO,DESCRIPCION) VALUES (1.1,'W-O - Rappel por Producción Resumen','INYC_RPI_RESUMEN',TO_DATE('20140101','yyyymmdd'),TO_DATE('22000101','yyyymmdd'),'1,2,3,4,5,6,7,8,9,10,11,12','1,2,3,4,5,6,7,8,9,10,11,12','pdf','RPI');
A2: =IF(INFORMES!J3="OBSOLETO","","INSERT INTO INYCEXT.INYC_CONF_INFORMES (COD_INFORME,DESC_INFORME,TABLA,F_INICIO,F_FIN,CARGA_TABLAS,PUBLICACION,FORMATO,DESCRIPCION) VALUES ("&INFORMES!B3&",'"&INFORMES!C3&"','"&INFORMES!D3&"',TO_DATE('"&INFORMES!E3&"','yyyymmdd'),TO_DATE('"&INFORMES!F3&"','yyyymmdd'),'"&INFORMES!G3&"','"&INFORMES!H3&"','"&INFORMES!I3&"','"&INFORMES!J3&"');") -> INSERT INTO INYCEXT.INYC_CONF_INFORMES (COD_INFORME,DESC_INFORME,TABLA,F_INICIO,F_FIN,CARGA_TABLAS,PUBLICACION,FORMATO,DESCRIPCION) VALUES (1.2,'W-O - Rappel por Producción Detalle','INYC_RPI_DETALLE',TO_DATE('20140101','yyyymmdd'),TO_DATE('20180101','yyyymmdd'),'1,2,3,4,5,6,7,8,9,10,11,12','1,2,3,4,5,6,7,8,9,10,11,12','excel','RPI_DETALLE'); | B2: =IF(INFORMES!J3="OBSOLETO","","INSERT INTO INYCEXT.INYC_CONF_INFORMES@tc_link (COD_INFORME,DESC_INFORME,TABLA,F_INICIO,F_FIN,CARGA_TABLAS,PUBLICACION,FORMATO,DESCRIPCION) VALUES ("&INFORMES!B3&",'"&INFORMES!C3&"','"&INFORMES!D3&"',TO_DATE('"&INFORMES!E3&"','yyyymmdd'),TO_DATE('"&INFORMES!F3&"','yyyymmdd'),'"&INFORMES!G3&"','"&INFORMES!H3&"','"&INFORMES!I3&"','"&INFORMES!J3&"');") -> INSERT INTO INYCEXT.INYC_CONF_INFORMES@tc_link (COD_INFORME,DESC_INFORME,TABLA,F_INICIO,F_FIN,CARGA_TABLAS,PUBLICACION,FORMATO,DESCRIPCION) VALUES (1.2,'W-O - Rappel por Producción Detalle','INYC_RPI_DETALLE',TO_DATE('20140101','yyyymmdd'),TO_DATE('20180101','yyyymmdd'),'1,2,3,4,5,6,7,8,9,10,11,12','1,2,3,4,5,6,7,8,9,10,11,12','excel','RPI_DETALLE');
A3: =IF(INFORMES!J4="OBSOLETO","","INSERT INTO INYCEXT.INYC_CONF_INFORMES (COD_INFORME,DESC_INFORME,TABLA,F_INICIO,F_FIN,CARGA_TABLAS,PUBLICACION,FORMATO,DESCRIPCION) VALUES ("&INFORMES!B4&",'"&INFORMES!C4&"','"&INFORMES!D4&"',TO_DATE('"&INFORMES!E4&"','yyyymmdd'),TO_DATE('"&INFORMES!F4&"','yyyymmdd'),'"&INFORMES!G4&"','"&INFORMES!H4&"','"&INFORMES!I4&"','"&INFORMES!J4&"');") -> INSERT INTO INYCEXT.INYC_CONF_INFORMES (COD_INFORME,DESC_INFORME,TABLA,F_INICIO,F_FIN,CARGA_TABLAS,PUBLICACION,FORMATO,DESCRIPCION) VALUES (2.1,'W-E - Rappel por Producción Resumen','INYC_RAG_RESUMEN',TO_DATE('20140101','yyyymmdd'),TO_DATE('22000101','yyyymmdd'),'1,2,3,4,5,6,7,8,9,10,11,12','1,2,3,4,5,6,7,8,9,10,11,12','pdf','RAG'); | B3: =IF(INFORMES!J4="OBSOLETO","","INSERT INTO INYCEXT.INYC_CONF_INFORMES@tc_link (COD_INFORME,DESC_INFORME,TABLA,F_INICIO,F_FIN,CARGA_TABLAS,PUBLICACION,FORMATO,DESCRIPCION) VALUES ("&INFORMES!B4&",'"&INFORMES!C4&"','"&INFORMES!D4&"',TO_DATE('"&INFORMES!E4&"','yyyymmdd'),TO_DATE('"&INFORMES!F4&"','yyyymmdd'),'"&INFORMES!G4&"','"&INFORMES!H4&"','"&INFORMES!I4&"','"&INFORMES!J4&"');") -> INSERT INTO INYCEXT.INYC_CONF_INFORMES@tc_link (COD_INFORME,DESC_INFORME,TABLA,F_INICIO,F_FIN,CARGA_TABLAS,PUBLICACION,FORMATO,DESCRIPCION) VALUES (2.1,'W-E - Rappel por Producción Resumen','INYC_RAG_RESUMEN',TO_DATE('20140101','yyyymmdd'),TO_DATE('22000101','yyyymmdd'),'1,2,3,4,5,6,7,8,9,10,11,12','1,2,3,4,5,6,7,8,9,10,11,12','pdf','RAG');
A4: =IF(INFORMES!J5="OBSOLETO","","INSERT INTO INYCEXT.INYC_CONF_INFORMES (COD_INFORME,DESC_INFORME,TABLA,F_INICIO,F_FIN,CARGA_TABLAS,PUBLICACION,FORMATO,DESCRIPCION) VALUES ("&INFORMES!B5&",'"&INFORMES!C5&"','"&INFORMES!D5&"',TO_DATE('"&INFORMES!E5&"','yyyymmdd'),TO_DATE('"&INFORMES!F5&"','yyyymmdd'),'"&INFORMES!G5&"','"&INFORMES!H5&"','"&INFORMES!I5&"','"&INFORMES!J5&"');") -> INSERT INTO INYCEXT.INYC_CONF_INFORMES (COD_INFORME,DESC_INFORME,TABLA,F_INICIO,F_FIN,CARGA_TABLAS,PUBLICACION,FORMATO,DESCRIPCION) VALUES (2.2,'W-E - Rappel por Producción Detalle','INYC_RAG_DETALLE',TO_DATE('20140101','yyyymmdd'),TO_DATE('20180101','yyyymmdd'),'1,2,3,4,5,6,7,8,9,10,11,12','1,2,3,4,5,6,7,8,9,10,11,12','excel','RAG_DETALLE'); | B4: =IF(INFORMES!J5="OBSOLETO","","INSERT INTO INYCEXT.INYC_CONF_INFORMES@tc_link (COD_INFORME,DESC_INFORME,TABLA,F_INICIO,F_FIN,CARGA_TABLAS,PUBLICACION,FORMATO,DESCRIPCION) VALUES ("&INFORMES!B5&",'"&INFORMES!C5&"','"&INFORMES!D5&"',TO_DATE('"&INFORMES!E5&"','yyyymmdd'),TO_DATE('"&INFORMES!F5&"','yyyymmdd'),'"&INFORMES!G5&"','"&INFORMES!H5&"','"&INFORMES!I5&"','"&INFORMES!J5&"');") -> INSERT INTO INYCEXT.INYC_CONF_INFORMES@tc_link (COD_INFORME,DESC_INFORME,TABLA,F_INICIO,F_FIN,CARGA_TABLAS,PUBLICACION,FORMATO,DESCRIPCION) VALUES (2.2,'W-E - Rappel por Producción Detalle','INYC_RAG_DETALLE',TO_DATE('20140101','yyyymmdd'),TO_DATE('20180101','yyyymmdd'),'1,2,3,4,5,6,7,8,9,10,11,12','1,2,3,4,5,6,7,8,9,10,11,12','excel','RAG_DETALLE');
A5: =IF(INFORMES!J6="OBSOLETO","","INSERT INTO INYCEXT.INYC_CONF_INFORMES (COD_INFORME,DESC_INFORME,TABLA,F_INICIO,F_FIN,CARGA_TABLAS,PUBLICACION,FORMATO,DESCRIPCION) VALUES ("&INFORMES!B6&",'"&INFORMES!C6&"','"&INFORMES!D6&"',TO_DATE('"&INFORMES!E6&"','yyyymmdd'),TO_DATE('"&INFORMES!F6&"','yyyymmdd'),'"&INFORMES!G6&"','"&INFORMES!H6&"','"&INFORMES!I6&"','"&INFORMES!J6&"');") -> INSERT INTO INYCEXT.INYC_CONF_INFORMES (COD_INFORME,DESC_INFORME,TABLA,F_INICIO,F_FIN,CARGA_TABLAS,PUBLICACION,FORMATO,DESCRIPCION) VALUES (2.3,'W-E - Rappel por producción Trimestral Resumen','INYC_RAGT_RESUMEN',TO_DATE('20190101','yyyymmdd'),TO_DATE('22000101','yyyymmdd'),'1,2,3,4,5,6,7,8,9,10,11,12','1,2,3,4,5,6,7,8,9,10,11,12','pdf','RAGT'); | B5: =IF(INFORMES!J6="OBSOLETO","","INSERT INTO INYCEXT.INYC_CONF_INFORMES@tc_link (COD_INFORME,DESC_INFORME,TABLA,F_INICIO,F_FIN,CARGA_TABLAS,PUBLICACION,FORMATO,DESCRIPCION) VALUES ("&INFORMES!B6&",'"&INFORMES!C6&"','"&INFORMES!D6&"',TO_DATE('"&INFORMES!E6&"','yyyymmdd'),TO_DATE('"&INFORMES!F6&"','yyyymmdd'),'"&INFORMES!G6&"','"&INFORMES!H6&"','"&INFORMES!I6&"','"&INFORMES!J6&"');") -> INSERT INTO INYCEXT.INYC_CONF_INFORMES@tc_link (COD_INFORME,DESC_INFORME,TABLA,F_INICIO,F_FIN,CARGA_TABLAS,PUBLICACION,FORMATO,DESCRIPCION) VALUES (2.3,'W-E - Rappel por producción Trimestral Resumen','INYC_RAGT_RESUMEN',TO_DATE('20190101','yyyymmdd'),TO_DATE('22000101','yyyymmdd'),'1,2,3,4,5,6,7,8,9,10,11,12','1,2,3,4,5,6,7,8,9,10,11,12','pdf','RAGT');
A6: =IF(INFORMES!J7="OBSOLETO","","INSERT INTO INYCEXT.INYC_CONF_INFORMES (COD_INFORME,DESC_INFORME,TABLA,F_INICIO,F_FIN,CARGA_TABLAS,PUBLICACION,FORMATO,DESCRIPCION) VALUES ("&INFORMES!B7&",'"&INFORMES!C7&"','"&INFORMES!D7&"',TO_DATE('"&INFORMES!E7&"','yyyymmdd'),TO_DATE('"&INFORMES!F7&"','yyyymmdd'),'"&INFORMES!G7&"','"&INFORMES!H7&"','"&INFORMES!I7&"','"&INFORMES!J7&"');") -> INSERT INTO INYCEXT.INYC_CONF_INFORMES (COD_INFORME,DESC_INFORME,TABLA,F_INICIO,F_FIN,CARGA_TABLAS,PUBLICACION,FORMATO,DESCRIPCION) VALUES (3.1,'W-E - Rappel Producción Agentes Resumen','INYC_RA_RESUMEN',TO_DATE('20140101','yyyymmdd'),TO_DATE('22000101','yyyymmdd'),'1,2,3,4,5,6,7,8,9,10,11,12','1,2,3,4,5,6,7,8,9,10,11,12','pdf','RA'); | B6: =IF(INFORMES!J7="OBSOLETO","","INSERT INTO INYCEXT.INYC_CONF_INFORMES@tc_link (COD_INFORME,DESC_INFORME,TABLA,F_INICIO,F_FIN,CARGA_TABLAS,PUBLICACION,FORMATO,DESCRIPCION) VALUES ("&INFORMES!B7&",'"&INFORMES!C7&"','"&INFORMES!D7&"',TO_DATE('"&INFORMES!E7&"','yyyymmdd'),TO_DATE('"&INFORMES!F7&"','yyyymmdd'),'"&INFORMES!G7&"','"&INFORMES!H7&"','"&INFORMES!I7&"','"&INFORMES!J7&"');") -> INSERT INTO INYCEXT.INYC_CONF_INFORMES@tc_link (COD_INFORME,DESC_INFORME,TABLA,F_INICIO,F_FIN,CARGA_TABLAS,PUBLICACION,FORMATO,DESCRIPCION) VALUES (3.1,'W-E - Rappel Producción Agentes Resumen','INYC_RA_RESUMEN',TO_DATE('20140101','yyyymmdd'),TO_DATE('22000101','yyyymmdd'),'1,2,3,4,5,6,7,8,9,10,11,12','1,2,3,4,5,6,7,8,9,10,11,12','pdf','RA');
A7: =IF(INFORMES!J8="OBSOLETO","","INSERT INTO INYCEXT.INYC_CONF_INFORMES (COD_INFORME,DESC_INFORME,TABLA,F_INICIO,F_FIN,CARGA_TABLAS,PUBLICACION,FORMATO,DESCRIPCION) VALUES ("&INFORMES!B8&",'"&INFORMES!C8&"','"&INFORMES!D8&"',TO_DATE('"&INFORMES!E8&"','yyyymmdd'),TO_DATE('"&INFORMES!F8&"','yyyymmdd'),'"&INFORMES!G8&"','"&INFORMES!H8&"','"&INFORMES!I8&"','"&INFORMES!J8&"');") -> INSERT INTO INYCEXT.INYC_CONF_INFORMES (COD_INFORME,DESC_INFORME,TABLA,F_INICIO,F_FIN,CARGA_TABLAS,PUBLICACION,FORMATO,DESCRIPCION) VALUES (3.2,'W-E - Rappel Producción Agentes Detalle','INYC_RA_DETALLE',TO_DATE('20140101','yyyymmdd'),TO_DATE('22000101','yyyymmdd'),'1,2,3,4,5,6,7,8,9,10,11,12','1,2,3,4,5,6,7,8,9,10,11,12','excel','RA'); | B7: =IF(INFORMES!J8="OBSOLETO","","INSERT INTO INYCEXT.INYC_CONF_INFORMES@tc_link (COD_INFORME,DESC_INFORME,TABLA,F_INICIO,F_FIN,CARGA_TABLAS,PUBLICACION,FORMATO,DESCRIPCION) VALUES ("&INFORMES!B8&",'"&INFORMES!C8&"','"&INFORMES!D8&"',TO_DATE('"&INFORMES!E8&"','yyyymmdd'),TO_DATE('"&INFORMES!F8&"','yyyymmdd'),'"&INFORMES!G8&"','"&INFORMES!H8&"','"&INFORMES!I8&"','"&INFORMES!J8&"');") -> INSERT INTO INYCEXT.INYC_CONF_INFORMES@tc_link (COD_INFORME,DESC_INFORME,TABLA,F_INICIO,F_FIN,CARGA_TABLAS,PUBLICACION,FORMATO,DESCRIPCION) VALUES (3.2,'W-E - Rappel Producción Agentes Detalle','INYC_RA_DETALLE',TO_DATE('20140101','yyyymmdd'),TO_DATE('22000101','yyyymmdd'),'1,2,3,4,5,6,7,8,9,10,11,12','1,2,3,4,5,6,7,8,9,10,11,12','excel','RA');
A8: =IF(INFORMES!J9="OBSOLETO","","INSERT INTO INYCEXT.INYC_CONF_INFORMES (COD_INFORME,DESC_INFORME,TABLA,F_INICIO,F_FIN,CARGA_TABLAS,PUBLICACION,FORMATO,DESCRIPCION) VALUES ("&INFORMES!B9&",'"&INFORMES!C9&"','"&INFORMES!D9&"',TO_DATE('"&INFORMES!E9&"','yyyymmdd'),TO_DATE('"&INFORMES!F9&"','yyyymmdd'),'"&INFORMES!G9&"','"&INFORMES!H9&"','"&INFORMES!I9&"','"&INFORMES!J9&"');") -> INSERT INTO INYCEXT.INYC_CONF_INFORMES (COD_INFORME,DESC_INFORME,TABLA,F_INICIO,F_FIN,CARGA_TABLAS,PUBLICACION,FORMATO,DESCRIPCION) VALUES (4.1,'W-E - Ranking Concurso de Producción Anual','INYC_CONCURSO',TO_DATE('20140101','yyyymmdd'),TO_DATE('22000101','yyyymmdd'),'12','12','pdf','CONCURSO'); | B8: =IF(INFORMES!J9="OBSOLETO","","INSERT INTO INYCEXT.INYC_CONF_INFORMES@tc_link (COD_INFORME,DESC_INFORME,TABLA,F_INICIO,F_FIN,CARGA_TABLAS,PUBLICACION,FORMATO,DESCRIPCION) VALUES ("&INFORMES!B9&",'"&INFORMES!C9&"','"&INFORMES!D9&"',TO_DATE('"&INFORMES!E9&"','yyyymmdd'),TO_DATE('"&INFORMES!F9&"','yyyymmdd'),'"&INFORMES!G9&"','"&INFORMES!H9&"','"&INFORMES!I9&"','"&INFORMES!J9&"');") -> INSERT INTO INYCEXT.INYC_CONF_INFORMES@tc_link (COD_INFORME,DESC_INFORME,TABLA,F_INICIO,F_FIN,CARGA_TABLAS,PUBLICACION,FORMATO,DESCRIPCION) VALUES (4.1,'W-E - Ranking Concurso de Producción Anual','INYC_CONCURSO',TO_DATE('20140101','yyyymmdd'),TO_DATE('22000101','yyyymmdd'),'12','12','pdf','CONCURSO');
A9: =IF(INFORMES!J10="OBSOLETO","","INSERT INTO INYCEXT.INYC_CONF_INFORMES (COD_INFORME,DESC_INFORME,TABLA,F_INICIO,F_FIN,CARGA_TABLAS,PUBLICACION,FORMATO,DESCRIPCION) VALUES ("&INFORMES!B10&",'"&INFORMES!C10&"','"&INFORMES!D10&"',TO_DATE('"&INFORMES!E10&"','yyyymmdd'),TO_DATE('"&INFORMES!F10&"','yyyymmdd'),'"&INFORMES!G10&"','"&INFORMES!H10&"','"&INFORMES!I10&"','"&INFORMES!J10&"');") -> INSERT INTO INYCEXT.INYC_CONF_INFORMES (COD_INFORME,DESC_INFORME,TABLA,F_INICIO,F_FIN,CARGA_TABLAS,PUBLICACION,FORMATO,DESCRIPCION) VALUES (5.1,'W-E - Incentivo Especial Anual','INYC_INCENTIVO',TO_DATE('20140101','yyyymmdd'),TO_DATE('22000101','yyyymmdd'),'12','12','pdf','INCENTIVO'); | B9: =IF(INFORMES!J10="OBSOLETO","","INSERT INTO INYCEXT.INYC_CONF_INFORMES@tc_link (COD_INFORME,DESC_INFORME,TABLA,F_INICIO,F_FIN,CARGA_TABLAS,PUBLICACION,FORMATO,DESCRIPCION) VALUES ("&INFORMES!B10&",'"&INFORMES!C10&"','"&INFORMES!D10&"',TO_DATE('"&INFORMES!E10&"','yyyymmdd'),TO_DATE('"&INFORMES!F10&"','yyyymmdd'),'"&INFORMES!G10&"','"&INFORMES!H10&"','"&INFORMES!I10&"','"&INFORMES!J10&"');") -> INSERT INTO INYCEXT.INYC_CONF_INFORMES@tc_link (COD_INFORME,DESC_INFORME,TABLA,F_INICIO,F_FIN,CARGA_TABLAS,PUBLICACION,FORMATO,DESCRIPCION) VALUES (5.1,'W-E - Incentivo Especial Anual','INYC_INCENTIVO',TO_DATE('20140101','yyyymmdd'),TO_DATE('22000101','yyyymmdd'),'12','12','pdf','INCENTIVO');
A10: =IF(INFORMES!J11="OBSOLETO","","INSERT INTO INYCEXT.INYC_CONF_INFORMES (COD_INFORME,DESC_INFORME,TABLA,F_INICIO,F_FIN,CARGA_TABLAS,PUBLICACION,FORMATO,DESCRIPCION) VALUES ("&INFORMES!B11&",'"&INFORMES!C11&"','"&INFORMES!D11&"',TO_DATE('"&INFORMES!E11&"','yyyymmdd'),TO_DATE('"&INFORMES!F11&"','yyyymmdd'),'"&INFORMES!G11&"','"&INFORMES!H11&"','"&INFORMES!I11&"','"&INFORMES!J11&"');") -> INSERT INTO INYCEXT.INYC_CONF_INFORMES (COD_INFORME,DESC_INFORME,TABLA,F_INICIO,F_FIN,CARGA_TABLAS,PUBLICACION,FORMATO,DESCRIPCION) VALUES (6.1,'W-O - Rappel Producción Agentes Resumen','INYC_RPA_RESUMEN',TO_DATE('20140101','yyyymmdd'),TO_DATE('22000101','yyyymmdd'),'1,2,3,4,5,6,7,8,9,10,11,12','1,2,3,4,5,6,7,8,9,10,11,12','pdf','RPA'); | B10: =IF(INFORMES!J11="OBSOLETO","","INSERT INTO INYCEXT.INYC_CONF_INFORMES@tc_link (COD_INFORME,DESC_INFORME,TABLA,F_INICIO,F_FIN,CARGA_TABLAS,PUBLICACION,FORMATO,DESCRIPCION) VALUES ("&INFORMES!B11&",'"&INFORMES!C11&"','"&INFORMES!D11&"',TO_DATE('"&INFORMES!E11&"','yyyymmdd'),TO_DATE('"&INFORMES!F11&"','yyyymmdd'),'"&INFORMES!G11&"','"&INFORMES!H11&"','"&INFORMES!I11&"','"&INFORMES!J11&"');") -> INSERT INTO INYCEXT.INYC_CONF_INFORMES@tc_link (COD_INFORME,DESC_INFORME,TABLA,F_INICIO,F_FIN,CARGA_TABLAS,PUBLICACION,FORMATO,DESCRIPCION) VALUES (6.1,'W-O - Rappel Producción Agentes Resumen','INYC_RPA_RESUMEN',TO_DATE('20140101','yyyymmdd'),TO_DATE('22000101','yyyymmdd'),'1,2,3,4,5,6,7,8,9,10,11,12','1,2,3,4,5,6,7,8,9,10,11,12','pdf','RPA');
A11: =IF(INFORMES!J12="OBSOLETO","","INSERT INTO INYCEXT.INYC_CONF_INFORMES (COD_INFORME,DESC_INFORME,TABLA,F_INICIO,F_FIN,CARGA_TABLAS,PUBLICACION,FORMATO,DESCRIPCION) VALUES ("&INFORMES!B12&",'"&INFORMES!C12&"','"&INFORMES!D12&"',TO_DATE('"&INFORMES!E12&"','yyyymmdd'),TO_DATE('"&INFORMES!F12&"','yyyymmdd'),'"&INFORMES!G12&"','"&INFORMES!H12&"','"&INFORMES!I12&"','"&INFORMES!J12&"');") -> INSERT INTO INYCEXT.INYC_CONF_INFORMES (COD_INFORME,DESC_INFORME,TABLA,F_INICIO,F_FIN,CARGA_TABLAS,PUBLICACION,FORMATO,DESCRIPCION) VALUES (6.2,'W-O - Rappel Producción Agentes Detalle','INYC_RPA_DETALLE',TO_DATE('20140101','yyyymmdd'),TO_DATE('22000101','yyyymmdd'),'1,2,3,4,5,6,7,8,9,10,11,12','1,2,3,4,5,6,7,8,9,10,11,12','excel','RPA'); | B11: =IF(INFORMES!J12="OBSOLETO","","INSERT INTO INYCEXT.INYC_CONF_INFORMES@tc_link (COD_INFORME,DESC_INFORME,TABLA,F_INICIO,F_FIN,CARGA_TABLAS,PUBLICACION,FORMATO,DESCRIPCION) VALUES ("&INFORMES!B12&",'"&INFORMES!C12&"','"&INFORMES!D12&"',TO_DATE('"&INFORMES!E12&"','yyyymmdd'),TO_DATE('"&INFORMES!F12&"','yyyymmdd'),'"&INFORMES!G12&"','"&INFORMES!H12&"','"&INFORMES!I12&"','"&INFORMES!J12&"');") -> INSERT INTO INYCEXT.INYC_CONF_INFORMES@tc_link (COD_INFORME,DESC_INFORME,TABLA,F_INICIO,F_FIN,CARGA_TABLAS,PUBLICACION,FORMATO,DESCRIPCION) VALUES (6.2,'W-O - Rappel Producción Agentes Detalle','INYC_RPA_DETALLE',TO_DATE('20140101','yyyymmdd'),TO_DATE('22000101','yyyymmdd'),'1,2,3,4,5,6,7,8,9,10,11,12','1,2,3,4,5,6,7,8,9,10,11,12','excel','RPA');
A12: =IF(INFORMES!J13="OBSOLETO","","INSERT INTO INYCEXT.INYC_CONF_INFORMES (COD_INFORME,DESC_INFORME,TABLA,F_INICIO,F_FIN,CARGA_TABLAS,PUBLICACION,FORMATO,DESCRIPCION) VALUES ("&INFORMES!B13&",'"&INFORMES!C13&"','"&INFORMES!D13&"',TO_DATE('"&INFORMES!E13&"','yyyymmdd'),TO_DATE('"&INFORMES!F13&"','yyyymmdd'),'"&INFORMES!G13&"','"&INFORMES!H13&"','"&INFORMES!I13&"','"&INFORMES!J13&"');") -> INSERT INTO INYCEXT.INYC_CONF_INFORMES (COD_INFORME,DESC_INFORME,TABLA,F_INICIO,F_FIN,CARGA_TABLAS,PUBLICACION,FORMATO,DESCRIPCION) VALUES (7.1,'W-O - Diferenciales Resumen','INYC_DIF_RESUMEN',TO_DATE('20140101','yyyymmdd'),TO_DATE('22000101','yyyymmdd'),'1,2,3,4,5,6,7,8,9,10,11,12','1,2,3,4,5,6,7,8,9,10,11,12','pdf','DIF'); | B12: =IF(INFORMES!J13="OBSOLETO","","INSERT INTO INYCEXT.INYC_CONF_INFORMES@tc_link (COD_INFORME,DESC_INFORME,TABLA,F_INICIO,F_FIN,CARGA_TABLAS,PUBLICACION,FORMATO,DESCRIPCION) VALUES ("&INFORMES!B13&",'"&INFORMES!C13&"','"&INFORMES!D13&"',TO_DATE('"&INFORMES!E13&"','yyyymmdd'),TO_DATE('"&INFORMES!F13&"','yyyymmdd'),'"&INFORMES!G13&"','"&INFORMES!H13&"','"&INFORMES!I13&"','"&INFORMES!J13&"');") -> INSERT INTO INYCEXT.INYC_CONF_INFORMES@tc_link (COD_INFORME,DESC_INFORME,TABLA,F_INICIO,F_FIN,CARGA_TABLAS,PUBLICACION,FORMATO,DESCRIPCION) VALUES (7.1,'W-O - Diferenciales Resumen','INYC_DIF_RESUMEN',TO_DATE('20140101','yyyymmdd'),TO_DATE('22000101','yyyymmdd'),'1,2,3,4,5,6,7,8,9,10,11,12','1,2,3,4,5,6,7,8,9,10,11,12','pdf','DIF');
... A80: =IF(INFORMES!J81="OBSOLETO","","INSERT INTO INYCEXT.INYC_CONF_INFORMES (COD_INFORME,DESC_INFORME,TABLA,F_INICIO,F_FIN,CARGA_TABLAS,PUBLICACION,FORMATO,DESCRIPCION) VALUES ("&INFORMES!B81&",'"&INFORMES!C81&"','"&INFORMES!D81&"',TO_DATE('"&INFORMES!E81&"','yyyymmdd'),TO_DATE('"&INFORMES!F81&"','yyyymmdd'),'"&INFORMES!G81&"','"&INFORMES!H81&"','"&INFORMES!I81&"','"&INFORMES!J81&"');") -> INSERT INTO INYCEXT.INYC_CONF_INFORMES (COD_INFORME,DESC_INFORME,TABLA,F_INICIO,F_FIN,CARGA_TABLAS,PUBLICACION,FORMATO,DESCRIPCION) VALUES (33.2,'W-O - Gestiones Explotacion Detalle','INYC_GES_DETALLE',TO_DATE('20220501','yyyymmdd'),TO_DATE('20200101','yyyymmdd'),'1,2,3,4,5,6,7,8,9,10,11,12','1,2,3,4,5,6,7,8,9,10,11,12','excel','GEX'); | B80: =IF(INFORMES!J81="OBSOLETO","","INSERT INTO INYCEXT.INYC_CONF_INFORMES@tc_link (COD_INFORME,DESC_INFORME,TABLA,F_INICIO,F_FIN,CARGA_TABLAS,PUBLICACION,FORMATO,DESCRIPCION) VALUES ("&INFORMES!B81&",'"&INFORMES!C81&"','"&INFORMES!D81&"',TO_DATE('"&INFORMES!E81&"','yyyymmdd'),TO_DATE('"&INFORMES!F81&"','yyyymmdd'),'"&INFORMES!G81&"','"&INFORMES!H81&"','"&INFORMES!I81&"','"&INFORMES!J81&"');") -> INSERT INTO INYCEXT.INYC_CONF_INFORMES@tc_link (COD_INFORME,DESC_INFORME,TABLA,F_INICIO,F_FIN,CARGA_TABLAS,PUBLICACION,FORMATO,DESCRIPCION) VALUES (33.2,'W-O - Gestiones Explotacion Detalle','INYC_GES_DETALLE',TO_DATE('20220501','yyyymmdd'),TO_DATE('20200101','yyyymmdd'),'1,2,3,4,5,6,7,8,9,10,11,12','1,2,3,4,5,6,7,8,9,10,11,12','excel','GEX');
A81: =IF(INFORMES!J82="OBSOLETO","","INSERT INTO INYCEXT.INYC_CONF_INFORMES (COD_INFORME,DESC_INFORME,TABLA,F_INICIO,F_FIN,CARGA_TABLAS,PUBLICACION,FORMATO,DESCRIPCION) VALUES ("&INFORMES!B82&",'"&INFORMES!C82&"','"&INFORMES!D82&"',TO_DATE('"&INFORMES!E82&"','yyyymmdd'),TO_DATE('"&INFORMES!F82&"','yyyymmdd'),'"&INFORMES!G82&"','"&INFORMES!H82&"','"&INFORMES!I82&"','"&INFORMES!J82&"');") -> INSERT INTO INYCEXT.INYC_CONF_INFORMES (COD_INFORME,DESC_INFORME,TABLA,F_INICIO,F_FIN,CARGA_TABLAS,PUBLICACION,FORMATO,DESCRIPCION) VALUES (3.3,'3.3 Percepciones Agentes Eterna','INYC_PERC_E_AGENTES',TO_DATE('20170101','yyyymmdd'),TO_DATE('22000101','yyyymmdd'),'DIARIO','DIARIO','excel','PEAG_E');
A82: =IF(INFORMES!J83="OBSOLETO","","INSERT INTO INYCEXT.INYC_CONF_INFORMES (COD_INFORME,DESC_INFORME,TABLA,F_INICIO,F_FIN,CARGA_TABLAS,PUBLICACION,FORMATO,DESCRIPCION) VALUES ("&INFORMES!B83&",'"&INFORMES!C83&"','"&INFORMES!D83&"',TO_DATE('"&INFORMES!E83&"','yyyymmdd'),TO_DATE('"&INFORMES!F83&"','yyyymmdd'),'"&INFORMES!G83&"','"&INFORMES!H83&"','"&INFORMES!I83&"','"&INFORMES!J83&"');") -> INSERT INTO INYCEXT.INYC_CONF_INFORMES (COD_INFORME,DESC_INFORME,TABLA,F_INICIO,F_FIN,CARGA_TABLAS,PUBLICACION,FORMATO,DESCRIPCION) VALUES (3.4,'3.4 Percepciones Inspectores Eterna','INYC_PERC_E_INSPECTORES',TO_DATE('20220101','yyyymmdd'),TO_DATE('22000101','yyyymmdd'),'DIARIO','DIARIO','excel','PEIN_E');
A83: =IF(INFORMES!J84="OBSOLETO","","INSERT INTO INYCEXT.INYC_CONF_INFORMES (COD_INFORME,DESC_INFORME,TABLA,F_INICIO,F_FIN,CARGA_TABLAS,PUBLICACION,FORMATO,DESCRIPCION) VALUES ("&INFORMES!B84&",'"&INFORMES!C84&"','"&INFORMES!D84&"',TO_DATE('"&INFORMES!E84&"','yyyymmdd'),TO_DATE('"&INFORMES!F84&"','yyyymmdd'),'"&INFORMES!G84&"','"&INFORMES!H84&"','"&INFORMES!I84&"','"&INFORMES!J84&"');") -> INSERT INTO INYCEXT.INYC_CONF_INFORMES (COD_INFORME,DESC_INFORME,TABLA,F_INICIO,F_FIN,CARGA_TABLAS,PUBLICACION,FORMATO,DESCRIPCION) VALUES (117.1,'1.17 Produccion Inspectores Eterna','INYC_PROD_E_INSPECTORES',TO_DATE('20220101','yyyymmdd'),TO_DATE('22000101','yyyymmdd'),'DIARIO','DIARIO','excel','PRIN_E');
A84: =IF(INFORMES!J85="OBSOLETO","","INSERT INTO INYCEXT.INYC_CONF_INFORMES (COD_INFORME,DESC_INFORME,TABLA,F_INICIO,F_FIN,CARGA_TABLAS,PUBLICACION,FORMATO,DESCRIPCION) VALUES ("&INFORMES!B85&",'"&INFORMES!C85&"','"&INFORMES!D85&"',TO_DATE('"&INFORMES!E85&"','yyyymmdd'),TO_DATE('"&INFORMES!F85&"','yyyymmdd'),'"&INFORMES!G85&"','"&INFORMES!H85&"','"&INFORMES!I85&"','"&INFORMES!J85&"');") -> INSERT INTO INYCEXT.INYC_CONF_INFORMES (COD_INFORME,DESC_INFORME,TABLA,F_INICIO,F_FIN,CARGA_TABLAS,PUBLICACION,FORMATO,DESCRIPCION) VALUES (25.1,'W-O - Incentivos Inspectores Comerciales','INYC_RPI_RESUMEN',TO_DATE('20140101','yyyymmdd'),TO_DATE('22000101','yyyymmdd'),'DIARIO','DIARIO','pdf','PEPI');

Sheet REGLAS
A1: SPRINT | B1: COD_INFORME | C1: TABLA | D1: NOMBRE | F1: REGLA ANTIGUAS | G1: REGLA | H1: F_INICIO | I1: F_FIN | J1: DESCRIPCION | K1: EJEMPLO
A2: 1 | B2: 1.1 | C2: INYC_RPI_RESUMEN | D2: SM - Objetivo Anual RRTT | E2: =F2=G2 -> TRUE | F2: SM-O-RPP-Inspector-ObjetivoAnual-NumPolizas-001 | G2: =IF(ISERROR(VLOOKUP(F2,MODIFICACIONES_REALIZADAS!F:H,3,)),F2,VLOOKUP(F2,MODIFICACIONES_REALIZADAS!F:H,3,)) -> SM-O-RPP-Inspector-ObjetivoAnual-NumPolizas-001 | H2: 20140101 | I2: 22000101
A3: 1 | B3: 1.1 | C3: INYC_RPI_RESUMEN | D3: SM - Objetivo Anual Hogar | E3: =F3=G3 -> TRUE | F3: SM-O-RPP-Inspector-ObjetivoAnual-NumPolizas-002 | G3: =IF(ISERROR(VLOOKUP(F3,MODIFICACIONES_REALIZADAS!F:H,3,)),F3,VLOOKUP(F3,MODIFICACIONES_REALIZADAS!F:H,3,)) -> SM-O-RPP-Inspector-ObjetivoAnual-NumPolizas-002 | H3: 20140101 | I3: 22000101
A4: 1 | B4: 1.1 | C4: INYC_RPI_RESUMEN | D4: SM - Objetivo Anual RRPP | E4: =F4=G4 -> TRUE | F4: SM-O-RPP-Inspector-ObjetivoAnual-NumPolizas-906 | G4: =IF(ISERROR(VLOOKUP(F4,MODIFICACIONES_REALIZADAS!F:H,3,)),F4,VLOOKUP(F4,MODIFICACIONES_REALIZADAS!F:H,3,)) -> SM-O-RPP-Inspector-ObjetivoAnual-NumPolizas-906 | H4: 20140101 | I4: 22000101
A5: 1 | B5: 1.1 | C5: INYC_RPI_RESUMEN | D5: SM - Objetivo Anual Total Ramos | E5: =F5=G5 -> TRUE | F5: SM-O-RPP-Inspector-ObjetivoAnual-NumPolizas-998 | G5: =IF(ISERROR(VLOOKUP(F5,MODIFICACIONES_REALIZADAS!F:H,3,)),F5,VLOOKUP(F5,MODIFICACIONES_REALIZADAS!F:H,3,)) -> SM-O-RPP-Inspector-ObjetivoAnual-NumPolizas-998 | H5: 20140101 | I5: 22000101
A6: 1 | B6: 1.1 | C6: INYC_RPI_RESUMEN | D6: SM - Objetivo Único Anual PC | E6: =F6=G6 -> TRUE | F6: SM-O-RPP-Inspector-ObjetivoUnicoAnual-PrimaCorregida | G6: =IF(ISERROR(VLOOKUP(F6,MODIFICACIONES_REALIZADAS!F:H,3,)),F6,VLOOKUP(F6,MODIFICACIONES_REALIZADAS!F:H,3,)) -> SM-O-RPP-Inspector-ObjetivoUnicoAnual-PrimaCorregida | H6: 20140101 | I6: 22000101
A7: 1 | B7: 1.1 | C7: INYC_RPI_RESUMEN | D7: SM - Objetivo Trimestral Rappel1 RRTT | E7: =F7=G7 -> TRUE | F7: SM-O-RPP-Inspector-ObjetivoTrimestral-Rappel1-NumPolizas-001 | G7: =IF(ISERROR(VLOOKUP(F7,MODIFICACIONES_REALIZADAS!F:H,3,)),F7,VLOOKUP(F7,MODIFICACIONES_REALIZADAS!F:H,3,)) -> SM-O-RPP-Inspector-ObjetivoTrimestral-Rappel1-NumPolizas-001 | H7: 20140101 | I7: 22000101
A8: 1 | B8: 1.1 | C8: INYC_RPI_RESUMEN | D8: SM - Objetivo Trimestral Rappel1 Hogar | E8: =F8=G8 -> TRUE | F8: SM-O-RPP-Inspector-ObjetivoTrimestral-Rappel1-NumPolizas-002 | G8: =IF(ISERROR(VLOOKUP(F8,MODIFICACIONES_REALIZADAS!F:H,3,)),F8,VLOOKUP(F8,MODIFICACIONES_REALIZADAS!F:H,3,)) -> SM-O-RPP-Inspector-ObjetivoTrimestral-Rappel1-NumPolizas-002 | H8: 20140101 | I8: 22000101
A9: 1 | B9: 1.1 | C9: INYC_RPI_RESUMEN | D9: SM - Objetivo Trimestral Rappel1 RRPP | E9: =F9=G9 -> TRUE | F9: SM-O-RPP-Inspector-ObjetivoTrimestral-Rappel1-NumPolizas-906 | G9: =IF(ISERROR(VLOOKUP(F9,MODIFICACIONES_REALIZADAS!F:H,3,)),F9,VLOOKUP(F9,MODIFICACIONES_REALIZADAS!F:H,3,)) -> SM-O-RPP-Inspector-ObjetivoTrimestral-Rappel1-NumPolizas-906 | H9: 20140101 | I9: 22000101
A10: 1 | B10: 1.1 | C10: INYC_RPI_RESUMEN | D10: SM - Objetivo Trimestral Rappel1 Total Ramos | E10: =F10=G10 -> TRUE | F10: SM-O-RPP-Inspector-ObjetivoTrimestral-Rappel1-NumPolizas-998 | G10: =IF(ISERROR(VLOOKUP(F10,MODIFICACIONES_REALIZADAS!F:H,3,)),F10,VLOOKUP(F10,MODIFICACIONES_REALIZADAS!F:H,3,)) -> SM-O-RPP-Inspector-ObjetivoTrimestral-Rappel1-NumPolizas-998 | H10: 20140101 | I10: 22000101
A11: 1 | B11: 1.1 | C11: INYC_RPI_RESUMEN | D11: SM - Objetivo Trimestral Rappel2 Total Ramos | E11: =F11=G11 -> TRUE | F11: SM-O-RPP-Inspector-ObjetivoTrimestral-Rappel2-NumPolizas-998 | G11: =IF(ISERROR(VLOOKUP(F11,MODIFICACIONES_REALIZADAS!F:H,3,)),F11,VLOOKUP(F11,MODIFICACIONES_REALIZADAS!F:H,3,)) -> SM-O-RPP-Inspector-ObjetivoTrimestral-Rappel2-NumPolizas-998 | H11: 20140101 | I11: 22000101
A12: 1 | B12: 1.1 | C12: INYC_RPI_RESUMEN | D12: SM - Importe Reg. Anual Rappel1 Mes1 | E12: =F12=G12 -> TRUE | F12: SM-RPP-Inspector-ImportesRegularizacionAnual-Rappel1-Mes1 | G12: =IF(ISERROR(VLOOKUP(F12,MODIFICACIONES_REALIZADAS!F:H,3,)),F12,VLOOKUP(F12,MODIFICACIONES_REALIZADAS!F:H,3,)) -> SM-RPP-Inspector-ImportesRegularizacionAnual-Rappel1-Mes1 | H12: 20140101 | I12: 22000101
A13: 1 | B13: 1.1 | C13: INYC_RPI_RESUMEN | D13: SM - Importe Reg. Anual Rappel1 Mes10 | E13: =F13=G13 -> TRUE | F13: SM-RPP-Inspector-ImportesRegularizacionAnual-Rappel1-Mes10 | G13: =IF(ISERROR(VLOOKUP(F13,MODIFICACIONES_REALIZADAS!F:H,3,)),F13,VLOOKUP(F13,MODIFICACIONES_REALIZADAS!F:H,3,)) -> SM-RPP-Inspector-ImportesRegularizacionAnual-Rappel1-Mes10 | H13: 20140101 | I13: 22000101
... A24: 1 | B24: 1.1 | C24: INYC_RPI_RESUMEN | D24: SM - Pago Reg. Anual Final | E24: =F24=G24 -> TRUE | F24: SM-RPP-Inspector-PagoRegularizacion-Anual-Final | G24: =IF(ISERROR(VLOOKUP(F24,MODIFICACIONES_REALIZADAS!F:H,3,)),F24,VLOOKUP(F24,MODIFICACIONES_REALIZADAS!F:H,3,)) -> SM-RPP-Inspector-PagoRegularizacion-Anual-Final | H24: 20140101 | I24: 22000101
A25: 1 | B25: 1.1 | C25: INYC_RPI_RESUMEN | D25: PM - Numero Pólizas RRTT | E25: =F25=G25 -> FALSE | F25: PM-GEN-NumeroPolizas-001 | G25: =IF(ISERROR(VLOOKUP(F25,MODIFICACIONES_REALIZADAS!F:H,3,)),F25,VLOOKUP(F25,MODIFICACIONES_REALIZADAS!F:H,3,)) -> PM-O-GEN-Inspector-NumeroPolizas-001 | H25: 20140101 | I25: 20180101 | J25: Version 20180126
A26: 1 | B26: 1.1 | C26: INYC_RPI_RESUMEN | D26: PM - Numero Pólizas Hogar | E26: =F26=G26 -> FALSE | F26: PM-GEN-NumeroPolizas-002 | G26: =IF(ISERROR(VLOOKUP(F26,MODIFICACIONES_REALIZADAS!F:H,3,)),F26,VLOOKUP(F26,MODIFICACIONES_REALIZADAS!F:H,3,)) -> PM-O-GEN-Inspector-NumeroPolizas-002 | H26: 20140101 | I26: 20180101 | J26: Version 20180126
A27: 1 | B27: 1.1 | C27: INYC_RPI_RESUMEN | D27: PM - Numero Pólizas RRPP | E27: =F27=G27 -> FALSE | F27: PM-GEN-NumeroPolizas-906 | G27: =IF(ISERROR(VLOOKUP(F27,MODIFICACIONES_REALIZADAS!F:H,3,)),F27,VLOOKUP(F27,MODIFICACIONES_REALIZADAS!F:H,3,)) -> PM-O-GEN-Inspector-NumeroPolizas-906 | H27: 20140101 | I27: 20180101 | J27: Version 20180126
A28: 1 | B28: 1.1 | C28: INYC_RPI_RESUMEN | D28: PM - Numero Pólizas Total Ramos | E28: =F28=G28 -> FALSE | F28: PM-GEN-NumeroPolizas-998 | G28: =IF(ISERROR(VLOOKUP(F28,MODIFICACIONES_REALIZADAS!F:H,3,)),F28,VLOOKUP(F28,MODIFICACIONES_REALIZADAS!F:H,3,)) -> PM-O-GEN-Inspector-NumeroPolizas-998 | H28: 20140101 | I28: 20180101 | J28: Version 20180126
A29: 1 | B29: 1.1 | C29: INYC_RPI_RESUMEN | D29: PM - Numero Pólizas Corregidas RRTT | E29: =F29=G29 -> TRUE | F29: PM-O-GEN-Inspector-NumeroPolizasCorregidas-001 | G29: =IF(ISERROR(VLOOKUP(F29,MODIFICACIONES_REALIZADAS!F:H,3,)),F29,VLOOKUP(F29,MODIFICACIONES_REALIZADAS!F:H,3,)) -> PM-O-GEN-Inspector-NumeroPolizasCorregidas-001 | H29: 20180101 | I29: 22000101 | J29: Version 20180126
A30: 1 | B30: 1.1 | C30: INYC_RPI_RESUMEN | D30: PM - Numero Pólizas Corregidas Hogar | E30: =F30=G30 -> TRUE | F30: PM-O-GEN-Inspector-NumeroPolizasCorregidas-002 | G30: =IF(ISERROR(VLOOKUP(F30,MODIFICACIONES_REALIZADAS!F:H,3,)),F30,VLOOKUP(F30,MODIFICACIONES_REALIZADAS!F:H,3,)) -> PM-O-GEN-Inspector-NumeroPolizasCorregidas-002 | H30: 20180101 | I30: 22000101 | J30: Version 20180126
A31: 1 | B31: 1.1 | C31: INYC_RPI_RESUMEN | D31: PM - Numero Pólizas Corregidas RRPP | E31: =F31=G31 -> TRUE | F31: PM-O-GEN-Inspector-NumeroPolizasCorregidas-906 | G31: =IF(ISERROR(VLOOKUP(F31,MODIFICACIONES_REALIZADAS!F:H,3,)),F31,VLOOKUP(F31,MODIFICACIONES_REALIZADAS!F:H,3,)) -> PM-O-GEN-Inspector-NumeroPolizasCorregidas-906 | H31: 20180101 | I31: 22000101 | J31: Version 20180126
A32: 1 | B32: 1.1 | C32: INYC_RPI_RESUMEN | D32: PM - Prima Corregida Total Ramos | E32: =F32=G32 -> FALSE | F32: PM-RPP-Inspector-PrimaCorregida | G32: =IF(ISERROR(VLOOKUP(F32,MODIFICACIONES_REALIZADAS!F:H,3,)),F32,VLOOKUP(F32,MODIFICACIONES_REALIZADAS!F:H,3,)) -> PM-O-GEN-Inspector-PrimaCorregida-998 | H32: 20140101 | I32: 22000101
A33: 1 | B33: 1.1 | C33: INYC_RPI_RESUMEN | D33: PM - Numero Pólizas Corregidas Total Ramos | E33: =F33=G33 -> TRUE | F33: PM-O-GEN-Inspector-NumeroPolizasCorregidas-998 | G33: =IF(ISERROR(VLOOKUP(F33,MODIFICACIONES_REALIZADAS!F:H,3,)),F33,VLOOKUP(F33,MODIFICACIONES_REALIZADAS!F:H,3,)) -> PM-O-GEN-Inspector-NumeroPolizasCorregidas-998 | H33: 20180101 | I33: 22000101 | J33: Version 20180119
A34: 1 | B34: 1.1 | C34: INYC_RPI_RESUMEN | D34: PM - Nº Asegurados Inspector | E34: =F34=G34 -> TRUE | F34: PM-O-GEN-Agente-NumAsegurados | G34: =IF(ISERROR(VLOOKUP(F34,MODIFICACIONES_REALIZADAS!F:H,3,)),F34,VLOOKUP(F34,MODIFICACIONES_REALIZADAS!F:H,3,)) -> PM-O-GEN-Agente-NumAsegurados | H34: 20180101 | I34: 22000101 | J34: Version 20180119
A35: 1 | B35: 1.1 | C35: INYC_RPI_RESUMEN | D35: PM - Numero Pólizas RRTT Agentes | E35: =F35=G35 -> FALSE | F35: PM-GEN-NumeroPolizas-001-Agentes | G35: =IF(ISERROR(VLOOKUP(F35,MODIFICACIONES_REALIZADAS!F:H,3,)),F35,VLOOKUP(F35,MODIFICACIONES_REALIZADAS!F:H,3,)) -> PM-O-GEN-Inspector-NumeroPolizas-001-Agentes | H35: 20140101 | I35: 20180101 | J35: Version 20180126
A36: 1 | B36: 1.1 | C36: INYC_RPI_RESUMEN | D36: PM - Numero Pólizas Hogar Agentes | E36: =F36=G36 -> FALSE | F36: PM-GEN-NumeroPolizas-002-Agentes | G36: =IF(ISERROR(VLOOKUP(F36,MODIFICACIONES_REALIZADAS!F:H,3,)),F36,VLOOKUP(F36,MODIFICACIONES_REALIZADAS!F:H,3,)) -> PM-O-GEN-Inspector-NumeroPolizas-002-Agentes | H36: 20140101 | I36: 20180101 | J36: Version 20180126
A37: 1 | B37: 1.1 | C37: INYC_RPI_RESUMEN | D37: PM - Numero Pólizas RRPP Agentes | E37: =F37=G37 -> FALSE | F37: PM-GEN-NumeroPolizas-906-Agentes | G37: =IF(ISERROR(VLOOKUP(F37,MODIFICACIONES_REALIZADAS!F:H,3,)),F37,VLOOKUP(F37,MODIFICACIONES_REALIZADAS!F:H,3,)) -> PM-O-GEN-Inspector-NumeroPolizas-906-Agentes | H37: 20140101 | I37: 20180101 | J37: Version 20180126
A38: 1 | B38: 1.1 | C38: INYC_RPI_RESUMEN | D38: PM - Numero Pólizas Total Ramos Agentes | E38: =F38=G38 -> FALSE | F38: PM-GEN-NumeroPolizas-998-Agentes | G38: =IF(ISERROR(VLOOKUP(F38,MODIFICACIONES_REALIZADAS!F:H,3,)),F38,VLOOKUP(F38,MODIFICACIONES_REALIZADAS!F:H,3,)) -> PM-O-GEN-Inspector-NumeroPolizas-998-Agentes | H38: 20140101 | I38: 20180101 | J38: Version 20180126
A39: 1 | B39: 1.1 | C39: INYC_RPI_RESUMEN | D39: PM - Numero Pólizas Corregidas RRTT Agentes | E39: =F39=G39 -> TRUE | F39: PM-O-GEN-Inspector-NumeroPolizasCorregidas-001-Agentes | G39: =IF(ISERROR(VLOOKUP(F39,MODIFICACIONES_REALIZADAS!F:H,3,)),F39,VLOOKUP(F39,MODIFICACIONES_REALIZADAS!F:H,3,)) -> PM-O-GEN-Inspector-NumeroPolizasCorregidas-001-Agentes | H39: 20180101 | I39: 22000101 | J39: Version 20180126
A40: 1 | B40: 1.1 | C40: INYC_RPI_RESUMEN | D40: PM - Numero Pólizas Corregidas Hogar Agentes | E40: =F40=G40 -> TRUE | F40: PM-O-GEN-Inspector-NumeroPolizasCorregidas-002-Agentes | G40: =IF(ISERROR(VLOOKUP(F40,MODIFICACIONES_REALIZADAS!F:H,3,)),F40,VLOOKUP(F40,MODIFICACIONES_REALIZADAS!F:H,3,)) -> PM-O-GEN-Inspector-NumeroPolizasCorregidas-002-Agentes | H40: 20180101 | I40: 22000101 | J40: Version 20180126
A41: 1 | B41: 1.1 | C41: INYC_RPI_RESUMEN | D41: PM - Numero Pólizas Corregidas RRPP Agentes | E41: =F41=G41 -> TRUE | F41: PM-O-GEN-Inspector-NumeroPolizasCorregidas-906-Agentes | G41: =IF(ISERROR(VLOOKUP(F41,MODIFICACIONES_REALIZADAS!F:H,3,)),F41,VLOOKUP(F41,MODIFICACIONES_REALIZADAS!F:H,3,)) -> PM-O-GEN-Inspector-NumeroPolizasCorregidas-906-Agentes | H41: 20180101 | I41: 22000101 | J41: Version 20180126
A42: 1 | B42: 1.1 | C42: INYC_RPI_RESUMEN | D42: PM - Prima Corregida Total Ramos Agentes | E42: =F42=G42 -> FALSE | F42: PM-RPP-Inspector-PrimaCorregida-Agentes | G42: =IF(ISERROR(VLOOKUP(F42,MODIFICACIONES_REALIZADAS!F:H,3,)),F42,VLOOKUP(F42,MODIFICACIONES_REALIZADAS!F:H,3,)) -> PM-O-GEN-Inspector-PrimaCorregida-998-Agentes | H42: 20140101 | I42: 22000101
A43: 1 | B43: 1.1 | C43: INYC_RPI_RESUMEN | D43: PM - Numero Pólizas Corregidas Total Ramos | E43: =F43=G43 -> TRUE | F43: PM-O-GEN-Inspector-NumeroPolizasCorregidas-998-Agentes | G43: =IF(ISERROR(VLOOKUP(F43,MODIFICACIONES_REALIZADAS!F:H,3,)),F43,VLOOKUP(F43,MODIFICACIONES_REALIZADAS!F:H,3,)) -> PM-O-GEN-Inspector-NumeroPolizasCorregidas-998-Agentes | H43: 20180101 | I43: 22000101 | J43: Version 20180119
A44: 1 | B44: 1.1 | C44: INYC_RPI_RESUMEN | D44: PM - Nº Asegurados Inspector Agentes | E44: =F44=G44 -> TRUE | F44: PM-O-GEN-Inspector-NumAsegurados-Agentes | G44: =IF(ISERROR(VLOOKUP(F44,MODIFICACIONES_REALIZADAS!F:H,3,)),F44,VLOOKUP(F44,MODIFICACIONES_REALIZADAS!F:H,3,)) -> PM-O-GEN-Inspector-NumAsegurados-Agentes | H44: 20180101 | I44: 22000101 | J44: Version 20180117
A45: 1 | B45: 1.1 | C45: INYC_RPI_RESUMEN | D45: SM - Nº Pólizas Inspector RRTT Mensual | E45: =F45=G45 -> FALSE | F45: SM-RPP-Inspector-NumeroPolizas-001-TotalMes | G45: =IF(ISERROR(VLOOKUP(F45,MODIFICACIONES_REALIZADAS!F:H,3,)),F45,VLOOKUP(F45,MODIFICACIONES_REALIZADAS!F:H,3,)) -> SM-O-GEN-Inspector-NumeroPolizas-001-TotalMes | H45: 20140101 | I45: 20180101 | J45: Version 20180126
A46: 1 | B46: 1.1 | C46: INYC_RPI_RESUMEN | D46: SM - Nº Pólizas Inspector Hogar Mensual | E46: =F46=G46 -> FALSE | F46: SM-RPP-Inspector-NumeroPolizas-002-TotalMes | G46: =IF(ISERROR(VLOOKUP(F46,MODIFICACIONES_REALIZADAS!F:H,3,)),F46,VLOOKUP(F46,MODIFICACIONES_REALIZADAS!F:H,3,)) -> SM-O-GEN-Inspector-NumeroPolizas-002-TotalMes | H46: 20140101 | I46: 20180101 | J46: Version 20180126
A47: 1 | B47: 1.1 | C47: INYC_RPI_RESUMEN | D47: SM - Nº Pólizas Inspector RRPP (excl PU y conv/colec) Mensual | E47: =F47=G47 -> FALSE | F47: SM-RPP-Inspector-NumeroPolizas-906-TotalMes | G47: =IF(ISERROR(VLOOKUP(F47,MODIFICACIONES_REALIZADAS!F:H,3,)),F47,VLOOKUP(F47,MODIFICACIONES_REALIZADAS!F:H,3,)) -> SM-O-GEN-Inspector-NumeroPolizas-906-TotalMes | H47: 20140101 | I47: 20180101 | J47: Version 20180126
A48: 1 | B48: 1.1 | C48: INYC_RPI_RESUMEN | D48: SM - Nº Pólizas Inspector Total Productos Mensual | E48: =F48=G48 -> FALSE | F48: SM-RPP-Inspector-NumeroPolizas-998-TotalMes | G48: =IF(ISERROR(VLOOKUP(F48,MODIFICACIONES_REALIZADAS!F:H,3,)),F48,VLOOKUP(F48,MODIFICACIONES_REALIZADAS!F:H,3,)) -> SM-O-GEN-Inspector-NumeroPolizas-998-TotalMes | H48: 20140101 | I48: 20180101 | J48: Version 20180126
A49: 1 | B49: 1.1 | C49: INYC_RPI_RESUMEN | D49: SM - Nº Pólizas Corregidas Inspector RRTT Mensual | E49: =F49=G49 -> TRUE | F49: SM-O-GEN-Inspector-NumeroPolizasCorregidas-001-TotalMes | G49: =IF(ISERROR(VLOOKUP(F49,MODIFICACIONES_REALIZADAS!F:H,3,)),F49,VLOOKUP(F49,MODIFICACIONES_REALIZADAS!F:H,3,)) -> SM-O-GEN-Inspector-NumeroPolizasCorregidas-001-TotalMes | H49: 20180101 | I49: 22000101 | J49: Version 20180126
A50: 1 | B50: 1.1 | C50: INYC_RPI_RESUMEN | D50: SM - Nº Pólizas Corregidas Inspector Hogar Mensual | E50: =F50=G50 -> TRUE | F50: SM-O-GEN-Inspector-NumeroPolizasCorregidas-002-TotalMes | G50: =IF(ISERROR(VLOOKUP(F50,MODIFICACIONES_REALIZADAS!F:H,3,)),F50,VLOOKUP(F50,MODIFICACIONES_REALIZADAS!F:H,3,)) -> SM-O-GEN-Inspector-NumeroPolizasCorregidas-002-TotalMes | H50: 20180101 | I50: 22000101 | J50: Version 20180126
A51: 1 | B51: 1.1 | C51: INYC_RPI_RESUMEN | D51: SM - Nº Pólizas Corregidas Inspector RRPP (excl PU y conv/colec) Mensual | E51: =F51=G51 -> TRUE | F51: SM-O-GEN-Inspector-NumeroPolizasCorregidas-906-TotalMes | G51: =IF(ISERROR(VLOOKUP(F51,MODIFICACIONES_REALIZADAS!F:H,3,)),F51,VLOOKUP(F51,MODIFICACIONES_REALIZADAS!F:H,3,)) -> SM-O-GEN-Inspector-NumeroPolizasCorregidas-906-TotalMes | H51: 20180101 | I51: 22000101 | J51: Version 20180126
A52: 1 | B52: 1.1 | C52: INYC_RPI_RESUMEN | D52: SM - Pago Mensual | E52: =F52=G52 -> TRUE | F52: SM-RPP-Inspector-PagoMensual | G52: =IF(ISERROR(VLOOKUP(F52,MODIFICACIONES_REALIZADAS!F:H,3,)),F52,VLOOKUP(F52,MODIFICACIONES_REALIZADAS!F:H,3,)) -> SM-RPP-Inspector-PagoMensual | H52: 20140101 | I52: 22000101
A53: 1 | B53: 1.1 | C53: INYC_RPI_RESUMEN | D53: SM - Prima Corregida Inspector Total Productos Mensual | E53: =F53=G53 -> FALSE | F53: SM-RPP-Inspector-PrimaCorregida-TotalMes | G53: =IF(ISERROR(VLOOKUP(F53,MODIFICACIONES_REALIZADAS!F:H,3,)),F53,VLOOKUP(F53,MODIFICACIONES_REALIZADAS!F:H,3,)) -> SM-O-GEN-Inspector-PrimaCorregida-998-TotalMes | H53: 20140101 | I53: 22000101
A54: 1 | B54: 1.1 | C54: INYC_RPI_RESUMEN | D54: SM - Nº Pólizas Corregidas Inspector Total Productos Mensual | E54: TRUE | F54: SM-O-GEN-Inspector-NumeroPolizasCorregidas-998-TotalMes | G54: =IF(ISERROR(VLOOKUP(F54,MODIFICACIONES_REALIZADAS!F:H,3,)),F54,VLOOKUP(F54,MODIFICACIONES_REALIZADAS!F:H,3,)) -> SM-O-GEN-Inspector-NumeroPolizasCorregidas-998-TotalMes | H54: 20180101 | I54: 22000101 | J54: Version 20180119
A55: 1 | B55: 1.1 | C55: INYC_RPI_RESUMEN | D55: SM - Nº Asegurados Inspector Mensual | E55: =F55=G55 -> TRUE | F55: SM-O-GEN-Inspector-NumAsegurados-TotalMes | G55: =IF(ISERROR(VLOOKUP(F55,MODIFICACIONES_REALIZADAS!F:H,3,)),F55,VLOOKUP(F55,MODIFICACIONES_REALIZADAS!F:H,3,)) -> SM-O-GEN-Inspector-NumAsegurados-TotalMes | H55: 20180101 | I55: 22000101 | J55: Version 20180117
A56: 1 | B56: 1.1 | C56: INYC_RPI_RESUMEN | D56: SM - importe Reg. Trimestral Rappel1 Mes1 | E56: =F56=G56 -> TRUE | F56: SM-RPP-Inspector-ImportesRegularizacionTrimestral-Rappel1-Mes1 | G56: =IF(ISERROR(VLOOKUP(F56,MODIFICACIONES_REALIZADAS!F:H,3,)),F56,VLOOKUP(F56,MODIFICACIONES_REALIZADAS!F:H,3,)) -> SM-RPP-Inspector-ImportesRegularizacionTrimestral-Rappel1-Mes1 | H56: 20140101 | I56: 22000101
A57: 1 | B57: 1.1 | C57: INYC_RPI_RESUMEN | D57: SM - importe Reg. Trimestral Rappel1 Mes2 | E57: =F57=G57 -> TRUE | F57: SM-RPP-Inspector-ImportesRegularizacionTrimestral-Rappel1-Mes2 | G57: =IF(ISERROR(VLOOKUP(F57,MODIFICACIONES_REALIZADAS!F:H,3,)),F57,VLOOKUP(F57,MODIFICACIONES_REALIZADAS!F:H,3,)) -> SM-RPP-Inspector-ImportesRegularizacionTrimestral-Rappel1-Mes2 | H57: 20140101 | I57: 22000101
A58: 1 | B58: 1.1 | C58: INYC_RPI_RESUMEN | D58: SM - importe Reg. Trimestral Rappel1 Mes3 | E58: =F58=G58 -> TRUE | F58: SM-RPP-Inspector-ImportesRegularizacionTrimestral-Rappel1-Mes3 | G58: =IF(ISERROR(VLOOKUP(F58,MODIFICACIONES_REALIZADAS!F:H,3,)),F58,VLOOKUP(F58,MODIFICACIONES_REALIZADAS!F:H,3,)) -> SM-RPP-Inspector-ImportesRegularizacionTrimestral-Rappel1-Mes3 | H58: 20140101 | I58: 22000101
A59: 1 | B59: 1.1 | C59: INYC_RPI_RESUMEN | D59: SM - importe Reg. Trimestral Rappel2 Mes1 | E59: =F59=G59 -> TRUE | F59: SM-RPP-Inspector-ImportesRegularizacionTrimestral-Rappel2-Mes1 | G59: =IF(ISERROR(VLOOKUP(F59,MODIFICACIONES_REALIZADAS!F:H,3,)),F59,VLOOKUP(F59,MODIFICACIONES_REALIZADAS!F:H,3,)) -> SM-RPP-Inspector-ImportesRegularizacionTrimestral-Rappel2-Mes1 | H59: 20140101 | I59: 22000101
A60: 1 | B60: 1.1 | C60: INYC_RPI_RESUMEN | D60: SM - importe Reg. Trimestral Rappel2 Mes2 | E60: =F60=G60 -> TRUE | F60: SM-RPP-Inspector-ImportesRegularizacionTrimestral-Rappel2-Mes2 | G60: =IF(ISERROR(VLOOKUP(F60,MODIFICACIONES_REALIZADAS!F:H,3,)),F60,VLOOKUP(F60,MODIFICACIONES_REALIZADAS!F:H,3,)) -> SM-RPP-Inspector-ImportesRegularizacionTrimestral-Rappel2-Mes2 | H60: 20140101 | I60: 22000101
A61: 1 | B61: 1.1 | C61: INYC_RPI_RESUMEN | D61: SM - importe Reg. Trimestral Rappel2 Mes3 | E61: =F61=G61 -> TRUE | F61: SM-RPP-Inspector-ImportesRegularizacionTrimestral-Rappel2-Mes3 | G61: =IF(ISERROR(VLOOKUP(F61,MODIFICACIONES_REALIZADAS!F:H,3,)),F61,VLOOKUP(F61,MODIFICACIONES_REALIZADAS!F:H,3,)) -> SM-RPP-Inspector-ImportesRegularizacionTrimestral-Rappel2-Mes3 | H61: 20140101 | I61: 22000101
A62: 1 | B62: 1.1 | C62: INYC_RPI_RESUMEN | D62: I - Importe Reg. Trimestral Rappel1 Mes1 | E62: =F62=G62 -> TRUE | F62: I-RPP-Inspector-ImporteRegTrimestral-Mes1 | G62: =IF(ISERROR(VLOOKUP(F62,MODIFICACIONES_REALIZADAS!F:H,3,)),F62,VLOOKUP(F62,MODIFICACIONES_REALIZADAS!F:H,3,)) -> I-RPP-Inspector-ImporteRegTrimestral-Mes1 | H62: 20180601 | I62: 22000101 | J62: Version 20180718
A63: 1 | B63: 1.1 | C63: INYC_RPI_RESUMEN | D63: I - Importe Reg. Trimestral Rappel1 Mes2 | E63: =F63=G63 -> TRUE | F63: I-RPP-Inspector-ImporteRegTrimestral-Mes2 | G63: =IF(ISERROR(VLOOKUP(F63,MODIFICACIONES_REALIZADAS!F:H,3,)),F63,VLOOKUP(F63,MODIFICACIONES_REALIZADAS!F:H,3,)) -> I-RPP-Inspector-ImporteRegTrimestral-Mes2 | H63: 20180601 | I63: 22000101 | J63: Version 20180718
A64: 1 | B64: 1.1 | C64: INYC_RPI_RESUMEN | D64: I - Importe Reg. Trimestral Rappel1 Mes3 | E64: =F64=G64 -> TRUE | F64: I-RPP-Inspector-ImporteRegTrimestral-Mes3 | G64: =IF(ISERROR(VLOOKUP(F64,MODIFICACIONES_REALIZADAS!F:H,3,)),F64,VLOOKUP(F64,MODIFICACIONES_REALIZADAS!F:H,3,)) -> I-RPP-Inspector-ImporteRegTrimestral-Mes3 | H64: 20180601 | I64: 22000101 | J64: Version 20180718
A65: 1 | B65: 1.1 | C65: INYC_RPI_RESUMEN | D65: I - Importe Reg. Trimestral Rappel2 Mes1 | E65: =F65=G65 -> TRUE | F65: I-RPP-Inspector-ImporteRegTrimestral-MinMes1 | G65: =IF(ISERROR(VLOOKUP(F65,MODIFICACIONES_REALIZADAS!F:H,3,)),F65,VLOOKUP(F65,MODIFICACIONES_REALIZADAS!F:H,3,)) -> I-RPP-Inspector-ImporteRegTrimestral-MinMes1 | H65: 20180601 | I65: 22000101 | J65: Version 20180718
A66: 1 | B66: 1.1 | C66: INYC_RPI_RESUMEN | D66: I - Importe Reg. Trimestral Rappel2 Mes2 | E66: =F66=G66 -> TRUE | F66: I-RPP-Inspector-ImporteRegTrimestral-MinMes2 | G66: =IF(ISERROR(VLOOKUP(F66,MODIFICACIONES_REALIZADAS!F:H,3,)),F66,VLOOKUP(F66,MODIFICACIONES_REALIZADAS!F:H,3,)) -> I-RPP-Inspector-ImporteRegTrimestral-MinMes2 | H66: 20180601 | I66: 22000101 | J66: Version 20180718
A67: 1 | B67: 1.1 | C67: INYC_RPI_RESUMEN | D67: I - Importe Reg. Trimestral Rappel2 Mes3 | E67: =F67=G67 -> TRUE | F67: I-RPP-Inspector-ImporteRegTrimestral-MinMes3 | G67: =IF(ISERROR(VLOOKUP(F67,MODIFICACIONES_REALIZADAS!F:H,3,)),F67,VLOOKUP(F67,MODIFICACIONES_REALIZADAS!F:H,3,)) -> I-RPP-Inspector-ImporteRegTrimestral-MinMes3 | H67: 20180601 | I67: 22000101 | J67: Version 20180718
A68: 1 | B68: 1.1 | C68: INYC_RPI_RESUMEN | D68: SM - Pago Reg. Trimestral Final | E68: =F68=G68 -> TRUE | F68: SM-RPP-Inspector-PagoRegularizacion-Trimestral-Final | G68: =IF(ISERROR(VLOOKUP(F68,MODIFICACIONES_REALIZADAS!F:H,3,)),F68,VLOOKUP(F68,MODIFICACIONES_REALIZADAS!F:H,3,)) -> SM-RPP-Inspector-PagoRegularizacion-Trimestral-Final | H68: 20140101 | I68: 20180601 | J68: Version 20180718
A69: 1 | B69: 1.1 | C69: INYC_RPI_RESUMEN | D69: I - Pago Reg. Trimestral Final | E69: =F69=G69 -> TRUE | F69: I-RPP-Inspector-ImporteRegTrimestral | G69: =IF(ISERROR(VLOOKUP(F69,MODIFICACIONES_REALIZADAS!F:H,3,)),F69,VLOOKUP(F69,MODIFICACIONES_REALIZADAS!F:H,3,)) -> I-RPP-Inspector-ImporteRegTrimestral | H69: 20180601 | I69: 22000101 | J69: Version 20180718
A70: 1 | B70: 1.1 | C70: INYC_RPI_RESUMEN | D70: SM - Consecución Anual RRTT | E70: =F70=G70 -> TRUE | F70: SM-RPP-Inspector-ConsecucionAnual-001 | G70: =IF(ISERROR(VLOOKUP(F70,MODIFICACIONES_REALIZADAS!F:H,3,)),F70,VLOOKUP(F70,MODIFICACIONES_REALIZADAS!F:H,3,)) -> SM-RPP-Inspector-ConsecucionAnual-001 | H70: 20140101 | I70: 22000101
A71: 1 | B71: 1.1 | C71: INYC_RPI_RESUMEN | D71: SM - Consecución Anual Hogar | E71: =F71=G71 -> TRUE | F71: SM-RPP-Inspector-ConsecucionAnual-002 | G71: =IF(ISERROR(VLOOKUP(F71,MODIFICACIONES_REALIZADAS!F:H,3,)),F71,VLOOKUP(F71,MODIFICACIONES_REALIZADAS!F:H,3,)) -> SM-RPP-Inspector-ConsecucionAnual-002 | H71: 20140101 | I71: 22000101
A72: 1 | B72: 1.1 | C72: INYC_RPI_RESUMEN | D72: SM - Consecución Anual RRPP | E72: =F72=G72 -> TRUE | F72: SM-RPP-Inspector-ConsecucionAnual-906 | G72: =IF(ISERROR(VLOOKUP(F72,MODIFICACIONES_REALIZADAS!F:H,3,)),F72,VLOOKUP(F72,MODIFICACIONES_REALIZADAS!F:H,3,)) -> SM-RPP-Inspector-ConsecucionAnual-906 | H72: 20140101 | I72: 22000101
A73: 1 | B73: 1.1 | C73: INYC_RPI_RESUMEN | D73: SM - Consecución Anual Total Ramos | E73: =F73=G73 -> TRUE | F73: SM-RPP-Inspector-ConsecucionAnual-998 | G73: =IF(ISERROR(VLOOKUP(F73,MODIFICACIONES_REALIZADAS!F:H,3,)),F73,VLOOKUP(F73,MODIFICACIONES_REALIZADAS!F:H,3,)) -> SM-RPP-Inspector-ConsecucionAnual-998 | H73: 20140101 | I73: 22000101
A74: 1 | B74: 1.1 | C74: INYC_RPI_RESUMEN | D74: SM - Consecución Anual Total Ramos Propia | E74: =F74=G74 -> TRUE | F74: SM-RPP-Inspector-ConsecucionAnual-998-Propia | G74: =IF(ISERROR(VLOOKUP(F74,MODIFICACIONES_REALIZADAS!F:H,3,)),F74,VLOOKUP(F74,MODIFICACIONES_REALIZADAS!F:H,3,)) -> SM-RPP-Inspector-ConsecucionAnual-998-Propia | H74: 20140101 | I74: 22000101
A75: 1 | B75: 1.1 | C75: INYC_RPI_RESUMEN | D75: SM - Consecución Anual Importe | E75: =F75=G75 -> TRUE | F75: SM-RPP-Inspector-ConsecucionAnual-Importe | G75: =IF(ISERROR(VLOOKUP(F75,MODIFICACIONES_REALIZADAS!F:H,3,)),F75,VLOOKUP(F75,MODIFICACIONES_REALIZADAS!F:H,3,)) -> SM-RPP-Inspector-ConsecucionAnual-Importe | H75: 20140101 | I75: 22000101
A76: 1 | B76: 1.1 | C76: INYC_RPI_RESUMEN | D76: SM - Consecución Anual PC Agentes | E76: =F76=G76 -> TRUE | F76: SM-RPP-Inspector-ConsecucionAnual-PrimaCorregida-Agentes | G76: =IF(ISERROR(VLOOKUP(F76,MODIFICACIONES_REALIZADAS!F:H,3,)),F76,VLOOKUP(F76,MODIFICACIONES_REALIZADAS!F:H,3,)) -> SM-RPP-Inspector-ConsecucionAnual-PrimaCorregida-Agentes | H76: 20140101 | I76: 22000101
A77: 1 | B77: 1.1 | C77: INYC_RPI_RESUMEN | D77: SM - Nº Pólizas Inspector RRTT Anual | E77: =F77=G77 -> FALSE | F77: SM-RPP-Inspector-NumeroPolizas-001-TotalAnual | G77: =IF(ISERROR(VLOOKUP(F77,MODIFICACIONES_REALIZADAS!F:H,3,)),F77,VLOOKUP(F77,MODIFICACIONES_REALIZADAS!F:H,3,)) -> SM-O-GEN-Inspector-NumeroPolizas-001-TotalAnual | H77: 20140101 | I77: 20180101 | J77: Version 20180324
A78: 1 | B78: 1.1 | C78: INYC_RPI_RESUMEN | D78: SM - Nº Pólizas Inspector Hogar Anual | E78: =F78=G78 -> FALSE | F78: SM-RPP-Inspector-NumeroPolizas-002-TotalAnual | G78: =IF(ISERROR(VLOOKUP(F78,MODIFICACIONES_REALIZADAS!F:H,3,)),F78,VLOOKUP(F78,MODIFICACIONES_REALIZADAS!F:H,3,)) -> SM-O-GEN-Inspector-NumeroPolizas-002-TotalAnual | H78: 20140101 | I78: 20180101 | J78: Version 20180324
A79: 1 | B79: 1.1 | C79: INYC_RPI_RESUMEN | D79: SM - Nº Pólizas Inspector RRPP (excl PU y conv/colec) Anual | E79: =F79=G79 -> FALSE | F79: SM-RPP-Inspector-NumeroPolizas-906-TotalAnual | G79: =IF(ISERROR(VLOOKUP(F79,MODIFICACIONES_REALIZADAS!F:H,3,)),F79,VLOOKUP(F79,MODIFICACIONES_REALIZADAS!F:H,3,)) -> SM-O-GEN-Inspector-NumeroPolizas-906-TotalAnual | H79: 20140101 | I79: 20180101 | J79: Version 20180324
A80: 1 | B80: 1.1 | C80: INYC_RPI_RESUMEN | D80: SM - Nº Pólizas Propias Inspector Total Productos Anual | E80: =F80=G80 -> FALSE | F80: SM-RPP-Inspector-NumeroPolizas-998-Propia-TotalAnual | G80: =IF(ISERROR(VLOOKUP(F80,MODIFICACIONES_REALIZADAS!F:H,3,)),F80,VLOOKUP(F80,MODIFICACIONES_REALIZADAS!F:H,3,)) -> SM-O-GEN-Inspector-NumeroPolizas-998-Propia-TotalAnual | H80: 20140101 | I80: 20180101 | J80: Version 20180324
A81: 1 | B81: 1.1 | C81: INYC_RPI_RESUMEN | D81: SM - Nº Pólizas Inspector Total Productos Anual | E81: =F81=G81 -> FALSE | F81: SM-RPP-Inspector-NumeroPolizas-998-TotalAnual | G81: =IF(ISERROR(VLOOKUP(F81,MODIFICACIONES_REALIZADAS!F:H,3,)),F81,VLOOKUP(F81,MODIFICACIONES_REALIZADAS!F:H,3,)) -> SM-O-GEN-Inspector-NumeroPolizas-998-TotalAnual | H81: 20140101 | I81: 20180101 | J81: Version 20180324
A82: 1 | B82: 1.1 | C82: INYC_RPI_RESUMEN | D82: SM - Nº Pólizas Corregidas Inspector RRTT Anual | E82: =F82=G82 -> TRUE | F82: SM-O-GEN-Inspector-NumeroPolizasCorregidas-001-TotalAnual | G82: =IF(ISERROR(VLOOKUP(F82,MODIFICACIONES_REALIZADAS!F:H,3,)),F82,VLOOKUP(F82,MODIFICACIONES_REALIZADAS!F:H,3,)) -> SM-O-GEN-Inspector-NumeroPolizasCorregidas-001-TotalAnual | H82: 20180101 | I82: 22000101 | J82: Version 20180324
A83: 1 | B83: 1.1 | C83: INYC_RPI_RESUMEN | D83: SM - Nº Pólizas Corregidas Inspector Hogar Anual | E83: =F83=G83 -> TRUE | F83: SM-O-GEN-Inspector-NumeroPolizasCorregidas-002-TotalAnual | G83: =IF(ISERROR(VLOOKUP(F83,MODIFICACIONES_REALIZADAS!F:H,3,)),F83,VLOOKUP(F83,MODIFICACIONES_REALIZADAS!F:H,3,)) -> SM-O-GEN-Inspector-NumeroPolizasCorregidas-002-TotalAnual | H83: 20180101 | I83: 22000101 | J83: Version 20180324
A84: 1 | B84: 1.1 | C84: INYC_RPI_RESUMEN | D84: SM - Nº Pólizas Corregidas Inspector RRPP (excl PU y conv/colec) Anual | E84: =F84=G84 -> TRUE | F84: SM-O-GEN-Inspector-NumeroPolizasCorregidas-906-TotalAnual | G84: =IF(ISERROR(VLOOKUP(F84,MODIFICACIONES_REALIZADAS!F:H,3,)),F84,VLOOKUP(F84,MODIFICACIONES_REALIZADAS!F:H,3,)) -> SM-O-GEN-Inspector-NumeroPolizasCorregidas-906-TotalAnual | H84: 20180101 | I84: 22000101 | J84: Version 20180324
A85: 1 | B85: 1.1 | C85: INYC_RPI_RESUMEN | D85: SM - Nº Pólizas Corregidas Propias Inspector Total Productos Anual | E85: =F85=G85 -> TRUE | F85: SM-O-GEN-Inspector-NumeroPolizasCorregidas-998-Propia-TotalAnual | G85: =IF(ISERROR(VLOOKUP(F85,MODIFICACIONES_REALIZADAS!F:H,3,)),F85,VLOOKUP(F85,MODIFICACIONES_REALIZADAS!F:H,3,)) -> SM-O-GEN-Inspector-NumeroPolizasCorregidas-998-Propia-TotalAnual | H85: 20180101 | I85: 22000101 | J85: Version 20180324
A86: 1 | B86: 1.1 | C86: INYC_RPI_RESUMEN | D86: SM - Prima Corregida Agentes Inspector Total Productos Anual | E86: =F86=G86 -> FALSE | F86: SM-RPP-Inspector-PrimaCorregida-AgentesAnual | G86: =IF(ISERROR(VLOOKUP(F86,MODIFICACIONES_REALIZADAS!F:H,3,)),F86,VLOOKUP(F86,MODIFICACIONES_REALIZADAS!F:H,3,)) -> SM-O-GEN-Inspector-PrimaCorregida-998-AgentesAnual | H86: 20140101 | I86: 22000101
A87: 1 | B87: 1.1 | C87: INYC_RPI_RESUMEN | D87: SM - Prima Corregida Propia Inspector Total Productos Anual | E87: =F87=G87 -> FALSE | F87: SM-RPP-Inspector-PrimaCorregida-PropiaAnual | G87: =IF(ISERROR(VLOOKUP(F87,MODIFICACIONES_REALIZADAS!F:H,3,)),F87,VLOOKUP(F87,MODIFICACIONES_REALIZADAS!F:H,3,)) -> SM-O-GEN-Inspector-PrimaCorregida-998-PropiaAnual | H87: 20140101 | I87: 22000101
A88: 1 | B88: 1.1 | C88: INYC_RPI_RESUMEN | D88: SM - Prima Corregida Inspector Total Productos Anual | E88: =F88=G88 -> FALSE | F88: SM-RPP-Inspector-PrimaCorregida-TotalAnual | G88: =IF(ISERROR(VLOOKUP(F88,MODIFICACIONES_REALIZADAS!F:H,3,)),F88,VLOOKUP(F88,MODIFICACIONES_REALIZADAS!F:H,3,)) -> SM-O-GEN-Inspector-PrimaCorregida-998-TotalAnual | H88: 20140101 | I88: 22000101
A89: 1 | B89: 1.1 | C89: INYC_RPI_RESUMEN | D89: SM - Nº Pólizas Corregidas Inspector Total Productos Anual | E89: TRUE | F89: SM-O-GEN-Inspector-NumeroPolizasCorregidas-998-TotalAnual | G89: =IF(ISERROR(VLOOKUP(F89,MODIFICACIONES_REALIZADAS!F:H,3,)),F89,VLOOKUP(F89,MODIFICACIONES_REALIZADAS!F:H,3,)) -> SM-O-GEN-Inspector-NumeroPolizasCorregidas-998-TotalAnual | H89: 20180101 | I89: 22000101 | J89: Version 20180119
A90: 1 | B90: 1.1 | C90: INYC_RPI_RESUMEN | D90: SM - Nº Asegurados Inspector Anual | E90: =F90=G90 -> TRUE | F90: SM-O-GEN-Inspector-NumAsegurados-TotalAnual | G90: =IF(ISERROR(VLOOKUP(F90,MODIFICACIONES_REALIZADAS!F:H,3,)),F90,VLOOKUP(F90,MODIFICACIONES_REALIZADAS!F:H,3,)) -> SM-O-GEN-Inspector-NumAsegurados-TotalAnual | H90: 20180101 | I90: 22000101 | J90: Version 20180117
A91: 1 | B91: 1.1 | C91: INYC_RPI_RESUMEN | D91: SM - Consecución Trimestral RRTT | E91: =F91=G91 -> TRUE | F91: SM-RPP-Inspector-ConsecucionTrimestral-001 | G91: =IF(ISERROR(VLOOKUP(F91,MODIFICACIONES_REALIZADAS!F:H,3,)),F91,VLOOKUP(F91,MODIFICACIONES_REALIZADAS!F:H,3,)) -> SM-RPP-Inspector-ConsecucionTrimestral-001 | H91: 20140101 | I91: 22000101
A92: 1 | B92: 1.1 | C92: INYC_RPI_RESUMEN | D92: SM - Consecución Trimestral Hogar | E92: =F92=G92 -> TRUE | F92: SM-RPP-Inspector-ConsecucionTrimestral-002 | G92: =IF(ISERROR(VLOOKUP(F92,MODIFICACIONES_REALIZADAS!F:H,3,)),F92,VLOOKUP(F92,MODIFICACIONES_REALIZADAS!F:H,3,)) -> SM-RPP-Inspector-ConsecucionTrimestral-002 | H92: 20140101 | I92: 22000101
A93: 1 | B93: 1.1 | C93: INYC_RPI_RESUMEN | D93: SM - Consecución Trimestral RRPP | E93: =F93=G93 -> TRUE | F93: SM-RPP-Inspector-ConsecucionTrimestral-906 | G93: =IF(ISERROR(VLOOKUP(F93,MODIFICACIONES_REALIZADAS!F:H,3,)),F93,VLOOKUP(F93,MODIFICACIONES_REALIZADAS!F:H,3,)) -> SM-RPP-Inspector-ConsecucionTrimestral-906 | H93: 20140101 | I93: 22000101
A94: 1 | B94: 1.1 | C94: INYC_RPI_RESUMEN | D94: SM - Consecución Trimestral Total Ramos | E94: =F94=G94 -> TRUE | F94: SM-RPP-Inspector-ConsecucionTrimestral-998 | G94: =IF(ISERROR(VLOOKUP(F94,MODIFICACIONES_REALIZADAS!F:H,3,)),F94,VLOOKUP(F94,MODIFICACIONES_REALIZADAS!F:H,3,)) -> SM-RPP-Inspector-ConsecucionTrimestral-998 | H94: 20140101 | I94: 22000101
A95: 1 | B95: 1.1 | C95: INYC_RPI_RESUMEN | D95: SM - Numero Pólizas Trimestral RRTT | E95: =F95=G95 -> TRUE | F95: SM-RPP-Inspector-NumeroPolizas-001-TotalTrimestre | G95: =IF(ISERROR(VLOOKUP(F95,MODIFICACIONES_REALIZADAS!F:H,3,)),F95,VLOOKUP(F95,MODIFICACIONES_REALIZADAS!F:H,3,)) -> SM-RPP-Inspector-NumeroPolizas-001-TotalTrimestre | H95: 20140101 | I95: 20180301 | J95: Version 20180321
A96: 1 | B96: 1.1 | C96: INYC_RPI_RESUMEN | D96: SM - Numero Pólizas Trimestral Hogar | E96: =F96=G96 -> TRUE | F96: SM-RPP-Inspector-NumeroPolizas-002-TotalTrimestre | G96: =IF(ISERROR(VLOOKUP(F96,MODIFICACIONES_REALIZADAS!F:H,3,)),F96,VLOOKUP(F96,MODIFICACIONES_REALIZADAS!F:H,3,)) -> SM-RPP-Inspector-NumeroPolizas-002-TotalTrimestre | H96: 20140101 | I96: 20180301 | J96: Version 20180321
A97: 1 | B97: 1.1 | C97: INYC_RPI_RESUMEN | D97: SM - Numero Pólizas Trimestral RRPP | E97: =F97=G97 -> TRUE | F97: SM-RPP-Inspector-NumeroPolizas-906-TotalTrimestre | G97: =IF(ISERROR(VLOOKUP(F97,MODIFICACIONES_REALIZADAS!F:H,3,)),F97,VLOOKUP(F97,MODIFICACIONES_REALIZADAS!F:H,3,)) -> SM-RPP-Inspector-NumeroPolizas-906-TotalTrimestre | H97: 20140101 | I97: 20180301 | J97: Version 20180321
A98: 1 | B98: 1.1 | C98: INYC_RPI_RESUMEN | D98: SM - Numero Pólizas Trimestral Total Ramos | E98: =F98=G98 -> TRUE | F98: SM-RPP-Inspector-NumeroPolizas-998-TotalTrimestre | G98: =IF(ISERROR(VLOOKUP(F98,MODIFICACIONES_REALIZADAS!F:H,3,)),F98,VLOOKUP(F98,MODIFICACIONES_REALIZADAS!F:H,3,)) -> SM-RPP-Inspector-NumeroPolizas-998-TotalTrimestre | H98: 20140101 | I98: 20180301 | J98: Version 20180321
A99: 1 | B99: 1.1 | C99: INYC_RPI_RESUMEN | D99: SM - Numero Pólizas Corregidas Trimestral RRTT | E99: =F99=G99 -> TRUE | F99: SM-O-GEN-Inspector-NumeroPolizasCorregidas-001-TotalTrimestre | G99: =IF(ISERROR(VLOOKUP(F99,MODIFICACIONES_REALIZADAS!F:H,3,)),F99,VLOOKUP(F99,MODIFICACIONES_REALIZADAS!F:H,3,)) -> SM-O-GEN-Inspector-NumeroPolizasCorregidas-001-TotalTrimestre | H99: 20180301 | I99: 22000101 | J99: Version 20180321
A100: 1 | B100: 1.1 | C100: INYC_RPI_RESUMEN | D100: SM - Numero Pólizas Corregidas Trimestral Hogar | E100: =F100=G100 -> TRUE | F100: SM-O-GEN-Inspector-NumeroPolizasCorregidas-002-TotalTrimestre | G100: =IF(ISERROR(VLOOKUP(F100,MODIFICACIONES_REALIZADAS!F:H,3,)),F100,VLOOKUP(F100,MODIFICACIONES_REALIZADAS!F:H,3,)) -> SM-O-GEN-Inspector-NumeroPolizasCorregidas-002-TotalTrimestre | H100: 20180301 | I100: 22000101 | J100: Version 20180321
A101: 1 | B101: 1.1 | C101: INYC_RPI_RESUMEN | D101: SM - Numero Pólizas Corregidas Trimestral RRPP | E101: =F101=G101 -> TRUE | F101: SM-O-GEN-Inspector-NumeroPolizasCorregidas-906-TotalTrimestre | G101: =IF(ISERROR(VLOOKUP(F101,MODIFICACIONES_REALIZADAS!F:H,3,)),F101,VLOOKUP(F101,MODIFICACIONES_REALIZADAS!F:H,3,)) -> SM-O-GEN-Inspector-NumeroPolizasCorregidas-906-TotalTrimestre | H101: 20180301 | I101: 22000101 | J101: Version 20180321
A102: 1 | B102: 1.1 | C102: INYC_RPI_RESUMEN | D102: SM - Numero Pólizas Corregidas Trimestral Total Ramos | E102: =F102=G102 -> TRUE | F102: SM-O-GEN-Inspector-NumeroPolizasCorregidas-998-TotalTrimestre | G102: =IF(ISERROR(VLOOKUP(F102,MODIFICACIONES_REALIZADAS!F:H,3,)),F102,VLOOKUP(F102,MODIFICACIONES_REALIZADAS!F:H,3,)) -> SM-O-GEN-Inspector-NumeroPolizasCorregidas-998-TotalTrimestre | H102: 20180301 | I102: 22000101 | J102: Version 20180321
A103: 1 | B103: 1.2 | C103: INYC_RPI_DETALLE | D103: DC - Prima Corregida Anual Total Ramos | E103: =F103=G103 -> FALSE | F103: DC-RPP-Inspector-PrimaCorregida | G103: =IF(ISERROR(VLOOKUP(F103,MODIFICACIONES_REALIZADAS!F:H,3,)),F103,VLOOKUP(F103,MODIFICACIONES_REALIZADAS!F:H,3,)) -> DC-O-GEN-Inspector-PrimaCorregida-998 | H103: 20140101 | I103: 22000101 | J103: Version 20180119
A104: 1 | B104: 1.2 | C104: INYC_RPI_DETALLE | D104: IC - Prima Corregida Anual Total Ramos | E104: =F104=G104 -> FALSE | F104: IC-RPP-Inspector-PrimaCorregida | G104: =IF(ISERROR(VLOOKUP(F104,MODIFICACIONES_REALIZADAS!F:H,3,)),F104,VLOOKUP(F104,MODIFICACIONES_REALIZADAS!F:H,3,)) -> IC-O-GEN-Inspector-PrimaCorregida-998 | H104: 20140101 | I104: 22000101 | J104: Version 20180119
A105: 1 | B105: 1.2 | C105: INYC_RPI_DETALLE | D105: DC - Numero Pólizas Total Ramos | E105: =F105=G105 -> FALSE | F105: DC-GEN-NumeroPolizas-998 | G105: =IF(ISERROR(VLOOKUP(F105,MODIFICACIONES_REALIZADAS!F:H,3,)),F105,VLOOKUP(F105,MODIFICACIONES_REALIZADAS!F:H,3,)) -> DC-O-GEN-Inspector-NumeroPolizas-998 | H105: 20140101 | I105: 22000101 | J105: Version 20180119
A106: 1 | B106: 1.2 | C106: INYC_RPI_DETALLE | D106: IC - Numero Pólizas Total Ramos | E106: =F106=G106 -> FALSE | F106: IC-GEN-NumeroPolizas-998 | G106: =IF(ISERROR(VLOOKUP(F106,MODIFICACIONES_REALIZADAS!F:H,3,)),F106,VLOOKUP(F106,MODIFICACIONES_REALIZADAS!F:H,3,)) -> IC-O-GEN-Inspector-NumeroPolizas-998 | H106: 20140101 | I106: 22000101 | J106: Version 20180119
... A122: 2 | B122: 2.1 | C122: INYC_RAG_RESUMEN | D122: SM - Prima Corregida Inspector Prod. Prioritarios Mensual | E122: =F122=G122 -> TRUE | F122: SM-E-GEN-Inspector-PrimaCorregida-ProdPrioritarios-TotalMes | G122: =IF(ISERROR(VLOOKUP(F122,MODIFICACIONES_REALIZADAS!F:H,3,)),F122,VLOOKUP(F122,MODIFICACIONES_REALIZADAS!F:H,3,)) -> SM-E-GEN-Inspector-PrimaCorregida-ProdPrioritarios-TotalMes | H122: 20140101 | I122: 22000101 | J122: Version 20180117
A123: 2 | B123: 2.1 | C123: INYC_RAG_RESUMEN | D123: SM - Pago Mensual Rappel Primas | E123: =F123=G123 -> TRUE | F123: SM-E-RP2-Inspector-PagoMensual | G123: =IF(ISERROR(VLOOKUP(F123,MODIFICACIONES_REALIZADAS!F:H,3,)),F123,VLOOKUP(F123,MODIFICACIONES_REALIZADAS!F:H,3,)) -> SM-E-RP2-Inspector-PagoMensual | H123: 20140101 | I123: 22000101
A124: 2 | B124: 2.1 | C124: INYC_RAG_RESUMEN | D124: SM - Pago Mensual Superrapel | E124: =F124=G124 -> TRUE | F124: SM-E-SP-Inspector-PagoMensual | G124: =IF(ISERROR(VLOOKUP(F124,MODIFICACIONES_REALIZADAS!F:H,3,)),F124,VLOOKUP(F124,MODIFICACIONES_REALIZADAS!F:H,3,)) -> SM-E-SP-Inspector-PagoMensual | H124: 20140101 | I124: 22000101
A125: 2 | B125: 2.1 | C125: INYC_RAG_RESUMEN | D125: PM - Numero Pólizas 001 Propia | E125: =F125=G125 -> TRUE | F125: PM-E-RP1-Inspector-NumeroPolizas-001 | G125: =IF(ISERROR(VLOOKUP(F125,MODIFICACIONES_REALIZADAS!F:H,3,)),F125,VLOOKUP(F125,MODIFICACIONES_REALIZADAS!F:H,3,)) -> PM-E-RP1-Inspector-NumeroPolizas-001 | H125: 20140101 | I125: 20170101 | J125: OBSOLETO
...

Sheet MODIFICACIONES_REALIZADAS
A1: id | B1: LINEA | C1: TIPO | E1: REGLA VIEJA | F1: NOMBRE SALIDA REGLA VIEJA | G1: REGLA NUEVA | H1: NOMBRE SALIDA REGLA NUEVA | I1: ACCION
A2: 1 | B2: 1 | C2: Inspector | D2: DC | E2: DC-GEN-NumeroPolizas-001 | F2: DC-GEN-NumeroPolizas-001 | G2: DC-O-GEN-Inspector-NumeroPolizas-001 | H2: DC-O-GEN-Inspector-NumeroPolizas-001 | I2: CAMBIO NOMBRE
A3: 2 | B3: 2 | C3: Inspector | D3: DC | E3: DC-GEN-NumeroPolizas-002 | F3: DC-GEN-NumeroPolizas-002 | G3: DC-O-GEN-Inspector-NumeroPolizas-002 | H3: DC-O-GEN-Inspector-NumeroPolizas-002 | I3: CAMBIO NOMBRE
A4: 3 | B4: 1 | C4: Inspector | D4: IC | E4: IC-GEN-NumeroPolizas-001 | F4: IC-GEN-NumeroPolizas-001 | G4: IC-O-GEN-Inspector-NumeroPolizas-001 | H4: IC-O-GEN-Inspector-NumeroPolizas-001 | I4: CAMBIO NOMBRE
A5: 4 | B5: 2 | C5: Inspector | D5: IC | E5: IC-GEN-NumeroPolizas-002 | F5: IC-GEN-NumeroPolizas-002 | G5: IC-O-GEN-Inspector-NumeroPolizas-002 | H5: IC-O-GEN-Inspector-NumeroPolizas-002 | I5: CAMBIO NOMBRE
A6: 5 | B6: 3 | C6: Inspector | D6: DC | G6: DC-O-GEN-Inspector-NumeroPolizas-003 | H6: DC-O-GEN-Inspector-NumeroPolizas-003 | I6: NUEVA
A7: 6 | B7: 4 | C7: Inspector | D7: DC | G7: DC-O-GEN-Inspector-NumeroPolizas-004 | H7: DC-O-GEN-Inspector-NumeroPolizas-004 | I7: NUEVA
A8: 7 | B8: 5 | C8: Inspector | D8: DC | G8: DC-O-GEN-Inspector-NumeroPolizas-005 | H8: DC-O-GEN-Inspector-NumeroPolizas-005 | I8: NUEVA
A9: 8 | B9: 6 | C9: Inspector | D9: DC | G9: DC-O-GEN-Inspector-NumeroPolizas-006 | H9: DC-O-GEN-Inspector-NumeroPolizas-006 | I9: NUEVA
A10: 9 | B10: 7 | C10: Inspector | D10: DC | G10: DC-O-GEN-Inspector-NumeroPolizas-007 | H10: DC-O-GEN-Inspector-NumeroPolizas-007 | I10: NUEVA
A11: 10 | B11: 3 | C11: Inspector | D11: IC | G11: IC-O-GEN-Inspector-NumeroPolizas-003 | H11: IC-O-GEN-Inspector-NumeroPolizas-003 | I11: NUEVA
A12: 11 | B12: 4 | C12: Inspector | D12: IC | G12: IC-O-GEN-Inspector-NumeroPolizas-004 | H12: IC-O-GEN-Inspector-NumeroPolizas-004 | I12: NUEVA
A13: 12 | B13: 5 | C13: Inspector | D13: IC | G13: IC-O-GEN-Inspector-NumeroPolizas-005 | H13: IC-O-GEN-Inspector-NumeroPolizas-005 | I13: NUEVA
A14: 13 | B14: 6 | C14: Inspector | D14: IC | G14: IC-O-GEN-Inspector-NumeroPolizas-006 | H14: IC-O-GEN-Inspector-NumeroPolizas-006 | I14: NUEVA
A15: 14 | B15: 7 | C15: Inspector | D15: IC | G15: IC-O-GEN-Inspector-NumeroPolizas-007 | H15: IC-O-GEN-Inspector-NumeroPolizas-007 | I15: NUEVA
A16: 15 | B16: 9 | C16: Inspector | D16: DC | G16: DC-O-GEN-Inspector-NumeroPolizas-009 | H16: DC-O-GEN-Inspector-NumeroPolizas-009 | I16: NUEVA
A17: 16 | B17: 9 | C17: Inspector | D17: IC | G17: IC-O-GEN-Inspector-NumeroPolizas-009 | H17: IC-O-GEN-Inspector-NumeroPolizas-009 | I17: NUEVA
A18: 17 | B18: 997 | C18: Inspector | D18: DC | E18: DC-O-GEN-Inspector-NumeroPolizas-997 | F18: DC-O-GEN-Inspector-NumeroPolizas-997 | G18: DC-O-GEN-Inspector-NumeroPolizas-998 y GB1 | H18: DC-O-GEN-Inspector-NumeroPolizas-998 | I18: ELIMINAR
A19: 18 | B19: 997 | C19: Inspector | D19: IC | E19: IC-O-GEN-Inspector-NumeroPolizas-997 | F19: IC-O-GEN-Inspector-NumeroPolizas-997 | G19: IC-O-GEN-Inspector-NumeroPolizas-998 y GB1 | H19: IC-O-GEN-Inspector-NumeroPolizas-998 | I19: ELIMINAR
A20: 19 | B20: 998 | C20: Inspector | D20: DC | E20: DC-GEN-NumeroPolizas-998 | F20: DC-GEN-NumeroPolizas-998 | G20: DC-O-GEN-Inspector-NumeroPolizas-998 | H20: DC-O-GEN-Inspector-NumeroPolizas-998 | I20: CAMBIO NOMBRE
A21: 20 | B21: 998 | C21: Inspector | D21: IC | E21: IC-GEN-NumeroPolizas-998 | F21: IC-GEN-NumeroPolizas-998 | G21: IC-O-GEN-Inspector-NumeroPolizas-998 | H21: IC-O-GEN-Inspector-NumeroPolizas-998 | I21: CAMBIO NOMBRE
A22: 21 | B22: 1 | C22: Inspector | D22: PM | E22: PM-GEN-NumeroPolizas-001-Agentes | F22: PM-GEN-NumeroPolizas-001-Agentes | G22: PM-O-GEN-Inspector-NumeroPolizas-001-Agentes | H22: PM-O-GEN-Inspector-NumeroPolizas-001-Agentes | I22: CAMBIO NOMBRE
A23: 22 | B23: 1 | C23: Inspector | D23: PM | E23: PM-GEN-NumeroPolizas-001 | F23: PM-GEN-NumeroPolizas-001 | G23: PM-O-GEN-Inspector-NumeroPolizas-001 | H23: PM-O-GEN-Inspector-NumeroPolizas-001 | I23: CAMBIO NOMBRE
A24: 23 | B24: 2 | C24: Inspector | D24: PM | E24: PM-GEN-NumeroPolizas-002-Agentes | F24: PM-GEN-NumeroPolizas-002-Agentes | G24: PM-O-GEN-Inspector-NumeroPolizas-002-Agentes | H24: PM-O-GEN-Inspector-NumeroPolizas-002-Agentes | I24: CAMBIO NOMBRE
A25: 24 | B25: 2 | C25: Inspector | D25: PM | E25: PM-GEN-NumeroPolizas-002 | F25: PM-GEN-NumeroPolizas-002 | G25: PM-O-GEN-Inspector-NumeroPolizas-002 | H25: PM-O-GEN-Inspector-NumeroPolizas-002 | I25: CAMBIO NOMBRE
A26: 25 | B26: 3 | C26: Inspector | D26: PM | G26: PM-O-GEN-Inspector-NumeroPolizas-003-Agentes | H26: PM-O-GEN-Inspector-NumeroPolizas-003-Agentes | I26: NUEVA
A27: 26 | B27: 3 | C27: Inspector | D27: PM | G27: PM-O-GEN-Inspector-NumeroPolizas-003 | H27: PM-O-GEN-Inspector-NumeroPolizas-003 | I27: NUEVA
A28: 27 | B28: 4 | C28: Inspector | D28: PM | G28: PM-O-GEN-Inspector-NumeroPolizas-004-Agentes | H28: PM-O-GEN-Inspector-NumeroPolizas-004-Agentes | I28: NUEVA
A29: 28 | B29: 4 | C29: Inspector | D29: PM | G29: PM-O-GEN-Inspector-NumeroPolizas-004 | H29: PM-O-GEN-Inspector-NumeroPolizas-004 | I29: NUEVA
A30: 29 | B30: 5 | C30: Inspector | D30: PM | G30: PM-O-GEN-Inspector-NumeroPolizas-006-Agentes | H30: PM-O-GEN-Inspector-NumeroPolizas-006-Agentes | I30: NUEVA
A31: 30 | B31: 5 | C31: Inspector | D31: PM | G31: PM-O-GEN-Inspector-NumeroPolizas-005 | H31: PM-O-GEN-Inspector-NumeroPolizas-005 | I31: NUEVA
A32: 31 | B32: 6 | C32: Inspector | D32: PM | G32: PM-O-GEN-Inspector-NumeroPolizas-006-Agentes | H32: PM-O-GEN-Inspector-NumeroPolizas-006-Agentes | I32: NUEVA
A33: 32 | B33: 6 | C33: Inspector | D33: PM | G33: PM-O-GEN-Inspector-NumeroPolizas-006 | H33: PM-O-GEN-Inspector-NumeroPolizas-006 | I33: NUEVA
A34: 33 | B34: 7 | C34: Inspector | D34: PM | G34: PM-O-GEN-Inspector-NumeroPolizas-007-Agentes | H34: PM-O-GEN-Inspector-NumeroPolizas-007-Agentes | I34: NUEVA
A35: 34 | B35: 7 | C35: Inspector | D35: PM | G35: PM-O-GEN-Inspector-NumeroPolizas-007 | H35: PM-O-GEN-Inspector-NumeroPolizas-007 | I35: NUEVA
A36: 35 | B36: 9 | C36: Inspector | D36: PM | G36: PM-O-GEN-Inspector-NumeroPolizas-009-Agentes | H36: PM-O-GEN-Inspector-NumeroPolizas-009-Agentes | I36: NUEVA
A37: 36 | B37: 9 | C37: Inspector | D37: PM | G37: PM-O-GEN-Inspector-NumeroPolizas-009 | H37: PM-O-GEN-Inspector-NumeroPolizas-009 | I37: NUEVA
A38: 37 | B38: 998 | C38: Inspector | D38: PM | E38: PM-GEN-NumeroPolizas-998-Agentes | F38: PM-GEN-NumeroPolizas-998-Agentes | G38: PM-O-GEN-Inspector-NumeroPolizas-998-Agentes | H38: PM-O-GEN-Inspector-NumeroPolizas-998-Agentes | I38: CAMBIO NOMBRE
A39: 38 | B39: 998 | C39: Inspector | D39: PM | E39: PM-GEN-NumeroPolizas-998 | F39: PM-GEN-NumeroPolizas-998 | G39: PM-O-GEN-Inspector-NumeroPolizas-998 | H39: PM-O-GEN-Inspector-NumeroPolizas-998 | I39: CAMBIO NOMBRE
A40: 39 | B40: 1 | C40: Inspector | D40: SM | E40: SM-RPP-Inspector-NumeroPolizas-001-TotalMes | F40: SM-RPP-Inspector-NumeroPolizas-001-Propia | G40: SM-O-GEN-Inspector-NumeroPolizas-001-TotalMes | H40: SM-O-GEN-Inspector-NumeroPolizas-001-Propia | I40: CAMBIO NOMBRE
A41: 40 | B41: 1 | C41: Inspector | D41: SM | E41: SM-RPP-Inspector-NumeroPolizas-001-TotalMes | F41: SM-RPP-Inspector-NumeroPolizas-001-Agentes | G41: SM-O-GEN-Inspector-NumeroPolizas-001-TotalMes | H41: SM-O-GEN-Inspector-NumeroPolizas-001-Agentes | I41: CAMBIO NOMBRE
A42: 41 | B42: 1 | C42: Inspector | D42: SM | E42: SM-RPP-Inspector-NumeroPolizas-001-TotalMes | F42: SM-RPP-Inspector-NumeroPolizas-001-TotalMes | G42: SM-O-GEN-Inspector-NumeroPolizas-001-TotalMes | H42: SM-O-GEN-Inspector-NumeroPolizas-001-TotalMes | I42: CAMBIO NOMBRE
A43: 42 | B43: 2 | C43: Inspector | D43: SM | E43: SM-RPP-Inspector-NumeroPolizas-002-TotalMes | F43: SM-RPP-Inspector-NumeroPolizas-002-Propia | G43: SM-O-GEN-Inspector-NumeroPolizas-002-TotalMes | H43: SM-O-GEN-Inspector-NumeroPolizas-002-Propia | I43: CAMBIO NOMBRE
A44: 43 | B44: 2 | C44: Inspector | D44: SM | E44: SM-RPP-Inspector-NumeroPolizas-002-TotalMes | F44: SM-RPP-Inspector-NumeroPolizas-002-Agentes | G44: SM-O-GEN-Inspector-NumeroPolizas-002-TotalMes | H44: SM-O-GEN-Inspector-NumeroPolizas-002-Agentes | I44: CAMBIO NOMBRE
A45: 44 | B45: 2 | C45: Inspector | D45: SM | E45: SM-RPP-Inspector-NumeroPolizas-002-TotalMes | F45: SM-RPP-Inspector-NumeroPolizas-002-TotalMes | G45: SM-O-GEN-Inspector-NumeroPolizas-002-TotalMes | H45: SM-O-GEN-Inspector-NumeroPolizas-002-TotalMes | I45: CAMBIO NOMBRE
A46: 45 | B46: 3 | C46: Inspector | D46: SM | G46: SM-O-GEN-Inspector-NumeroPolizas-003-TotalMes | H46: SM-O-GEN-Inspector-NumeroPolizas-003-TotalMes | I46: NUEVA
A47: 46 | B47: 4 | C47: Inspector | D47: SM | G47: SM-O-GEN-Inspector-NumeroPolizas-004-TotalMes | H47: SM-O-GEN-Inspector-NumeroPolizas-004-TotalMes | I47: NUEVA
A48: 47 | B48: 5 | C48: Inspector | D48: SM | G48: SM-O-GEN-Inspector-NumeroPolizas-005-TotalMes | H48: SM-O-GEN-Inspector-NumeroPolizas-005-TotalMes | I48: NUEVA
A49: 48 | B49: 6 | C49: Inspector | D49: SM | G49: SM-O-GEN-Inspector-NumeroPolizas-006-TotalMes | H49: SM-O-GEN-Inspector-NumeroPolizas-006-TotalMes | I49: NUEVA
A50: 49 | B50: 7 | C50: Inspector | D50: SM | G50: SM-O-GEN-Inspector-NumeroPolizas-007-TotalMes | H50: SM-O-GEN-Inspector-NumeroPolizas-007-TotalMes | I50: NUEVA
A51: 50 | B51: 9 | C51: Inspector | D51: SM | G51: SM-O-GEN-Inspector-NumeroPolizas-009-TotalMes | H51: SM-O-GEN-Inspector-NumeroPolizas-009-TotalMes | I51: NUEVA
A52: 51 | B52: 998 | C52: Inspector | D52: SM | E52: SM-RPP-Inspector-NumeroPolizas-998-TotalMes | F52: SM-RPP-Inspector-NumeroPolizas-998-Propia | G52: SM-O-GEN-Inspector-NumeroPolizas-998-TotalMes | H52: SM-O-GEN-Inspector-NumeroPolizas-998-Propia | I52: CAMBIO NOMBRE
A53: 52 | B53: 998 | C53: Inspector | D53: SM | E53: SM-RPP-Inspector-NumeroPolizas-998-TotalMes | F53: SM-RPP-Inspector-NumeroPolizas-998-Agentes | G53: SM-O-GEN-Inspector-NumeroPolizas-998-TotalMes | H53: SM-O-GEN-Inspector-NumeroPolizas-998-Agentes | I53: CAMBIO NOMBRE
A54: 53 | B54: 998 | C54: Inspector | D54: SM | E54: SM-RPP-Inspector-NumeroPolizas-998-TotalMes | F54: SM-RPP-Inspector-NumeroPolizas-998-TotalMes | G54: SM-O-GEN-Inspector-NumeroPolizas-998-TotalMes | H54: SM-O-GEN-Inspector-NumeroPolizas-998-TotalMes | I54: CAMBIO NOMBRE
A55: 54 | B55: 998 | C55: Inspector | D55: DC | E55: DC-RPP-Inspector-PrimaCorregida | F55: DC-RPP-Inspector-PrimaCorregida | G55: DC-O-GEN-Inspector-PrimaCorregida-998 | H55: DC-O-GEN-Inspector-PrimaCorregida-998 | I55: CAMBIO NOMBRE
A56: 55 | B56: 998 | C56: Inspector | D56: IC | E56: IC-RPP-Inspector-PrimaCorregida | F56: IC-RPP-Inspector-PrimaCorregida | G56: IC-O-GEN-Inspector-PrimaCorregida-998 | H56: IC-O-GEN-Inspector-PrimaCorregida-998 | I56: CAMBIO NOMBRE
A57: 56 | B57: 998 | C57: Inspector | D57: PM | E57: PM-RPP-Inspector-PrimaCorregida-Agentes | F57: PM-RPP-Inspector-PrimaCorregida-Agentes | G57: PM-O-GEN-Inspector-PrimaCorregida-998-Agentes | H57: PM-O-GEN-Inspector-PrimaCorregida-998-Agentes | I57: CAMBIO NOMBRE
A58: 57 | B58: 998 | C58: Inspector | D58: PM | G58: PM-O-GEN-Inspector-PrimaCorregida-998-Agentes | H58: PM-O-GEN-Inspector-Prima-998-Agentes | I58: NUEVA
A59: 58 | B59: 998 | C59: Inspector | D59: PM | E59: PM-RPP-Inspector-PrimaCorregida | F59: PM-RPP-Inspector-PrimaCorregida | G59: PM-O-GEN-Inspector-PrimaCorregida-998 | H59: PM-O-GEN-Inspector-PrimaCorregida-998 | I59: CAMBIO NOMBRE
A60: 59 | B60: 998 | C60: Inspector | D60: PM | G60: PM-O-GEN-Inspector-PrimaCorregida-998 | H60: PM-O-GEN-Inspector-Prima-998 | I60: NUEVA
A61: 60 | B61: 1 | C61: Inspector | D61: PM | E61: PM-O-GEN-Inspector-PrimaCorregida-001-Agentes | F61: PM-O-GEN-Inspector-PrimaCorregida-001-Agentes | G61: PM-O-GEN-Inspector-PrimaCorregida-001-Agentes | H61: PM-O-GEN-Inspector-PrimaCorregida-001-Agentes | I61: IGUAL
A62: 61 | B62: 1 | C62: Inspector | D62: PM | G62: PM-O-GEN-Inspector-PrimaCorregida-001-Agentes | H62: PM-O-GEN-Inspector-Prima-001-Agentes | I62: NUEVA
A63: 62 | B63: 1 | C63: Inspector | D63: PM | E63: PM-O-GEN-Inspector-PrimaCorregida-001 | F63: PM-O-GEN-Inspector-PrimaCorregida-001 | G63: PM-O-GEN-Inspector-PrimaCorregida-001 | H63: PM-O-GEN-Inspector-PrimaCorregida-001 | I63: IGUAL
A64: 63 | B64: 1 | C64: Inspector | D64: PM | G64: PM-O-GEN-Inspector-PrimaCorregida-001 | H64: PM-O-GEN-Inspector-Prima-001 | I64: NUEVA
A65: 64 | B65: 2 | C65: Inspector | D65: PM | E65: PM-O-GEN-Inspector-PrimaCorregida-002-Agentes | F65: PM-O-GEN-Inspector-PrimaCorregida-002-Agentes | G65: PM-O-GEN-Inspector-PrimaCorregida-002-Agentes | H65: PM-O-GEN-Inspector-PrimaCorregida-002-Agentes | I65: IGUAL
A66: 65 | B66: 2 | C66: Inspector | D66: PM | G66: PM-O-GEN-Inspector-PrimaCorregida-002-Agentes | H66: PM-O-GEN-Inspector-Prima-002-Agentes | I66: NUEVA
A67: 66 | B67: 2 | C67: Inspector | D67: PM | E67: PM-O-GEN-Inspector-PrimaCorregida-002 | F67: PM-O-GEN-Inspector-PrimaCorregida-002 | G67: PM-O-GEN-Inspector-PrimaCorregida-002 | H67: PM-O-GEN-Inspector-PrimaCorregida-002 | I67: IGUAL
A68: 67 | B68: 2 | C68: Inspector | D68: PM | G68: PM-O-GEN-Inspector-PrimaCorregida-002 | H68: PM-O-GEN-Inspector-Prima-002 | I68: NUEVA
A69: 68 | B69: 3 | C69: Inspector | D69: PM | E69: PM-O-GEN-Inspector-PrimaCorregida-003-Agentes | F69: PM-O-GEN-Inspector-PrimaCorregida-003-Agentes | G69: PM-O-GEN-Inspector-PrimaCorregida-003-Agentes | H69: PM-O-GEN-Inspector-PrimaCorregida-003-Agentes | I69: IGUAL
A70: 69 | B70: 3 | C70: Inspector | D70: PM | G70: PM-O-GEN-Inspector-PrimaCorregida-003-Agentes | H70: PM-O-GEN-Inspector-Prima-003-Agentes | I70: NUEVA
A71: 70 | B71: 3 | C71: Inspector | D71: PM | E71: PM-O-GEN-Inspector-PrimaCorregida-003 | F71: PM-O-GEN-Inspector-PrimaCorregida-003 | G71: PM-O-GEN-Inspector-PrimaCorregida-003 | H71: PM-O-GEN-Inspector-PrimaCorregida-003 | I71: IGUAL
A72: 71 | B72: 3 | C72: Inspector | D72: PM | G72: PM-O-GEN-Inspector-PrimaCorregida-003 | H72: PM-O-GEN-Inspector-Prima-003 | I72: NUEVA
A73: 72 | B73: 4 | C73: Inspector | D73: PM | E73: PM-O-GEN-Inspector-PrimaCorregida-004-Agentes | F73: PM-O-GEN-Inspector-PrimaCorregida-004-Agentes | G73: PM-O-GEN-Inspector-PrimaCorregida-004-Agentes | H73: PM-O-GEN-Inspector-PrimaCorregida-004-Agentes | I73: IGUAL
A74: 73 | B74: 4 | C74: Inspector | D74: PM | G74: PM-O-GEN-Inspector-PrimaCorregida-004-Agentes | H74: PM-O-GEN-Inspector-Prima-004-Agentes | I74: NUEVA
A75: 74 | B75: 4 | C75: Inspector | D75: PM | E75: PM-O-GEN-Inspector-PrimaCorregida-004 | F75: PM-O-GEN-Inspector-PrimaCorregida-004 | G75: PM-O-GEN-Inspector-PrimaCorregida-004 | H75: PM-O-GEN-Inspector-PrimaCorregida-004 | I75: IGUAL
A76: 75 | B76: 4 | C76: Inspector | D76: PM | G76: PM-O-GEN-Inspector-PrimaCorregida-004 | H76: PM-O-GEN-Inspector-Prima-004 | I76: NUEVA
A77: 76 | B77: 5 | C77: Inspector | D77: PM | E77: PM-O-GEN-Inspector-PrimaCorregida-005-Agentes | F77: PM-O-GEN-Inspector-PrimaCorregida-005-Agentes | G77: PM-O-GEN-Inspector-PrimaCorregida-005-Agentes | H77: PM-O-GEN-Inspector-PrimaCorregida-005-Agentes | I77: IGUAL
A78: 77 | B78: 5 | C78: Inspector | D78: PM | G78: PM-O-GEN-Inspector-PrimaCorregida-005-Agentes | H78: PM-O-GEN-Inspector-Prima-005-Agentes | I78: NUEVA
A79: 78 | B79: 5 | C79: Inspector | D79: PM | E79: PM-O-GEN-Inspector-PrimaCorregida-005 | F79: PM-O-GEN-Inspector-PrimaCorregida-005 | G79: PM-O-GEN-Inspector-PrimaCorregida-005 | H79: PM-O-GEN-Inspector-PrimaCorregida-005 | I79: IGUAL
A80: 79 | B80: 5 | C80: Inspector | D80: PM | G80: PM-O-GEN-Inspector-PrimaCorregida-005 | H80: PM-O-GEN-Inspector-Prima-005 | I80: NUEVA
A81: 80 | B81: 6 | C81: Inspector | D81: PM | E81: PM-O-GEN-Inspector-PrimaCorregida-006-Agentes | F81: PM-O-GEN-Inspector-PrimaCorregida-006-Agentes | G81: PM-O-GEN-Inspector-PrimaCorregida-006-Agentes | H81: PM-O-GEN-Inspector-PrimaCorregida-006-Agentes | I81: IGUAL
A82: 81 | B82: 6 | C82: Inspector | D82: PM | G82: PM-O-GEN-Inspector-PrimaCorregida-006-Agentes | H82: PM-O-GEN-Inspector-Prima-006-Agentes | I82: NUEVA
A83: 82 | B83: 6 | C83: Inspector | D83: PM | E83: PM-O-GEN-Inspector-PrimaCorregida-006 | F83: PM-O-GEN-Inspector-PrimaCorregida-006 | G83: PM-O-GEN-Inspector-PrimaCorregida-006 | H83: PM-O-GEN-Inspector-PrimaCorregida-006 | I83: IGUAL
A84: 83 | B84: 6 | C84: Inspector | D84: PM | G84: PM-O-GEN-Inspector-PrimaCorregida-006 | H84: PM-O-GEN-Inspector-Prima-006 | I84: NUEVA
A85: 84 | B85: 7 | C85: Inspector | D85: PM | E85: PM-O-GEN-Inspector-PrimaCorregida-007-Agentes | F85: PM-O-GEN-Inspector-PrimaCorregida-007-Agentes | G85: PM-O-GEN-Inspector-PrimaCorregida-007-Agentes | H85: PM-O-GEN-Inspector-PrimaCorregida-007-Agentes | I85: IGUAL
A86: 85 | B86: 7 | C86: Inspector | D86: PM | G86: PM-O-GEN-Inspector-PrimaCorregida-007-Agentes | H86: PM-O-GEN-Inspector-Prima-007-Agentes | I86: NUEVA
A87: 86 | B87: 7 | C87: Inspector | D87: PM | E87: PM-O-GEN-Inspector-PrimaCorregida-007 | F87: PM-O-GEN-Inspector-PrimaCorregida-007 | G87: PM-O-GEN-Inspector-PrimaCorregida-007 | H87: PM-O-GEN-Inspector-PrimaCorregida-007 | I87: IGUAL
A88: 87 | B88: 7 | C88: Inspector | D88: PM | G88: PM-O-GEN-Inspector-PrimaCorregida-007 | H88: PM-O-GEN-Inspector-Prima-007 | I88: NUEVA
A89: 88 | B89: 8 | C89: Inspector | D89: PM | E89: PM-O-GEN-Inspector-PrimaCorregida-008-Agentes | F89: PM-O-GEN-Inspector-PrimaCorregida-008-Agentes | G89: PM-O-GEN-Inspector-PrimaCorregida-008-Agentes | H89: PM-O-GEN-Inspector-PrimaCorregida-008-Agentes | I89: IGUAL
A90: 89 | B90: 8 | C90: Inspector | D90: PM | G90: PM-O-GEN-Inspector-PrimaCorregida-008-Agentes | H90: PM-O-GEN-Inspector-Prima-008-Agentes | I90: NUEVA
A91: 90 | B91: 8 | C91: Inspector | D91: PM | E91: PM-O-GEN-Inspector-PrimaCorregida-008 | F91: PM-O-GEN-Inspector-PrimaCorregida-008 | G91: PM-O-GEN-Inspector-PrimaCorregida-008 | H91: PM-O-GEN-Inspector-PrimaCorregida-008 | I91: IGUAL
A92: 91 | B92: 8 | C92: Inspector | D92: PM | G92: PM-O-GEN-Inspector-PrimaCorregida-008 | H92: PM-O-GEN-Inspector-Prima-008 | I92: NUEVA
A93: 92 | B93: 9 | C93: Inspector | D93: PM | E93: PM-O-GEN-Inspector-PrimaCorregida-009-Agentes | F93: PM-O-GEN-Inspector-PrimaCorregida-009-Agentes | G93: PM-O-GEN-Inspector-PrimaCorregida-009-Agentes | H93: PM-O-GEN-Inspector-PrimaCorregida-009-Agentes | I93: IGUAL
A94: 93 | B94: 9 | C94: Inspector | D94: PM | G94: PM-O-GEN-Inspector-PrimaCorregida-009-Agentes | H94: PM-O-GEN-Inspector-Prima-009-Agentes | I94: NUEVA
A95: 94 | B95: 9 | C95: Inspector | D95: PM | E95: PM-O-GEN-Inspector-PrimaCorregida-009 | F95: PM-O-GEN-Inspector-PrimaCorregida-009 | G95: PM-O-GEN-Inspector-PrimaCorregida-009 | H95: PM-O-GEN-Inspector-PrimaCorregida-009 | I95: IGUAL
A96: 95 | B96: 9 | C96: Inspector | D96: PM | G96: PM-O-GEN-Inspector-PrimaCorregida-009 | H96: PM-O-GEN-Inspector-Prima-009 | I96: NUEVA
A97: 96 | B97: 997 | C97: Inspector | D97: PM | E97: PM-O-GEN-Inspector-PrimaCorregida-997-Agentes | F97: PM-O-GEN-Inspector-PrimaCorregida-997-Agentes | G97: PM-O-GEN-Inspector-PrimaCorregida-997-Agentes | H97: PM-O-GEN-Inspector-PrimaCorregida-997-Agentes | I97: IGUAL
A98: 97 | B98: 997 | C98: Inspector | D98: PM | G98: PM-O-GEN-Inspector-PrimaCorregida-997-Agentes | H98: PM-O-GEN-Inspector-Prima-997-Agentes | I98: NUEVA
A99: 98 | B99: 997 | C99: Inspector | D99: PM | E99: PM-O-GEN-Inspector-PrimaCorregida-997 | F99: PM-O-GEN-Inspector-PrimaCorregida-997 | G99: PM-O-GEN-Inspector-PrimaCorregida-997 | H99: PM-O-GEN-Inspector-PrimaCorregida-997 | I99: IGUAL
A100: 99 | B100: 997 | C100: Inspector | D100: PM | G100: PM-O-GEN-Inspector-PrimaCorregida-997 | H100: PM-O-GEN-Inspector-Prima-997 | I100: NUEVA
...

Sheet INSERT REGLAS
A1: =IF(REGLAS!J2="OBSOLETO","","INSERT INTO INYCEXT.INYC_CONF_INF_REGLAS (COD_INFORME,TABLA,NOMBRE,REGLA,F_INICIO,F_FIN,DESCRIPCION) VALUES ("&REGLAS!B2&",'"&REGLAS!C2&"','"&REGLAS!D2&"','"&REGLAS!G2&"',TO_DATE('"&REGLAS!H2&"','yyyymmdd'),TO_DATE('"&REGLAS!I2&"','yyyymmdd'),'"&REGLAS!J2&"');") -> INSERT INTO INYCEXT.INYC_CONF_INF_REGLAS (COD_INFORME,TABLA,NOMBRE,REGLA,F_INICIO,F_FIN,DESCRIPCION) VALUES (1.1,'INYC_RPI_RESUMEN','SM - Objetivo Anual RRTT','SM-O-RPP-Inspector-ObjetivoAnual-NumPolizas-001',TO_DATE('20140101','yyyymmdd'),TO_DATE('22000101','yyyymmdd'),''); | B1: =IF(REGLAS!J2="OBSOLETO","","INSERT INTO INYCEXT.INYC_CONF_INF_REGLAS@tc_link (COD_INFORME,TABLA,NOMBRE,REGLA,F_INICIO,F_FIN,DESCRIPCION) VALUES ("&REGLAS!B2&",'"&REGLAS!C2&"','"&REGLAS!D2&"','"&REGLAS!G2&"',TO_DATE('"&REGLAS!H2&"','yyyymmdd'),TO_DATE('"&REGLAS!I2&"','yyyymmdd'),'"&REGLAS!J2&"');") -> INSERT INTO INYCEXT.INYC_CONF_INF_REGLAS@tc_link (COD_INFORME,TABLA,NOMBRE,REGLA,F_INICIO,F_FIN,DESCRIPCION) VALUES (1.1,'INYC_RPI_RESUMEN','SM - Objetivo Anual RRTT','SM-O-RPP-Inspector-ObjetivoAnual-NumPolizas-001',TO_DATE('20140101','yyyymmdd'),TO_DATE('22000101','yyyymmdd'),'');
A2: =IF(REGLAS!J3="OBSOLETO","","INSERT INTO INYCEXT.INYC_CONF_INF_REGLAS (COD_INFORME,TABLA,NOMBRE,REGLA,F_INICIO,F_FIN,DESCRIPCION) VALUES ("&REGLAS!B3&",'"&REGLAS!C3&"','"&REGLAS!D3&"','"&REGLAS!G3&"',TO_DATE('"&REGLAS!H3&"','yyyymmdd'),TO_DATE('"&REGLAS!I3&"','yyyymmdd'),'"&REGLAS!J3&"');") -> INSERT INTO INYCEXT.INYC_CONF_INF_REGLAS (COD_INFORME,TABLA,NOMBRE,REGLA,F_INICIO,F_FIN,DESCRIPCION) VALUES (1.1,'INYC_RPI_RESUMEN','SM - Objetivo Anual Hogar','SM-O-RPP-Inspector-ObjetivoAnual-NumPolizas-002',TO_DATE('20140101','yyyymmdd'),TO_DATE('22000101','yyyymmdd'),''); | B2: =IF(REGLAS!J3="OBSOLETO","","INSERT INTO INYCEXT.INYC_CONF_INF_REGLAS@tc_link (COD_INFORME,TABLA,NOMBRE,REGLA,F_INICIO,F_FIN,DESCRIPCION) VALUES ("&REGLAS!B3&",'"&REGLAS!C3&"','"&REGLAS!D3&"','"&REGLAS!G3&"',TO_DATE('"&REGLAS!H3&"','yyyymmdd'),TO_DATE('"&REGLAS!I3&"','yyyymmdd'),'"&REGLAS!J3&"');") -> INSERT INTO INYCEXT.INYC_CONF_INF_REGLAS@tc_link (COD_INFORME,TABLA,NOMBRE,REGLA,F_INICIO,F_FIN,DESCRIPCION) VALUES (1.1,'INYC_RPI_RESUMEN','SM - Objetivo Anual Hogar','SM-O-RPP-Inspector-ObjetivoAnual-NumPolizas-002',TO_DATE('20140101','yyyymmdd'),TO_DATE('22000101','yyyymmdd'),'');
A3: =IF(REGLAS!J4="OBSOLETO","","INSERT INTO INYCEXT.INYC_CONF_INF_REGLAS (COD_INFORME,TABLA,NOMBRE,REGLA,F_INICIO,F_FIN,DESCRIPCION) VALUES ("&REGLAS!B4&",'"&REGLAS!C4&"','"&REGLAS!D4&"','"&REGLAS!G4&"',TO_DATE('"&REGLAS!H4&"','yyyymmdd'),TO_DATE('"&REGLAS!I4&"','yyyymmdd'),'"&REGLAS!J4&"');") -> INSERT INTO INYCEXT.INYC_CONF_INF_REGLAS (COD_INFORME,TABLA,NOMBRE,REGLA,F_INICIO,F_FIN,DESCRIPCION) VALUES (1.1,'INYC_RPI_RESUMEN','SM - Objetivo Anual RRPP','SM-O-RPP-Inspector-ObjetivoAnual-NumPolizas-906',TO_DATE('20140101','yyyymmdd'),TO_DATE('22000101','yyyymmdd'),''); | B3: =IF(REGLAS!J4="OBSOLETO","","INSERT INTO INYCEXT.INYC_CONF_INF_REGLAS@tc_link (COD_INFORME,TABLA,NOMBRE,REGLA,F_INICIO,F_FIN,DESCRIPCION) VALUES ("&REGLAS!B4&",'"&REGLAS!C4&"','"&REGLAS!D4&"','"&REGLAS!G4&"',TO_DATE('"&REGLAS!H4&"','yyyymmdd'),TO_DATE('"&REGLAS!I4&"','yyyymmdd'),'"&REGLAS!J4&"');") -> INSERT INTO INYCEXT.INYC_CONF_INF_REGLAS@tc_link (COD_INFORME,TABLA,NOMBRE,REGLA,F_INICIO,F_FIN,DESCRIPCION) VALUES (1.1,'INYC_RPI_RESUMEN','SM - Objetivo Anual RRPP','SM-O-RPP-Inspector-ObjetivoAnual-NumPolizas-906',TO_DATE('20140101','yyyymmdd'),TO_DATE('22000101','yyyymmdd'),'');
A4: =IF(REGLAS!J5="OBSOLETO","","INSERT INTO INYCEXT.INYC_CONF_INF_REGLAS (COD_INFORME,TABLA,NOMBRE,REGLA,F_INICIO,F_FIN,DESCRIPCION) VALUES ("&REGLAS!B5&",'"&REGLAS!C5&"','"&REGLAS!D5&"','"&REGLAS!G5&"',TO_DATE('"&REGLAS!H5&"','yyyymmdd'),TO_DATE('"&REGLAS!I5&"','yyyymmdd'),'"&REGLAS!J5&"');") -> INSERT INTO INYCEXT.INYC_CONF_INF_REGLAS (COD_INFORME,TABLA,NOMBRE,REGLA,F_INICIO,F_FIN,DESCRIPCION) VALUES (1.1,'INYC_RPI_RESUMEN','SM - Objetivo Anual Total Ramos','SM-O-RPP-Inspector-ObjetivoAnual-NumPolizas-998',TO_DATE('20140101','yyyymmdd'),TO_DATE('22000101','yyyymmdd'),''); | B4: =IF(REGLAS!J5="OBSOLETO","","INSERT INTO INYCEXT.INYC_CONF_INF_REGLAS@tc_link (COD_INFORME,TABLA,NOMBRE,REGLA,F_INICIO,F_FIN,DESCRIPCION) VALUES ("&REGLAS!B5&",'"&REGLAS!C5&"','"&REGLAS!D5&"','"&REGLAS!G5&"',TO_DATE('"&REGLAS!H5&"','yyyymmdd'),TO_DATE('"&REGLAS!I5&"','yyyymmdd'),'"&REGLAS!J5&"');") -> INSERT INTO INYCEXT.INYC_CONF_INF_REGLAS@tc_link (COD_INFORME,TABLA,NOMBRE,REGLA,F_INICIO,F_FIN,DESCRIPCION) VALUES (1.1,'INYC_RPI_RESUMEN','SM - Objetivo Anual Total Ramos','SM-O-RPP-Inspector-ObjetivoAnual-NumPolizas-998',TO_DATE('20140101','yyyymmdd'),TO_DATE('22000101','yyyymmdd'),'');
A5: =IF(REGLAS!J6="OBSOLETO","","INSERT INTO INYCEXT.INYC_CONF_INF_REGLAS (COD_INFORME,TABLA,NOMBRE,REGLA,F_INICIO,F_FIN,DESCRIPCION) VALUES ("&REGLAS!B6&",'"&REGLAS!C6&"','"&REGLAS!D6&"','"&REGLAS!G6&"',TO_DATE('"&REGLAS!H6&"','yyyymmdd'),TO_DATE('"&REGLAS!I6&"','yyyymmdd'),'"&REGLAS!J6&"');") -> INSERT INTO INYCEXT.INYC_CONF_INF_REGLAS (COD_INFORME,TABLA,NOMBRE,REGLA,F_INICIO,F_FIN,DESCRIPCION) VALUES (1.1,'INYC_RPI_RESUMEN','SM - Objetivo Único Anual PC','SM-O-RPP-Inspector-ObjetivoUnicoAnual-PrimaCorregida',TO_DATE('20140101','yyyymmdd'),TO_DATE('22000101','yyyymmdd'),''); | B5: =IF(REGLAS!J6="OBSOLETO","","INSERT INTO INYCEXT.INYC_CONF_INF_REGLAS@tc_link (COD_INFORME,TABLA,NOMBRE,REGLA,F_INICIO,F_FIN,DESCRIPCION) VALUES ("&REGLAS!B6&",'"&REGLAS!C6&"','"&REGLAS!D6&"','"&REGLAS!G6&"',TO_DATE('"&REGLAS!H6&"','yyyymmdd'),TO_DATE('"&REGLAS!I6&"','yyyymmdd'),'"&REGLAS!J6&"');") -> INSERT INTO INYCEXT.INYC_CONF_INF_REGLAS@tc_link (COD_INFORME,TABLA,NOMBRE,REGLA,F_INICIO,F_FIN,DESCRIPCION) VALUES (1.1,'INYC_RPI_RESUMEN','SM - Objetivo Único Anual PC','SM-O-RPP-Inspector-ObjetivoUnicoAnual-PrimaCorregida',TO_DATE('20140101','yyyymmdd'),TO_DATE('22000101','yyyymmdd'),'');
A6: =IF(REGLAS!J7="OBSOLETO","","INSERT INTO INYCEXT.INYC_CONF_INF_REGLAS (COD_INFORME,TABLA,NOMBRE,REGLA,F_INICIO,F_FIN,DESCRIPCION) VALUES ("&REGLAS!B7&",'"&REGLAS!C7&"','"&REGLAS!D7&"','"&REGLAS!G7&"',TO_DATE('"&REGLAS!H7&"','yyyymmdd'),TO_DATE('"&REGLAS!I7&"','yyyymmdd'),'"&REGLAS!J7&"');") -> INSERT INTO INYCEXT.INYC_CONF_INF_REGLAS (COD_INFORME,TABLA,NOMBRE,REGLA,F_INICIO,F_FIN,DESCRIPCION) VALUES (1.1,'INYC_RPI_RESUMEN','SM - Objetivo Trimestral Rappel1 RRTT','SM-O-RPP-Inspector-ObjetivoTrimestral-Rappel1-NumPolizas-001',TO_DATE('20140101','yyyymmdd'),TO_DATE('22000101','yyyymmdd'),''); | B6: =IF(REGLAS!J7="OBSOLETO","","INSERT INTO INYCEXT.INYC_CONF_INF_REGLAS@tc_link (COD_INFORME,TABLA,NOMBRE,REGLA,F_INICIO,F_FIN,DESCRIPCION) VALUES ("&REGLAS!B7&",'"&REGLAS!C7&"','"&REGLAS!D7&"','"&REGLAS!G7&"',TO_DATE('"&REGLAS!H7&"','yyyymmdd'),TO_DATE('"&REGLAS!I7&"','yyyymmdd'),'"&REGLAS!J7&"');") -> INSERT INTO INYCEXT.INYC_CONF_INF_REGLAS@tc_link (COD_INFORME,TABLA,NOMBRE,REGLA,F_INICIO,F_FIN,DESCRIPCION) VALUES (1.1,'INYC_RPI_RESUMEN','SM - Objetivo Trimestral Rappel1 RRTT','SM-O-RPP-Inspector-ObjetivoTrimestral-Rappel1-NumPolizas-001',TO_DATE('20140101','yyyymmdd'),TO_DATE('22000101','yyyymmdd'),'');
A7: =IF(REGLAS!J8="OBSOLETO","","INSERT INTO INYCEXT.INYC_CONF_INF_REGLAS (COD_INFORME,TABLA,NOMBRE,REGLA,F_INICIO,F_FIN,DESCRIPCION) VALUES ("&REGLAS!B8&",'"&REGLAS!C8&"','"&REGLAS!D8&"','"&REGLAS!G8&"',TO_DATE('"&REGLAS!H8&"','yyyymmdd'),TO_DATE('"&REGLAS!I8&"','yyyymmdd'),'"&REGLAS!J8&"');") -> INSERT INTO INYCEXT.INYC_CONF_INF_REGLAS (COD_INFORME,TABLA,NOMBRE,REGLA,F_INICIO,F_FIN,DESCRIPCION) VALUES (1.1,'INYC_RPI_RESUMEN','SM - Objetivo Trimestral Rappel1 Hogar','SM-O-RPP-Inspector-ObjetivoTrimestral-Rappel1-NumPolizas-002',TO_DATE('20140101','yyyymmdd'),TO_DATE('22000101','yyyymmdd'),''); | B7: =IF(REGLAS!J8="OBSOLETO","","INSERT INTO INYCEXT.INYC_CONF_INF_REGLAS@tc_link (COD_INFORME,TABLA,NOMBRE,REGLA,F_INICIO,F_FIN,DESCRIPCION) VALUES ("&REGLAS!B8&",'"&REGLAS!C8&"','"&REGLAS!D8&"','"&REGLAS!G8&"',TO_DATE('"&REGLAS!H8&"','yyyymmdd'),TO_DATE('"&REGLAS!I8&"','yyyymmdd'),'"&REGLAS!J8&"');") -> INSERT INTO INYCEXT.INYC_CONF_INF_REGLAS@tc_link (COD_INFORME,TABLA,NOMBRE,REGLA,F_INICIO,F_FIN,DESCRIPCION) VALUES (1.1,'INYC_RPI_RESUMEN','SM - Objetivo Trimestral Rappel1 Hogar','SM-O-RPP-Inspector-ObjetivoTrimestral-Rappel1-NumPolizas-002',TO_DATE('20140101','yyyymmdd'),TO_DATE('22000101','yyyymmdd'),'');
A8: =IF(REGLAS!J9="OBSOLETO","","INSERT INTO INYCEXT.INYC_CONF_INF_REGLAS (COD_INFORME,TABLA,NOMBRE,REGLA,F_INICIO,F_FIN,DESCRIPCION) VALUES ("&REGLAS!B9&",'"&REGLAS!C9&"','"&REGLAS!D9&"','"&REGLAS!G9&"',TO_DATE('"&REGLAS!H9&"','yyyymmdd'),TO_DATE('"&REGLAS!I9&"','yyyymmdd'),'"&REGLAS!J9&"');") -> INSERT INTO INYCEXT.INYC_CONF_INF_REGLAS (COD_INFORME,TABLA,NOMBRE,REGLA,F_INICIO,F_FIN,DESCRIPCION) VALUES (1.1,'INYC_RPI_RESUMEN','SM - Objetivo Trimestral Rappel1 RRPP','SM-O-RPP-Inspector-ObjetivoTrimestral-Rappel1-NumPolizas-906',TO_DATE('20140101','yyyymmdd'),TO_DATE('22000101','yyyymmdd'),''); | B8: =IF(REGLAS!J9="OBSOLETO","","INSERT INTO INYCEXT.INYC_CONF_INF_REGLAS@tc_link (COD_INFORME,TABLA,NOMBRE,REGLA,F_INICIO,F_FIN,DESCRIPCION) VALUES ("&REGLAS!B9&",'"&REGLAS!C9&"','"&REGLAS!D9&"','"&REGLAS!G9&"',TO_DATE('"&REGLAS!H9&"','yyyymmdd'),TO_DATE('"&REGLAS!I9&"','yyyymmdd'),'"&REGLAS!J9&"');") -> INSERT INTO INYCEXT.INYC_CONF_INF_REGLAS@tc_link (COD_INFORME,TABLA,NOMBRE,REGLA,F_INICIO,F_FIN,DESCRIPCION) VALUES (1.1,'INYC_RPI_RESUMEN','SM - Objetivo Trimestral Rappel1 RRPP','SM-O-RPP-Inspector-ObjetivoTrimestral-Rappel1-NumPolizas-906',TO_DATE('20140101','yyyymmdd'),TO_DATE('22000101','yyyymmdd'),'');
A9: =IF(REGLAS!J10="OBSOLETO","","INSERT INTO INYCEXT.INYC_CONF_INF_REGLAS (COD_INFORME,TABLA,NOMBRE,REGLA,F_INICIO,F_FIN,DESCRIPCION) VALUES ("&REGLAS!B10&",'"&REGLAS!C10&"','"&REGLAS!D10&"','"&REGLAS!G10&"',TO_DATE('"&REGLAS!H10&"','yyyymmdd'),TO_DATE('"&REGLAS!I10&"','yyyymmdd'),'"&REGLAS!J10&"');") -> INSERT INTO INYCEXT.INYC_CONF_INF_REGLAS (COD_INFORME,TABLA,NOMBRE,REGLA,F_INICIO,F_FIN,DESCRIPCION) VALUES (1.1,'INYC_RPI_RESUMEN','SM - Objetivo Trimestral Rappel1 Total Ramos','SM-O-RPP-Inspector-ObjetivoTrimestral-Rappel1-NumPolizas-998',TO_DATE('20140101','yyyymmdd'),TO_DATE('22000101','yyyymmdd'),''); | B9: =IF(REGLAS!J10="OBSOLETO","","INSERT INTO INYCEXT.INYC_CONF_INF_REGLAS@tc_link (COD_INFORME,TABLA,NOMBRE,REGLA,F_INICIO,F_FIN,DESCRIPCION) VALUES ("&REGLAS!B10&",'"&REGLAS!C10&"','"&REGLAS!D10&"','"&REGLAS!G10&"',TO_DATE('"&REGLAS!H10&"','yyyymmdd'),TO_DATE('"&REGLAS!I10&"','yyyymmdd'),'"&REGLAS!J10&"');") -> INSERT INTO INYCEXT.INYC_CONF_INF_REGLAS@tc_link (COD_INFORME,TABLA,NOMBRE,REGLA,F_INICIO,F_FIN,DESCRIPCION) VALUES (1.1,'INYC_RPI_RESUMEN','SM - Objetivo Trimestral Rappel1 Total Ramos','SM-O-RPP-Inspector-ObjetivoTrimestral-Rappel1-NumPolizas-998',TO_DATE('20140101','yyyymmdd'),TO_DATE('22000101','yyyymmdd'),'');
A10: =IF(REGLAS!J11="OBSOLETO","","INSERT INTO INYCEXT.INYC_CONF_INF_REGLAS (COD_INFORME,TABLA,NOMBRE,REGLA,F_INICIO,F_FIN,DESCRIPCION) VALUES ("&REGLAS!B11&",'"&REGLAS!C11&"','"&REGLAS!D11&"','"&REGLAS!G11&"',TO_DATE('"&REGLAS!H11&"','yyyymmdd'),TO_DATE('"&REGLAS!I11&"','yyyymmdd'),'"&REGLAS!J11&"');") -> INSERT INTO INYCEXT.INYC_CONF_INF_REGLAS (COD_INFORME,TABLA,NOMBRE,REGLA,F_INICIO,F_FIN,DESCRIPCION) VALUES (1.1,'INYC_RPI_RESUMEN','SM - Objetivo Trimestral Rappel2 Total Ramos','SM-O-RPP-Inspector-ObjetivoTrimestral-Rappel2-NumPolizas-998',TO_DATE('20140101','yyyymmdd'),TO_DATE('22000101','yyyymmdd'),''); | B10: =IF(REGLAS!J11="OBSOLETO","","INSERT INTO INYCEXT.INYC_CONF_INF_REGLAS@tc_link (COD_INFORME,TABLA,NOMBRE,REGLA,F_INICIO,F_FIN,DESCRIPCION) VALUES ("&REGLAS!B11&",'"&REGLAS!C11&"','"&REGLAS!D11&"','"&REGLAS!G11&"',TO_DATE('"&REGLAS!H11&"','yyyymmdd'),TO_DATE('"&REGLAS!I11&"','yyyymmdd'),'"&REGLAS!J11&"');") -> INSERT INTO INYCEXT.INYC_CONF_INF_REGLAS@tc_link (COD_INFORME,TABLA,NOMBRE,REGLA,F_INICIO,F_FIN,DESCRIPCION) VALUES (1.1,'INYC_RPI_RESUMEN','SM - Objetivo Trimestral Rappel2 Total Ramos','SM-O-RPP-Inspector-ObjetivoTrimestral-Rappel2-NumPolizas-998',TO_DATE('20140101','yyyymmdd'),TO_DATE('22000101','yyyymmdd'),'');
A11: =IF(REGLAS!J12="OBSOLETO","","INSERT INTO INYCEXT.INYC_CONF_INF_REGLAS (COD_INFORME,TABLA,NOMBRE,REGLA,F_INICIO,F_FIN,DESCRIPCION) VALUES ("&REGLAS!B12&",'"&REGLAS!C12&"','"&REGLAS!D12&"','"&REGLAS!G12&"',TO_DATE('"&REGLAS!H12&"','yyyymmdd'),TO_DATE('"&REGLAS!I12&"','yyyymmdd'),'"&REGLAS!J12&"');") -> INSERT INTO INYCEXT.INYC_CONF_INF_REGLAS (COD_INFORME,TABLA,NOMBRE,REGLA,F_INICIO,F_FIN,DESCRIPCION) VALUES (1.1,'INYC_RPI_RESUMEN','SM - Importe Reg. Anual Rappel1 Mes1','SM-RPP-Inspector-ImportesRegularizacionAnual-Rappel1-Mes1',TO_DATE('20140101','yyyymmdd'),TO_DATE('22000101','yyyymmdd'),''); | B11: =IF(REGLAS!J12="OBSOLETO","","INSERT INTO INYCEXT.INYC_CONF_INF_REGLAS@tc_link (COD_INFORME,TABLA,NOMBRE,REGLA,F_INICIO,F_FIN,DESCRIPCION) VALUES ("&REGLAS!B12&",'"&REGLAS!C12&"','"&REGLAS!D12&"','"&REGLAS!G12&"',TO_DATE('"&REGLAS!H12&"','yyyymmdd'),TO_DATE('"&REGLAS!I12&"','yyyymmdd'),'"&REGLAS!J12&"');") -> INSERT INTO INYCEXT.INYC_CONF_INF_REGLAS@tc_link (COD_INFORME,TABLA,NOMBRE,REGLA,F_INICIO,F_FIN,DESCRIPCION) VALUES (1.1,'INYC_RPI_RESUMEN','SM - Importe Reg. Anual Rappel1 Mes1','SM-RPP-Inspector-ImportesRegularizacionAnual-Rappel1-Mes1',TO_DATE('20140101','yyyymmdd'),TO_DATE('22000101','yyyymmdd'),'');
A12: =IF(REGLAS!J13="OBSOLETO","","INSERT INTO INYCEXT.INYC_CONF_INF_REGLAS (COD_INFORME,TABLA,NOMBRE,REGLA,F_INICIO,F_FIN,DESCRIPCION) VALUES ("&REGLAS!B13&",'"&REGLAS!C13&"','"&REGLAS!D13&"','"&REGLAS!G13&"',TO_DATE('"&REGLAS!H13&"','yyyymmdd'),TO_DATE('"&REGLAS!I13&"','yyyymmdd'),'"&REGLAS!J13&"');") -> INSERT INTO INYCEXT.INYC_CONF_INF_REGLAS (COD_INFORME,TABLA,NOMBRE,REGLA,F_INICIO,F_FIN,DESCRIPCION) VALUES (1.1,'INYC_RPI_RESUMEN','SM - Importe Reg. Anual Rappel1 Mes10','SM-RPP-Inspector-ImportesRegularizacionAnual-Rappel1-Mes10',TO_DATE('20140101','yyyymmdd'),TO_DATE('22000101','yyyymmdd'),''); | B12: =IF(REGLAS!J13="OBSOLETO","","INSERT INTO INYCEXT.INYC_CONF_INF_REGLAS@tc_link (COD_INFORME,TABLA,NOMBRE,REGLA,F_INICIO,F_FIN,DESCRIPCION) VALUES ("&REGLAS!B13&",'"&REGLAS!C13&"','"&REGLAS!D13&"','"&REGLAS!G13&"',TO_DATE('"&REGLAS!H13&"','yyyymmdd'),TO_DATE('"&REGLAS!I13&"','yyyymmdd'),'"&REGLAS!J13&"');") -> INSERT INTO INYCEXT.INYC_CONF_INF_REGLAS@tc_link (COD_INFORME,TABLA,NOMBRE,REGLA,F_INICIO,F_FIN,DESCRIPCION) VALUES (1.1,'INYC_RPI_RESUMEN','SM - Importe Reg. Anual Rappel1 Mes10','SM-RPP-Inspector-ImportesRegularizacionAnual-Rappel1-Mes10',TO_DATE('20140101','yyyymmdd'),TO_DATE('22000101','yyyymmdd'),'');
... A1372: =IF(REGLAS!J1373="OBSOLETO","","INSERT INTO INYCEXT.INYC_CONF_INF_REGLAS (COD_INFORME,TABLA,NOMBRE,REGLA,F_INICIO,F_FIN,DESCRIPCION) VALUES ("&REGLAS!B1373&",'"&REGLAS!C1373&"','"&REGLAS!D1373&"','"&REGLAS!G1373&"',TO_DATE('"&REGLAS!H1373&"','yyyymmdd'),TO_DATE('"&REGLAS!I1373&"','yyyymmdd'),'"&REGLAS!J1373&"');") -> INSERT INTO INYCEXT.INYC_CONF_INF_REGLAS (COD_INFORME,TABLA,NOMBRE,REGLA,F_INICIO,F_FIN,DESCRIPCION) VALUES (101.2,'INYC_S5_POLIZAS','Captacion Agentes','IC-O-GEN-Inspector-NumeroPolizas-998-Captacion',TO_DATE('20230101','yyyymmdd'),TO_DATE('22000101','yyyymmdd'),'Version 20230101'); | B1372: =IF(REGLAS!J1373="OBSOLETO","","INSERT INTO INYCEXT.INYC_CONF_INF_REGLAS@tc_link (COD_INFORME,TABLA,NOMBRE,REGLA,F_INICIO,F_FIN,DESCRIPCION) VALUES ("&REGLAS!B1373&",'"&REGLAS!C1373&"','"&REGLAS!D1373&"','"&REGLAS!G1373&"',TO_DATE('"&REGLAS!H1373&"','yyyymmdd'),TO_DATE('"&REGLAS!I1373&"','yyyymmdd'),'"&REGLAS!J1373&"');") -> INSERT INTO INYCEXT.INYC_CONF_INF_REGLAS@tc_link (COD_INFORME,TABLA,NOMBRE,REGLA,F_INICIO,F_FIN,DESCRIPCION) VALUES (101.2,'INYC_S5_POLIZAS','Captacion Agentes','IC-O-GEN-Inspector-NumeroPolizas-998-Captacion',TO_DATE('20230101','yyyymmdd'),TO_DATE('22000101','yyyymmdd'),'Version 20230101');
A1373: =IF(REGLAS!J1374="OBSOLETO","","INSERT INTO INYCEXT.INYC_CONF_INF_REGLAS (COD_INFORME,TABLA,NOMBRE,REGLA,F_INICIO,F_FIN,DESCRIPCION) VALUES ("&REGLAS!B1374&",'"&REGLAS!C1374&"','"&REGLAS!D1374&"','"&REGLAS!G1374&"',TO_DATE('"&REGLAS!H1374&"','yyyymmdd'),TO_DATE('"&REGLAS!I1374&"','yyyymmdd'),'"&REGLAS!J1374&"');") -> INSERT INTO INYCEXT.INYC_CONF_INF_REGLAS (COD_INFORME,TABLA,NOMBRE,REGLA,F_INICIO,F_FIN,DESCRIPCION) VALUES (2.1,'INYC_RAGT_RESUMEN','SM-E-GEN-Inspector-NumPolCorregidas-ProdPrioritarios-TotalSemestre','SM-E-GEN-Inspector-NumPolCorregidas-ProdPrioritarios-TotalSemestre',TO_DATE('20230101','yyyymmdd'),TO_DATE('22000101','yyyymmdd'),'Version 20230101');
A1374: =IF(REGLAS!J1375="OBSOLETO","","INSERT INTO INYCEXT.INYC_CONF_INF_REGLAS (COD_INFORME,TABLA,NOMBRE,REGLA,F_INICIO,F_FIN,DESCRIPCION) VALUES ("&REGLAS!B1375&",'"&REGLAS!C1375&"','"&REGLAS!D1375&"','"&REGLAS!G1375&"',TO_DATE('"&REGLAS!H1375&"','yyyymmdd'),TO_DATE('"&REGLAS!I1375&"','yyyymmdd'),'"&REGLAS!J1375&"');") -> INSERT INTO INYCEXT.INYC_CONF_INF_REGLAS (COD_INFORME,TABLA,NOMBRE,REGLA,F_INICIO,F_FIN,DESCRIPCION) VALUES (2.1,'INYC_RAGT_RESUMEN','SM-E-ImportePago-Semestral','SM-E-RSEM-AG-ImportePago',TO_DATE('20230101','yyyymmdd'),TO_DATE('22000101','yyyymmdd'),'Version 20230101');
A1375: =IF(REGLAS!J1376="OBSOLETO","","INSERT INTO INYCEXT.INYC_CONF_INF_REGLAS (COD_INFORME,TABLA,NOMBRE,REGLA,F_INICIO,F_FIN,DESCRIPCION) VALUES ("&REGLAS!B1376&",'"&REGLAS!C1376&"','"&REGLAS!D1376&"','"&REGLAS!G1376&"',TO_DATE('"&REGLAS!H1376&"','yyyymmdd'),TO_DATE('"&REGLAS!I1376&"','yyyymmdd'),'"&REGLAS!J1376&"');") -> INSERT INTO INYCEXT.INYC_CONF_INF_REGLAS (COD_INFORME,TABLA,NOMBRE,REGLA,F_INICIO,F_FIN,DESCRIPCION) VALUES (6.1,'INYC_RPA_RESUMEN','SM-O-RPP-Agente-Rappel-Pago-MensualXL','SM-O-RPP-Agente-Rappel-Pago-MensualXL',TO_DATE('20230101','yyyymmdd'),TO_DATE('22000101','yyyymmdd'),'Version 20220801');
A1376: =IF(REGLAS!J1377="OBSOLETO","","INSERT INTO INYCEXT.INYC_CONF_INF_REGLAS (COD_INFORME,TABLA,NOMBRE,REGLA,F_INICIO,F_FIN,DESCRIPCION) VALUES ("&REGLAS!B1377&",'"&REGLAS!C1377&"','"&REGLAS!D1377&"','"&REGLAS!G1377&"',TO_DATE('"&REGLAS!H1377&"','yyyymmdd'),TO_DATE('"&REGLAS!I1377&"','yyyymmdd'),'"&REGLAS!J1377&"');") -> INSERT INTO INYCEXT.INYC_CONF_INF_REGLAS (COD_INFORME,TABLA,NOMBRE,REGLA,F_INICIO,F_FIN,DESCRIPCION) VALUES (6.1,'INYC_RPA_RESUMEN','SM - Porcentaje Consecucion','SM-O-COM-GestionExplotacion-PorcentajeConsecucion',TO_DATE('20230101','yyyymmdd'),TO_DATE('22000101','yyyymmdd'),'Versión 20230525');
A1377: =IF(REGLAS!J1378="OBSOLETO","","INSERT INTO INYCEXT.INYC_CONF_INF_REGLAS (COD_INFORME,TABLA,NOMBRE,REGLA,F_INICIO,F_FIN,DESCRIPCION) VALUES ("&REGLAS!B1378&",'"&REGLAS!C1378&"','"&REGLAS!D1378&"','"&REGLAS!G1378&"',TO_DATE('"&REGLAS!H1378&"','yyyymmdd'),TO_DATE('"&REGLAS!I1378&"','yyyymmdd'),'"&REGLAS!J1378&"');") -> INSERT INTO INYCEXT.INYC_CONF_INF_REGLAS (COD_INFORME,TABLA,NOMBRE,REGLA,F_INICIO,F_FIN,DESCRIPCION) VALUES (6.1,'INYC_RPA_RESUMEN','SM - Gestiones','SM-O-COM-GestionExplotacion',TO_DATE('20230101','yyyymmdd'),TO_DATE('22000101','yyyymmdd'),'Versión 20230525');
A1378: =IF(REGLAS!J1379="OBSOLETO","","INSERT INTO INYCEXT.INYC_CONF_INF_REGLAS (COD_INFORME,TABLA,NOMBRE,REGLA,F_INICIO,F_FIN,DESCRIPCION) VALUES ("&REGLAS!B1379&",'"&REGLAS!C1379&"','"&REGLAS!D1379&"','"&REGLAS!G1379&"',TO_DATE('"&REGLAS!H1379&"','yyyymmdd'),TO_DATE('"&REGLAS!I1379&"','yyyymmdd'),'"&REGLAS!J1379&"');") -> INSERT INTO INYCEXT.INYC_CONF_INF_REGLAS (COD_INFORME,TABLA,NOMBRE,REGLA,F_INICIO,F_FIN,DESCRIPCION) VALUES (6.1,'INYC_RPA_RESUMEN','SM - Porcentaje Pago','SM-O-COM-GestionExplotacion-PorcentajePagoFinal',TO_DATE('20230101','yyyymmdd'),TO_DATE('22000101','yyyymmdd'),'Versión 20230525');
A1379: =IF(REGLAS!J1380="OBSOLETO","","INSERT INTO INYCEXT.INYC_CONF_INF_REGLAS (COD_INFORME,TABLA,NOMBRE,REGLA,F_INICIO,F_FIN,DESCRIPCION) VALUES ("&REGLAS!B1380&",'"&REGLAS!C1380&"','"&REGLAS!D1380&"','"&REGLAS!G1380&"',TO_DATE('"&REGLAS!H1380&"','yyyymmdd'),TO_DATE('"&REGLAS!I1380&"','yyyymmdd'),'"&REGLAS!J1380&"');") -> INSERT INTO INYCEXT.INYC_CONF_INF_REGLAS (COD_INFORME,TABLA,NOMBRE,REGLA,F_INICIO,F_FIN,DESCRIPCION) VALUES (6.1,'INYC_RPA_RESUMEN','SM - Importe Pago','SM-O-COM-GestionExplotacion-ImportePago',TO_DATE('20230101','yyyymmdd'),TO_DATE('22000101','yyyymmdd'),'Versión 20230525');
A1380: =IF(REGLAS!J1381="OBSOLETO","","INSERT INTO INYCEXT.INYC_CONF_INF_REGLAS (COD_INFORME,TABLA,NOMBRE,REGLA,F_INICIO,F_FIN,DESCRIPCION) VALUES ("&REGLAS!B1381&",'"&REGLAS!C1381&"','"&REGLAS!D1381&"','"&REGLAS!G1381&"',TO_DATE('"&REGLAS!H1381&"','yyyymmdd'),TO_DATE('"&REGLAS!I1381&"','yyyymmdd'),'"&REGLAS!J1381&"');") -> INSERT INTO INYCEXT.INYC_CONF_INF_REGLAS (COD_INFORME,TABLA,NOMBRE,REGLA,F_INICIO,F_FIN,DESCRIPCION) VALUES (3.1,'INYC_RA_RESUMEN','PrimaCorregida-ProdPrioritarios Trimestre','SM-E-GEN-Agente-PrimaCorregida-ProdPrioritarios-TotalTrimestre',TO_DATE('20240101','yyyymmdd'),TO_DATE('22000101','yyyymmdd'),'Version 20240101');
A1381: =IF(REGLAS!J1382="OBSOLETO","","INSERT INTO INYCEXT.INYC_CONF_INF_REGLAS (COD_INFORME,TABLA,NOMBRE,REGLA,F_INICIO,F_FIN,DESCRIPCION) VALUES ("&REGLAS!B1382&",'"&REGLAS!C1382&"','"&REGLAS!D1382&"','"&REGLAS!G1382&"',TO_DATE('"&REGLAS!H1382&"','yyyymmdd'),TO_DATE('"&REGLAS!I1382&"','yyyymmdd'),'"&REGLAS!J1382&"');") -> INSERT INTO INYCEXT.INYC_CONF_INF_REGLAS (COD_INFORME,TABLA,NOMBRE,REGLA,F_INICIO,F_FIN,DESCRIPCION) VALUES (3.1,'INYC_RA_RESUMEN','Rappel Trimestral por Primas Corregidas de nueva producción.','SM-E-R-Agente-Pago-Primas-Trimestre',TO_DATE('20240101','yyyymmdd'),TO_DATE('22000101','yyyymmdd'),'Version 20240101');
A1382: =IF(REGLAS!J1383="OBSOLETO","","INSERT INTO INYCEXT.INYC_CONF_INF_REGLAS (COD_INFORME,TABLA,NOMBRE,REGLA,F_INICIO,F_FIN,DESCRIPCION) VALUES ("&REGLAS!B1383&",'"&REGLAS!C1383&"','"&REGLAS!D1383&"','"&REGLAS!G1383&"',TO_DATE('"&REGLAS!H1383&"','yyyymmdd'),TO_DATE('"&REGLAS!I1383&"','yyyymmdd'),'"&REGLAS!J1383&"');") -> INSERT INTO INYCEXT.INYC_CONF_INF_REGLAS (COD_INFORME,TABLA,NOMBRE,REGLA,F_INICIO,F_FIN,DESCRIPCION) VALUES (17.1,'INYC_RE_RESUMEN','SM-Polizas fisicas Vida/Accidente','SM-O-REP-Inspector-NumeroPolizas-VidaAccidentes-TotalMes',TO_DATE('20240301','yyyymmdd'),TO_DATE('22000101','yyyymmdd'),'Version 20240101');
A1383: =IF(REGLAS!J1384="OBSOLETO","","INSERT INTO INYCEXT.INYC_CONF_INF_REGLAS (COD_INFORME,TABLA,NOMBRE,REGLA,F_INICIO,F_FIN,DESCRIPCION) VALUES ("&REGLAS!B1384&",'"&REGLAS!C1384&"','"&REGLAS!D1384&"','"&REGLAS!G1384&"',TO_DATE('"&REGLAS!H1384&"','yyyymmdd'),TO_DATE('"&REGLAS!I1384&"','yyyymmdd'),'"&REGLAS!J1384&"');") -> INSERT INTO INYCEXT.INYC_CONF_INF_REGLAS (COD_INFORME,TABLA,NOMBRE,REGLA,F_INICIO,F_FIN,DESCRIPCION) VALUES (17.1,'INYC_RE_RESUMEN','SM-Polizas Corregidas Vida/Accidente','SM-O-REP-Inspector-NumeroPolizasCorregidas-VidaAccidentes-TotalMes',TO_DATE('20240301','yyyymmdd'),TO_DATE('22000101','yyyymmdd'),'Version 20240101');
A1384: =IF(REGLAS!J1385="OBSOLETO","","INSERT INTO INYCEXT.INYC_CONF_INF_REGLAS (COD_INFORME,TABLA,NOMBRE,REGLA,F_INICIO,F_FIN,DESCRIPCION) VALUES ("&REGLAS!B1385&",'"&REGLAS!C1385&"','"&REGLAS!D1385&"','"&REGLAS!G1385&"',TO_DATE('"&REGLAS!H1385&"','yyyymmdd'),TO_DATE('"&REGLAS!I1385&"','yyyymmdd'),'"&REGLAS!J1385&"');") -> INSERT INTO INYCEXT.INYC_CONF_INF_REGLAS (COD_INFORME,TABLA,NOMBRE,REGLA,F_INICIO,F_FIN,DESCRIPCION) VALUES (17.1,'INYC_RE_RESUMEN','PM- PolizasCorregidas Vida/Accidente Propia','PM-O-REP-Inspector-NumeroPolizasCorregidas-VidaAccidentes',TO_DATE('20240301','yyyymmdd'),TO_DATE('22000101','yyyymmdd'),'Version 20240101');
... A1408: =IF(REGLAS!J1409="OBSOLETO","","INSERT INTO INYCEXT.INYC_CONF_INF_REGLAS (COD_INFORME,TABLA,NOMBRE,REGLA,F_INICIO,F_FIN,DESCRIPCION) VALUES ("&REGLAS!B1409&",'"&REGLAS!C1409&"','"&REGLAS!D1409&"','"&REGLAS!G1409&"',TO_DATE('"&REGLAS!H1409&"','yyyymmdd'),TO_DATE('"&REGLAS!I1409&"','yyyymmdd'),'"&REGLAS!J1409&"');") -> INSERT INTO INYCEXT.INYC_CONF_INF_REGLAS (COD_INFORME,TABLA,NOMBRE,REGLA,F_INICIO,F_FIN,DESCRIPCION) VALUES (100.2,'INYC_S4_POLIZAS','Comision Nueva Produccion','DC-O-COM-NuevaProduccion-PorcentajeFijo-N',TO_DATE('20140101','yyyymmdd'),TO_DATE('22000101','yyyymmdd'),'Version 20250101');

Sheet AGENTES
A1: SPRINT | B1: COD_INFORME | C1: BO_GROUP | D1: COMPANIA | E1: ID_TIPO_AGENTE | F1: TABLA | G1: F_INICIO | H1: F_FIN | I1: DESCRIPCION
A2: 1 | B2: 1 | C2: INYC Compensation Reports User Group - RPI | D2: 01 | E2: 52 | F2: INYC_RPI_RESUMEN,INYC_RPI_DETALLE | G2: 20140101 | H2: 22000101
A3: 1 | B3: 1 | C3: INYC Compensation Reports User Group - RPI | D3: 01 | E3: 54 | F3: INYC_RPI_RESUMEN,INYC_RPI_DETALLE | G3: 20140101 | H3: 22000101
A4: 1 | B4: 1 | C4: INYC Compensation Reports User Group - RPI | D4: 01 | E4: 56 | F4: INYC_RPI_RESUMEN,INYC_RPI_DETALLE | G4: 20140101 | H4: 22000101
A5: 1 | B5: 1 | C5: INYC Compensation Reports User Group - RPI | D5: 01 | E5: 57 | F5: INYC_RPI_RESUMEN,INYC_RPI_DETALLE | G5: 20140101 | H5: 22000101
A6: 1 | B6: 1 | C6: INYC Compensation Reports User Group - RPI | D6: 01 | E6: 58 | F6: INYC_RPI_RESUMEN,INYC_RPI_DETALLE | G6: 20140101 | H6: 22000101
A7: 1 | B7: 1 | C7: INYC Compensation Reports User Group - RPI | D7: 01 | E7: 59 | F7: INYC_RPI_RESUMEN,INYC_RPI_DETALLE | G7: 20140101 | H7: 22000101
A8: 1 | B8: 1 | C8: INYC Compensation Reports User Group - RPI | D8: 01 | E8: 60 | F8: INYC_RPI_RESUMEN,INYC_RPI_DETALLE | G8: 20200101 | H8: 22000101 | I8: Version 20200526
A9: 1 | B9: 1 | C9: INYC Compensation Reports User Group - RPI | D9: 01 | E9: 61 | F9: INYC_RPI_RESUMEN,INYC_RPI_DETALLE | G9: 20140101 | H9: 22000101
A10: 1 | B10: 1 | C10: INYC Compensation Reports User Group - RPI | D10: 01 | E10: 62 | F10: INYC_RPI_RESUMEN,INYC_RPI_DETALLE | G10: 20140101 | H10: 22000101
A11: 1 | B11: 1 | C11: INYC Compensation Reports User Group - RPI | D11: 01 | E11: 65 | F11: INYC_RPI_RESUMEN,INYC_RPI_DETALLE | G11: 20140101 | H11: 22000101
A12: 2 | B12: 2 | C12: INYC Compensation Reports User Group - RAG | D12: 03 | E12: 350 | F12: INYC_RAG_RESUMEN,INYC_RAG_DETALLE | G12: 20140101 | H12: 22000101
A13: 2 | B13: 2 | C13: INYC Compensation Reports User Group - RAG | D13: 03 | E13: 351 | F13: INYC_RAG_RESUMEN,INYC_RAG_DETALLE | G13: 20140101 | H13: 22000101
A14: 2 | B14: 2 | C14: INYC Compensation Reports User Group - RAG | D14: 03 | E14: 352 | F14: INYC_RAG_RESUMEN,INYC_RAG_DETALLE | G14: 20140101 | H14: 22000101
A15: 2 | B15: 3 | C15: INYC Compensation Reports User Group - RA | D15: 03 | E15: 301 | F15: INYC_RA_RESUMEN,INYC_RA_DETALLE | G15: 20140101 | H15: 20170101 | I15: Version 20170602
A16: 2 | B16: 3 | C16: INYC Compensation Reports User Group - RA | D16: 03 | E16: 302 | F16: INYC_RA_RESUMEN,INYC_RA_DETALLE | G16: 20140101 | H16: 20170101 | I16: Version 20170602
A17: 2 | B17: 3 | C17: INYC Compensation Reports User Group - RA | D17: 03 | E17: 303 | F17: INYC_RA_RESUMEN,INYC_RA_DETALLE | G17: 20140101 | H17: 20170101 | I17: Version 20170602
A18: 2 | B18: 3 | C18: INYC Compensation Reports User Group - RA | D18: 03 | E18: 316 | F18: INYC_RA_RESUMEN,INYC_RA_DETALLE | G18: 20170101 | H18: 22000101 | I18: Version 20170602
A19: 2 | B19: 3 | C19: INYC Compensation Reports User Group - RA | D19: 03 | E19: 317 | F19: INYC_RA_RESUMEN,INYC_RA_DETALLE | G19: 20200101 | H19: 22000101 | I19: Version 20200214
A20: 2 | B20: 3 | C20: INYC Compensation Reports User Group - RA | D20: 03 | E20: 331 | F20: INYC_RA_RESUMEN,INYC_RA_DETALLE | G20: 20140101 | H20: 20170101 | I20: Version 20170602
A21: 2 | B21: 3 | C21: INYC Compensation Reports User Group - RA | D21: 03 | E21: 334 | F21: INYC_RA_RESUMEN,INYC_RA_DETALLE | G21: 20140101 | H21: 20170101 | I21: Version 20170602
A22: 2 | B22: 3 | C22: INYC Compensation Reports User Group - RA | D22: 03 | E22: 332 | F22: INYC_RA_RESUMEN,INYC_RA_DETALLE | G22: 20190101 | H22: 22000101 | I22: Version 20190116
A23: 2 | B23: 3 | C23: INYC Compensation Reports User Group - RA | D23: 03 | E23: 333 | F23: INYC_RA_RESUMEN,INYC_RA_DETALLE | G23: 20190101 | H23: 22000101 | I23: Version 20190116
A24: 2 | B24: 3 | C24: INYC Compensation Reports User Group - RA | D24: 03 | E24: 338 | F24: INYC_RA_RESUMEN,INYC_RA_DETALLE | G24: 20140101 | H24: 22000101
A25: 2 | B25: 3 | C25: INYC Compensation Reports User Group - RA | D25: 03 | E25: 340 | F25: INYC_RA_RESUMEN,INYC_RA_DETALLE | G25: 20140101 | H25: 22000101
A26: 2 | B26: 3 | C26: INYC Compensation Reports User Group - RA | D26: 03 | E26: 341 | F26: INYC_RA_RESUMEN,INYC_RA_DETALLE | G26: 20200101 | H26: 22000101 | I26: Version 20200506
A27: 2 | B27: 4 | C27: INYC Compensation Reports User Group - Concurso | D27: 03 | E27: 13 | F27: INYC_CONCURSO | G27: 20140101 | H27: 22000101
A28: 2 | B28: 4 | C28: INYC Compensation Reports User Group - Concurso | D28: 03 | E28: 14 | F28: INYC_CONCURSO | G28: 20140101 | H28: 22000101
A29: 2 | B29: 4 | C29: INYC Compensation Reports User Group - Concurso | D29: 03 | E29: 301 | F29: INYC_CONCURSO | G29: 20140101 | H29: 22000101
A30: 2 | B30: 4 | C30: INYC Compensation Reports User Group - Concurso | D30: 03 | E30: 303 | F30: INYC_CONCURSO | G30: 20140101 | H30: 22000101
A31: 2 | B31: 4 | C31: INYC Compensation Reports User Group - Concurso | D31: 03 | E31: 331 | F31: INYC_CONCURSO | G31: 20140101 | H31: 22000101
A32: 2 | B32: 4 | C32: INYC Compensation Reports User Group - Concurso | D32: 03 | E32: 334 | F32: INYC_CONCURSO | G32: 20140101 | H32: 22000101
A33: 2 | B33: 4 | C33: INYC Compensation Reports User Group - Concurso | D33: 03 | E33: 338 | F33: INYC_CONCURSO | G33: 20140101 | H33: 22000101
A34: 2 | B34: 4 | C34: INYC Compensation Reports User Group - Concurso | D34: 03 | E34: 340 | F34: INYC_CONCURSO | G34: 20140101 | H34: 22000101
A35: 2 | B35: 4 | C35: INYC Compensation Reports User Group - Concurso | D35: 03 | E35: 341 | F35: INYC_CONCURSO | G35: 20200101 | H35: 22000101 | I35: Version 20200506
A36: 2 | B36: 4 | C36: INYC Compensation Reports User Group - Concurso | D36: 03 | E36: 350 | F36: INYC_CONCURSO | G36: 20170101 | H36: 22000101 | I36: Version 20171106
A37: 2 | B37: 4 | C37: INYC Compensation Reports User Group - Concurso | D37: 03 | E37: 351 | F37: INYC_CONCURSO | G37: 20170101 | H37: 22000101 | I37: Version 20171106
A38: 2 | B38: 4 | C38: INYC Compensation Reports User Group - Concurso | D38: 03 | E38: 352 | F38: INYC_CONCURSO | G38: 20170101 | H38: 22000101 | I38: Version 20171106
A39: 2 | B39: 5 | C39: INYC Compensation Reports User Group - Incentivo | D39: 03 | E39: 350 | F39: INYC_INCENTIVO | G39: 20140101 | H39: 22000101
A40: 2 | B40: 5 | C40: INYC Compensation Reports User Group - Incentivo | D40: 03 | E40: 351 | F40: INYC_INCENTIVO | G40: 20140101 | H40: 22000101
A41: 2 | B41: 5 | C41: INYC Compensation Reports User Group - Incentivo | D41: 03 | E41: 352 | F41: INYC_INCENTIVO | G41: 20140101 | H41: 22000101
A42: 2 | B42: 6 | C42: INYC Compensation Reports User Group - RPA | D42: 01 | E42: 11 | F42: INYC_RPA_RESUMEN,INYC_RPA_DETALLE | G42: 20140101 | H42: 22000101
A43: 2 | B43: 6 | C43: INYC Compensation Reports User Group - RPA | D43: 01 | E43: 13 | F43: INYC_RPA_RESUMEN,INYC_RPA_DETALLE | G43: 20140101 | H43: 22000101
A44: 2 | B44: 6 | C44: INYC Compensation Reports User Group - RPA | D44: 01 | E44: 16 | F44: INYC_RPA_RESUMEN,INYC_RPA_DETALLE | G44: 20140101 | H44: 22000101
A45: 2 | B45: 6 | C45: INYC Compensation Reports User Group - RPA | D45: 01 | E45: 19 | F45: INYC_RPA_RESUMEN,INYC_RPA_DETALLE | G45: 20170801 | H45: 22000101 | I45: Version 20170810
A46: 2 | B46: 6 | C46: INYC Compensation Reports User Group - RPA | D46: 01 | E46: 20 | F46: INYC_RPA_RESUMEN,INYC_RPA_DETALLE | G46: 20140101 | H46: 22000101
A47: 2 | B47: 6 | C47: INYC Compensation Reports User Group - RPA | D47: 01 | E47: 22 | F47: INYC_RPA_RESUMEN,INYC_RPA_DETALLE | G47: 20140101 | H47: 22000101
A48: 2 | B48: 6 | C48: INYC Compensation Reports User Group - RPA | D48: 01 | E48: 23 | F48: INYC_RPA_RESUMEN,INYC_RPA_DETALLE | G48: 20140101 | H48: 22000101
A49: 2 | B49: 6 | C49: INYC Compensation Reports User Group - RPA | D49: 01 | E49: 27 | F49: INYC_RPA_RESUMEN,INYC_RPA_DETALLE | G49: 20140101 | H49: 22000101
A50: 2 | B50: 6 | C50: INYC Compensation Reports User Group - RPA | D50: 01 | E50: 29 | F50: INYC_RPA_RESUMEN,INYC_RPA_DETALLE | G50: 20140101 | H50: 22000101
A51: 2 | B51: 6 | C51: INYC Compensation Reports User Group - RPA | D51: 01 | E51: 30 | F51: INYC_RPA_RESUMEN,INYC_RPA_DETALLE | G51: 20140101 | H51: 22000101
A52: 2 | B52: 6 | C52: INYC Compensation Reports User Group - RPA | D52: 01 | E52: 32 | F52: INYC_RPA_RESUMEN,INYC_RPA_DETALLE | G52: 20140101 | H52: 22000101 | I52: Version 20180926
A53: 2 | B53: 6 | C53: INYC Compensation Reports User Group - RPA | D53: 01 | E53: 33 | F53: INYC_RPA_RESUMEN,INYC_RPA_DETALLE | G53: 20140101 | H53: 22000101
A54: 2 | B54: 6 | C54: INYC Compensation Reports User Group - RPA | D54: 01 | E54: 34 | F54: INYC_RPA_RESUMEN,INYC_RPA_DETALLE | G54: 20140101 | H54: 22000101
A55: 2 | B55: 6 | C55: INYC Compensation Reports User Group - RPA | D55: 01 | E55: 36 | F55: INYC_RPA_RESUMEN,INYC_RPA_DETALLE | G55: 20140101 | H55: 22000101
A56: 2 | B56: 6 | C56: INYC Compensation Reports User Group - RPA | D56: 01 | E56: 38 | F56: INYC_RPA_RESUMEN,INYC_RPA_DETALLE | G56: 20140101 | H56: 22000101
A57: 2 | B57: 6 | C57: INYC Compensation Reports User Group - RPA | D57: 01 | E57: 39 | F57: INYC_RPA_RESUMEN,INYC_RPA_DETALLE | G57: 20140101 | H57: 22000101
A58: 2 | B58: 6 | C58: INYC Compensation Reports User Group - RPA | D58: 01 | E58: 40 | F58: INYC_RPA_RESUMEN,INYC_RPA_DETALLE | G58: 20140101 | H58: 22000101
A59: 2 | B59: 6 | C59: INYC Compensation Reports User Group - RPA | D59: 01 | E59: 41 | F59: INYC_RPA_RESUMEN,INYC_RPA_DETALLE | G59: 20140101 | H59: 22000101
A60: 2 | B60: 6 | C60: INYC Compensation Reports User Group - RPA | D60: 01 | E60: 42 | F60: INYC_RPA_RESUMEN,INYC_RPA_DETALLE | G60: 20140101 | H60: 22000101
A61: 2 | B61: 6 | C61: INYC Compensation Reports User Group - RPA | D61: 01 | E61: 44 | F61: INYC_RPA_RESUMEN,INYC_RPA_DETALLE | G61: 20140101 | H61: 22000101
A62: 2 | B62: 6 | C62: INYC Compensation Reports User Group - RPA | D62: 01 | E62: 45 | F62: INYC_RPA_RESUMEN,INYC_RPA_DETALLE | G62: 20140101 | H62: 22000101
A63: 2 | B63: 6 | C63: INYC Compensation Reports User Group - RPA | D63: 01 | E63: 46 | F63: INYC_RPA_RESUMEN,INYC_RPA_DETALLE | G63: 20140101 | H63: 22000101
A64: 2 | B64: 6 | C64: INYC Compensation Reports User Group - RPA | D64: 01 | E64: 47 | F64: INYC_RPA_RESUMEN,INYC_RPA_DETALLE | G64: 20140101 | H64: 22000101
... A72: 3 | B72: 7 | C72: INYC Compensation Reports User Group - DIF | D72: 01 | E72: 59 | F72: INYC_DIF_RESUMEN,INYC_DIF_DETALLE | G72: 20140101 | H72: 22000101
A73: 3 | B73: 7 | C73: INYC Compensation Reports User Group - DIF | D73: 01 | E73: 60 | F73: INYC_DIF_RESUMEN,INYC_DIF_DETALLE | G73: 20200101 | H73: 22000101 | I73: Version 20200526
A74: 3 | B74: 7 | C74: INYC Compensation Reports User Group - DIF | D74: 01 | E74: 61 | F74: INYC_DIF_RESUMEN,INYC_DIF_DETALLE | G74: 20140101 | H74: 22000101
A75: 3 | B75: 7 | C75: INYC Compensation Reports User Group - DIF | D75: 01 | E75: 62 | F75: INYC_DIF_RESUMEN,INYC_DIF_DETALLE | G75: 20140101 | H75: 22000101
A76: 3 | B76: 7 | C76: INYC Compensation Reports User Group - DIF | D76: 01 | E76: 65 | F76: INYC_DIF_RESUMEN,INYC_DIF_DETALLE | G76: 20140101 | H76: 22000101
A77: 3 | B77: 7 | C77: INYC Compensation Reports User Group - DIF | D77: 01 | E77: 70 | F77: INYC_DIF_RESUMEN,INYC_DIF_DETALLE | G77: 20140101 | H77: 22000101
A78: 3 | B78: 7 | C78: INYC Compensation Reports User Group - DIF | D78: 01 | E78: 71 | F78: INYC_DIF_RESUMEN,INYC_DIF_DETALLE | G78: 20140101 | H78: 22000101
A79: 3 | B79: 7 | C79: INYC Compensation Reports User Group - DIF | D79: 01 | E79: 72 | F79: INYC_DIF_RESUMEN,INYC_DIF_DETALLE | G79: 20140101 | H79: 22000101
A80: 3 | B80: 7 | C80: INYC Compensation Reports User Group - DIF | D80: 01 | E80: 74 | F80: INYC_DIF_RESUMEN,INYC_DIF_DETALLE | G80: 20140101 | H80: 22000101
A81: 3 | B81: 7 | C81: INYC Compensation Reports User Group - DIF | D81: 01 | E81: 82 | F81: INYC_DIF_RESUMEN,INYC_DIF_DETALLE | G81: 20140101 | H81: 22000101
A82: 3 | B82: 8 | C82: INYC Compensation Reports User Group - COLC | D82: 01 | E82: 70 | F82: INYC_COLC_RESUMEN | G82: 20140101 | H82: 22000101
A83: 3 | B83: 8 | C83: INYC Compensation Reports User Group - COLC | D83: 01 | E83: 71 | F83: INYC_COLC_RESUMEN | G83: 20140101 | H83: 22000101
A84: 3 | B84: 8 | C84: INYC Compensation Reports User Group - COLC | D84: 01 | E84: 72 | F84: INYC_COLC_RESUMEN | G84: 20140101 | H84: 22000101
A85: 3 | B85: 8 | C85: INYC Compensation Reports User Group - COLC | D85: 01 | E85: 74 | F85: INYC_COLC_RESUMEN | G85: 20140101 | H85: 22000101
A86: 3 | B86: 9 | C86: INYC Compensation Reports CT User Group | D86: 01 | E86: 70 | F86: INYC_CT_RESUMEN,INYC_CT_DETALLE | G86: 20140101 | H86: 20151001 | I86: OBSOLETO
A87: 3 | B87: 9 | C87: INYC Compensation Reports CT User Group | D87: 01 | E87: 71 | F87: INYC_CT_RESUMEN,INYC_CT_DETALLE | G87: 20140101 | H87: 20151001 | I87: OBSOLETO
A88: 3 | B88: 9 | C88: INYC Compensation Reports CT User Group | D88: 01 | E88: 72 | F88: INYC_CT_RESUMEN,INYC_CT_DETALLE | G88: 20140101 | H88: 20151001 | I88: OBSOLETO
A89: 3 | B89: 9 | C89: INYC Compensation Reports CT User Group | D89: 01 | E89: 74 | F89: INYC_CT_RESUMEN,INYC_CT_DETALLE | G89: 20140101 | H89: 20151001 | I89: OBSOLETO
A90: 3 | B90: 9 | C90: INYC Compensation Reports CT User Group | D90: 01 | E90: 82 | F90: INYC_CT_RESUMEN,INYC_CT_DETALLE | G90: 20140101 | H90: 20151001 | I90: OBSOLETO
A91: 3 | B91: 10 | C91: INYC Compensation Reports User Group - RDC | D91: 01 | E91: 20 | F91: INYC_RDC_RESUMEN,INYC_RDC_DETALLE | G91: 20140101 | H91: 22000101
A92: 3 | B92: 10 | C92: INYC Compensation Reports User Group - RDC | D92: 01 | E92: 39 | F92: INYC_RDC_RESUMEN,INYC_RDC_DETALLE | G92: 20170101 | H92: 22000101 | I92: Version 20170118
A93: 3 | B93: 11 | C93: INYC Compensation Reports User Group - IPP | D93: 01 | E93: 11 | F93: INYC_IPP_RESUMEN | G93: 20140101 | H93: 20170101 | I93: OBSOLETO
A94: 3 | B94: 11 | C94: INYC Compensation Reports User Group - IPP | D94: 01 | E94: 16 | F94: INYC_IPP_RESUMEN | G94: 20140101 | H94: 20170101 | I94: OBSOLETO
A95: 3 | B95: 11 | C95: INYC Compensation Reports User Group - IPP | D95: 01 | E95: 20 | F95: INYC_IPP_RESUMEN | G95: 20140101 | H95: 20170101 | I95: OBSOLETO
A96: 3 | B96: 11 | C96: INYC Compensation Reports User Group - IPP | D96: 01 | E96: 22 | F96: INYC_IPP_RESUMEN | G96: 20140101 | H96: 20170101 | I96: OBSOLETO
A97: 3 | B97: 11 | C97: INYC Compensation Reports User Group - IPP | D97: 01 | E97: 23 | F97: INYC_IPP_RESUMEN | G97: 20140101 | H97: 20170101 | I97: OBSOLETO
A98: 3 | B98: 11 | C98: INYC Compensation Reports User Group - IPP | D98: 01 | E98: 27 | F98: INYC_IPP_RESUMEN | G98: 20140101 | H98: 20170101 | I98: OBSOLETO
A99: 3 | B99: 11 | C99: INYC Compensation Reports User Group - IPP | D99: 01 | E99: 29 | F99: INYC_IPP_RESUMEN | G99: 20140101 | H99: 20170101 | I99: OBSOLETO
A100: 3 | B100: 11 | C100: INYC Compensation Reports User Group - IPP | D100: 01 | E100: 30 | F100: INYC_IPP_RESUMEN | G100: 20140101 | H100: 20170101 | I100: OBSOLETO
A101: 3 | B101: 11 | C101: INYC Compensation Reports User Group - IPP | D101: 01 | E101: 33 | F101: INYC_IPP_RESUMEN | G101: 20140101 | H101: 20170101 | I101: OBSOLETO
A102: 3 | B102: 11 | C102: INYC Compensation Reports User Group - IPP | D102: 01 | E102: 34 | F102: INYC_IPP_RESUMEN | G102: 20140101 | H102: 20170101 | I102: OBSOLETO
A103: 3 | B103: 11 | C103: INYC Compensation Reports User Group - IPP | D103: 01 | E103: 36 | F103: INYC_IPP_RESUMEN | G103: 20140101 | H103: 20170101 | I103: OBSOLETO
... A108: 3 | B108: 11 | C108: INYC Compensation Reports User Group - IPP | D108: 01 | E108: 47 | F108: INYC_IPP_RESUMEN | G108: 20140101 | H108: 20170101 | I108: OBSOLETO
A109: 3 | B109: 12 | C109: INYC Compensation Reports User Group - AN | D109: 01 | E109: 52 | F109: INYC_AN_RESUMEN,INYC_AN_DETALLE | G109: 20140101 | H109: 22000101
A110: 3 | B110: 12 | C110: INYC Compensation Reports User Group - AN | D110: 01 | E110: 54 | F110: INYC_AN_RESUMEN,INYC_AN_DETALLE | G110: 20140101 | H110: 22000101
A111: 3 | B111: 12 | C111: INYC Compensation Reports User Group - AN | D111: 01 | E111: 56 | F111: INYC_AN_RESUMEN,INYC_AN_DETALLE | G111: 20140101 | H111: 22000101
...

Sheet INSERT AGENTES
A1: =IF(AGENTES!I2="OBSOLETO","","INSERT INTO INYCEXT.INYC_CONF_INF_AGENTES (COD_INFORME,BO_GROUP,COMPANIA,ID_TIPO_AGENTE,TABLA,F_INICIO,F_FIN,DESCRIPCION) VALUES ("&AGENTES!B2&",'"&AGENTES!C2&"','"&AGENTES!D2&"','"&AGENTES!E2&"','"&AGENTES!F2&"',TO_DATE('"&AGENTES!G2&"','yyyymmdd'),TO_DATE('"&AGENTES!H2&"','yyyymmdd'),'"&AGENTES!I2&"');") -> INSERT INTO INYCEXT.INYC_CONF_INF_AGENTES (COD_INFORME,BO_GROUP,COMPANIA,ID_TIPO_AGENTE,TABLA,F_INICIO,F_FIN,DESCRIPCION) VALUES (1,'INYC Compensation Reports User Group - RPI','01','52','INYC_RPI_RESUMEN,INYC_RPI_DETALLE',TO_DATE('20140101','yyyymmdd'),TO_DATE('22000101','yyyymmdd'),'');
A2: =IF(AGENTES!I3="OBSOLETO","","INSERT INTO INYCEXT.INYC_CONF_INF_AGENTES (COD_INFORME,BO_GROUP,COMPANIA,ID_TIPO_AGENTE,TABLA,F_INICIO,F_FIN,DESCRIPCION) VALUES ("&AGENTES!B3&",'"&AGENTES!C3&"','"&AGENTES!D3&"','"&AGENTES!E3&"','"&AGENTES!F3&"',TO_DATE('"&AGENTES!G3&"','yyyymmdd'),TO_DATE('"&AGENTES!H3&"','yyyymmdd'),'"&AGENTES!I3&"');") -> INSERT INTO INYCEXT.INYC_CONF_INF_AGENTES (COD_INFORME,BO_GROUP,COMPANIA,ID_TIPO_AGENTE,TABLA,F_INICIO,F_FIN,DESCRIPCION) VALUES (1,'INYC Compensation Reports User Group - RPI','01','54','INYC_RPI_RESUMEN,INYC_RPI_DETALLE',TO_DATE('20140101','yyyymmdd'),TO_DATE('22000101','yyyymmdd'),'');
A3: =IF(AGENTES!I4="OBSOLETO","","INSERT INTO INYCEXT.INYC_CONF_INF_AGENTES (COD_INFORME,BO_GROUP,COMPANIA,ID_TIPO_AGENTE,TABLA,F_INICIO,F_FIN,DESCRIPCION) VALUES ("&AGENTES!B4&",'"&AGENTES!C4&"','"&AGENTES!D4&"','"&AGENTES!E4&"','"&AGENTES!F4&"',TO_DATE('"&AGENTES!G4&"','yyyymmdd'),TO_DATE('"&AGENTES!H4&"','yyyymmdd'),'"&AGENTES!I4&"');") -> INSERT INTO INYCEXT.INYC_CONF_INF_AGENTES (COD_INFORME,BO_GROUP,COMPANIA,ID_TIPO_AGENTE,TABLA,F_INICIO,F_FIN,DESCRIPCION) VALUES (1,'INYC Compensation Reports User Group - RPI','01','56','INYC_RPI_RESUMEN,INYC_RPI_DETALLE',TO_DATE('20140101','yyyymmdd'),TO_DATE('22000101','yyyymmdd'),'');
A4: =IF(AGENTES!I5="OBSOLETO","","INSERT INTO INYCEXT.INYC_CONF_INF_AGENTES (COD_INFORME,BO_GROUP,COMPANIA,ID_TIPO_AGENTE,TABLA,F_INICIO,F_FIN,DESCRIPCION) VALUES ("&AGENTES!B5&",'"&AGENTES!C5&"','"&AGENTES!D5&"','"&AGENTES!E5&"','"&AGENTES!F5&"',TO_DATE('"&AGENTES!G5&"','yyyymmdd'),TO_DATE('"&AGENTES!H5&"','yyyymmdd'),'"&AGENTES!I5&"');") -> INSERT INTO INYCEXT.INYC_CONF_INF_AGENTES (COD_INFORME,BO_GROUP,COMPANIA,ID_TIPO_AGENTE,TABLA,F_INICIO,F_FIN,DESCRIPCION) VALUES (1,'INYC Compensation Reports User Group - RPI','01','57','INYC_RPI_RESUMEN,INYC_RPI_DETALLE',TO_DATE('20140101','yyyymmdd'),TO_DATE('22000101','yyyymmdd'),'');
A5: =IF(AGENTES!I6="OBSOLETO","","INSERT INTO INYCEXT.INYC_CONF_INF_AGENTES (COD_INFORME,BO_GROUP,COMPANIA,ID_TIPO_AGENTE,TABLA,F_INICIO,F_FIN,DESCRIPCION) VALUES ("&AGENTES!B6&",'"&AGENTES!C6&"','"&AGENTES!D6&"','"&AGENTES!E6&"','"&AGENTES!F6&"',TO_DATE('"&AGENTES!G6&"','yyyymmdd'),TO_DATE('"&AGENTES!H6&"','yyyymmdd'),'"&AGENTES!I6&"');") -> INSERT INTO INYCEXT.INYC_CONF_INF_AGENTES (COD_INFORME,BO_GROUP,COMPANIA,ID_TIPO_AGENTE,TABLA,F_INICIO,F_FIN,DESCRIPCION) VALUES (1,'INYC Compensation Reports User Group - RPI','01','58','INYC_RPI_RESUMEN,INYC_RPI_DETALLE',TO_DATE('20140101','yyyymmdd'),TO_DATE('22000101','yyyymmdd'),'');
A6: =IF(AGENTES!I7="OBSOLETO","","INSERT INTO INYCEXT.INYC_CONF_INF_AGENTES (COD_INFORME,BO_GROUP,COMPANIA,ID_TIPO_AGENTE,TABLA,F_INICIO,F_FIN,DESCRIPCION) VALUES ("&AGENTES!B7&",'"&AGENTES!C7&"','"&AGENTES!D7&"','"&AGENTES!E7&"','"&AGENTES!F7&"',TO_DATE('"&AGENTES!G7&"','yyyymmdd'),TO_DATE('"&AGENTES!H7&"','yyyymmdd'),'"&AGENTES!I7&"');") -> INSERT INTO INYCEXT.INYC_CONF_INF_AGENTES (COD_INFORME,BO_GROUP,COMPANIA,ID_TIPO_AGENTE,TABLA,F_INICIO,F_FIN,DESCRIPCION) VALUES (1,'INYC Compensation Reports User Group - RPI','01','59','INYC_RPI_RESUMEN,INYC_RPI_DETALLE',TO_DATE('20140101','yyyymmdd'),TO_DATE('22000101','yyyymmdd'),'');
A7: =IF(AGENTES!I8="OBSOLETO","","INSERT INTO INYCEXT.INYC_CONF_INF_AGENTES (COD_INFORME,BO_GROUP,COMPANIA,ID_TIPO_AGENTE,TABLA,F_INICIO,F_FIN,DESCRIPCION) VALUES ("&AGENTES!B8&",'"&AGENTES!C8&"','"&AGENTES!D8&"','"&AGENTES!E8&"','"&AGENTES!F8&"',TO_DATE('"&AGENTES!G8&"','yyyymmdd'),TO_DATE('"&AGENTES!H8&"','yyyymmdd'),'"&AGENTES!I8&"');") -> INSERT INTO INYCEXT.INYC_CONF_INF_AGENTES (COD_INFORME,BO_GROUP,COMPANIA,ID_TIPO_AGENTE,TABLA,F_INICIO,F_FIN,DESCRIPCION) VALUES (1,'INYC Compensation Reports User Group - RPI','01','60','INYC_RPI_RESUMEN,INYC_RPI_DETALLE',TO_DATE('20200101','yyyymmdd'),TO_DATE('22000101','yyyymmdd'),'Version 20200526');
A8: =IF(AGENTES!I9="OBSOLETO","","INSERT INTO INYCEXT.INYC_CONF_INF_AGENTES (COD_INFORME,BO_GROUP,COMPANIA,ID_TIPO_AGENTE,TABLA,F_INICIO,F_FIN,DESCRIPCION) VALUES ("&AGENTES!B9&",'"&AGENTES!C9&"','"&AGENTES!D9&"','"&AGENTES!E9&"','"&AGENTES!F9&"',TO_DATE('"&AGENTES!G9&"','yyyymmdd'),TO_DATE('"&AGENTES!H9&"','yyyymmdd'),'"&AGENTES!I9&"');") -> INSERT INTO INYCEXT.INYC_CONF_INF_AGENTES (COD_INFORME,BO_GROUP,COMPANIA,ID_TIPO_AGENTE,TABLA,F_INICIO,F_FIN,DESCRIPCION) VALUES (1,'INYC Compensation Reports User Group - RPI','01','61','INYC_RPI_RESUMEN,INYC_RPI_DETALLE',TO_DATE('20140101','yyyymmdd'),TO_DATE('22000101','yyyymmdd'),'');
A9: =IF(AGENTES!I10="OBSOLETO","","INSERT INTO INYCEXT.INYC_CONF_INF_AGENTES (COD_INFORME,BO_GROUP,COMPANIA,ID_TIPO_AGENTE,TABLA,F_INICIO,F_FIN,DESCRIPCION) VALUES ("&AGENTES!B10&",'"&AGENTES!C10&"','"&AGENTES!D10&"','"&AGENTES!E10&"','"&AGENTES!F10&"',TO_DATE('"&AGENTES!G10&"','yyyymmdd'),TO_DATE('"&AGENTES!H10&"','yyyymmdd'),'"&AGENTES!I10&"');") -> INSERT INTO INYCEXT.INYC_CONF_INF_AGENTES (COD_INFORME,BO_GROUP,COMPANIA,ID_TIPO_AGENTE,TABLA,F_INICIO,F_FIN,DESCRIPCION) VALUES (1,'INYC Compensation Reports User Group - RPI','01','62','INYC_RPI_RESUMEN,INYC_RPI_DETALLE',TO_DATE('20140101','yyyymmdd'),TO_DATE('22000101','yyyymmdd'),'');
A10: =IF(AGENTES!I11="OBSOLETO","","INSERT INTO INYCEXT.INYC_CONF_INF_AGENTES (COD_INFORME,BO_GROUP,COMPANIA,ID_TIPO_AGENTE,TABLA,F_INICIO,F_FIN,DESCRIPCION) VALUES ("&AGENTES!B11&",'"&AGENTES!C11&"','"&AGENTES!D11&"','"&AGENTES!E11&"','"&AGENTES!F11&"',TO_DATE('"&AGENTES!G11&"','yyyymmdd'),TO_DATE('"&AGENTES!H11&"','yyyymmdd'),'"&AGENTES!I11&"');") -> INSERT INTO INYCEXT.INYC_CONF_INF_AGENTES (COD_INFORME,BO_GROUP,COMPANIA,ID_TIPO_AGENTE,TABLA,F_INICIO,F_FIN,DESCRIPCION) VALUES (1,'INYC Compensation Reports User Group - RPI','01','65','INYC_RPI_RESUMEN,INYC_RPI_DETALLE',TO_DATE('20140101','yyyymmdd'),TO_DATE('22000101','yyyymmdd'),'');
A11: =IF(AGENTES!I12="OBSOLETO","","INSERT INTO INYCEXT.INYC_CONF_INF_AGENTES (COD_INFORME,BO_GROUP,COMPANIA,ID_TIPO_AGENTE,TABLA,F_INICIO,F_FIN,DESCRIPCION) VALUES ("&AGENTES!B12&",'"&AGENTES!C12&"','"&AGENTES!D12&"','"&AGENTES!E12&"','"&AGENTES!F12&"',TO_DATE('"&AGENTES!G12&"','yyyymmdd'),TO_DATE('"&AGENTES!H12&"','yyyymmdd'),'"&AGENTES!I12&"');") -> INSERT INTO INYCEXT.INYC_CONF_INF_AGENTES (COD_INFORME,BO_GROUP,COMPANIA,ID_TIPO_AGENTE,TABLA,F_INICIO,F_FIN,DESCRIPCION) VALUES (2,'INYC Compensation Reports User Group - RAG','03','350','INYC_RAG_RESUMEN,INYC_RAG_DETALLE',TO_DATE('20140101','yyyymmdd'),TO_DATE('22000101','yyyymmdd'),'');
A12: =IF(AGENTES!I13="OBSOLETO","","INSERT INTO INYCEXT.INYC_CONF_INF_AGENTES (COD_INFORME,BO_GROUP,COMPANIA,ID_TIPO_AGENTE,TABLA,F_INICIO,F_FIN,DESCRIPCION) VALUES ("&AGENTES!B13&",'"&AGENTES!C13&"','"&AGENTES!D13&"','"&AGENTES!E13&"','"&AGENTES!F13&"',TO_DATE('"&AGENTES!G13&"','yyyymmdd'),TO_DATE('"&AGENTES!H13&"','yyyymmdd'),'"&AGENTES!I13&"');") -> INSERT INTO INYCEXT.INYC_CONF_INF_AGENTES (COD_INFORME,BO_GROUP,COMPANIA,ID_TIPO_AGENTE,TABLA,F_INICIO,F_FIN,DESCRIPCION) VALUES (2,'INYC Compensation Reports User Group - RAG','03','351','INYC_RAG_RESUMEN,INYC_RAG_DETALLE',TO_DATE('20140101','yyyymmdd'),TO_DATE('22000101','yyyymmdd'),'');
... A879: =IF(AGENTES!I880="OBSOLETO","","INSERT INTO INYCEXT.INYC_CONF_INF_AGENTES (COD_INFORME,BO_GROUP,COMPANIA,ID_TIPO_AGENTE,TABLA,F_INICIO,F_FIN,DESCRIPCION) VALUES ("&AGENTES!B880&",'"&AGENTES!C880&"','"&AGENTES!D880&"','"&AGENTES!E880&"','"&AGENTES!F880&"',TO_DATE('"&AGENTES!G880&"','yyyymmdd'),TO_DATE('"&AGENTES!H880&"','yyyymmdd'),'"&AGENTES!I880&"');") -> INSERT INTO INYCEXT.INYC_CONF_INF_AGENTES (COD_INFORME,BO_GROUP,COMPANIA,ID_TIPO_AGENTE,TABLA,F_INICIO,F_FIN,DESCRIPCION) VALUES (33,'INYC Compensation Reports User Group - GES','01','28','INYC_GES_RESUMEN,INYC_GES_DETALLE',TO_DATE('20250401','yyyymmdd'),TO_DATE('22000101','yyyymmdd'),'');

Sheet Hoja1
A1: INSERT INTO INYCEXT.INYC_CONF_INF_AGENTES (COD_INFORME,BO_GROUP,COMPANIA,ID_TIPO_AGENTE,TABLA,F_INICIO,F_FIN,DESCRIPCION) VALUES (3,4,'INYC Compensation Reports User Group - PEIN_E','03','52','INYC_PERC_E_INSPECTORES',TO_DATE('20220101','yyyymmdd'),TO_DATE('22000101','yyyymmdd'),'');
A2: INSERT INTO INYCEXT.INYC_CONF_INF_AGENTES (COD_INFORME,BO_GROUP,COMPANIA,ID_TIPO_AGENTE,TABLA,F_INICIO,F_FIN,DESCRIPCION) VALUES (3,4,'INYC Compensation Reports User Group - PEIN_E','03','54','INYC_PERC_E_INSPECTORES',TO_DATE('20220101','yyyymmdd'),TO_DATE('22000101','yyyymmdd'),'');
A3: INSERT INTO INYCEXT.INYC_CONF_INF_AGENTES (COD_INFORME,BO_GROUP,COMPANIA,ID_TIPO_AGENTE,TABLA,F_INICIO,F_FIN,DESCRIPCION) VALUES (3,4,'INYC Compensation Reports User Group - PEIN_E','03','56','INYC_PERC_E_INSPECTORES',TO_DATE('20220101','yyyymmdd'),TO_DATE('22000101','yyyymmdd'),'');
A4: INSERT INTO INYCEXT.INYC_CONF_INF_AGENTES (COD_INFORME,BO_GROUP,COMPANIA,ID_TIPO_AGENTE,TABLA,F_INICIO,F_FIN,DESCRIPCION) VALUES (3,4,'INYC Compensation Reports User Group - PEIN_E','03','57','INYC_PERC_E_INSPECTORES',TO_DATE('20220101','yyyymmdd'),TO_DATE('22000101','yyyymmdd'),'');
A5: INSERT INTO INYCEXT.INYC_CONF_INF_AGENTES (COD_INFORME,BO_GROUP,COMPANIA,ID_TIPO_AGENTE,TABLA,F_INICIO,F_FIN,DESCRIPCION) VALUES (3,4,'INYC Compensation Reports User Group - PEIN_E','03','58','INYC_PERC_E_INSPECTORES',TO_DATE('20220101','yyyymmdd'),TO_DATE('22000101','yyyymmdd'),'');
A6: INSERT INTO INYCEXT.INYC_CONF_INF_AGENTES (COD_INFORME,BO_GROUP,COMPANIA,ID_TIPO_AGENTE,TABLA,F_INICIO,F_FIN,DESCRIPCION) VALUES (3,4,'INYC Compensation Reports User Group - PEIN_E','03','59','INYC_PERC_E_INSPECTORES',TO_DATE('20220101','yyyymmdd'),TO_DATE('22000101','yyyymmdd'),'');
A7: INSERT INTO INYCEXT.INYC_CONF_INF_AGENTES (COD_INFORME,BO_GROUP,COMPANIA,ID_TIPO_AGENTE,TABLA,F_INICIO,F_FIN,DESCRIPCION) VALUES (3,4,'INYC Compensation Reports User Group - PEIN_E','03','60','INYC_PERC_E_INSPECTORES',TO_DATE('20220101','yyyymmdd'),TO_DATE('22000101','yyyymmdd'),'');
A8: INSERT INTO INYCEXT.INYC_CONF_INF_AGENTES (COD_INFORME,BO_GROUP,COMPANIA,ID_TIPO_AGENTE,TABLA,F_INICIO,F_FIN,DESCRIPCION) VALUES (3,4,'INYC Compensation Reports User Group - PEIN_E','03','61','INYC_PERC_E_INSPECTORES',TO_DATE('20220101','yyyymmdd'),TO_DATE('22000101','yyyymmdd'),'');
A9: INSERT INTO INYCEXT.INYC_CONF_INF_AGENTES (COD_INFORME,BO_GROUP,COMPANIA,ID_TIPO_AGENTE,TABLA,F_INICIO,F_FIN,DESCRIPCION) VALUES (3,4,'INYC Compensation Reports User Group - PEIN_E','03','62','INYC_PERC_E_INSPECTORES',TO_DATE('20220101','yyyymmdd'),TO_DATE('22000101','yyyymmdd'),'');
A10: INSERT INTO INYCEXT.INYC_CONF_INF_AGENTES (COD_INFORME,BO_GROUP,COMPANIA,ID_TIPO_AGENTE,TABLA,F_INICIO,F_FIN,DESCRIPCION) VALUES (3,4,'INYC Compensation Reports User Group - PEIN_E','03','65','INYC_PERC_E_INSPECTORES',TO_DATE('20220101','yyyymmdd'),TO_DATE('22000101','yyyymmdd'),'');
A11: INSERT INTO INYCEXT.INYC_CONF_INF_AGENTES (COD_INFORME,BO_GROUP,COMPANIA,ID_TIPO_AGENTE,TABLA,F_INICIO,F_FIN,DESCRIPCION) VALUES (3,4,'INYC Compensation Reports User Group - PEIN_E','03','70','INYC_PERC_E_INSPECTORES',TO_DATE('20220101','yyyymmdd'),TO_DATE('22000101','yyyymmdd'),'');
A12: INSERT INTO INYCEXT.INYC_CONF_INF_AGENTES (COD_INFORME,BO_GROUP,COMPANIA,ID_TIPO_AGENTE,TABLA,F_INICIO,F_FIN,DESCRIPCION) VALUES (3,4,'INYC Compensation Reports User Group - PEIN_E','03','71','INYC_PERC_E_INSPECTORES',TO_DATE('20220101','yyyymmdd'),TO_DATE('22000101','yyyymmdd'),'');
... A58: INSERT INTO INYCEXT.INYC_CONF_INF_AGENTES (COD_INFORME,BO_GROUP,COMPANIA,ID_TIPO_AGENTE,TABLA,F_INICIO,F_FIN,DESCRIPCION) VALUES (3,3,'INYC Compensation Reports User Group - PEAG_E','03','342','INYC_PERC_E_AGENTES',TO_DATE('20250401','yyyymmdd'),TO_DATE('22000101','yyyymmdd'),'');

Sheet Hoja2
A1: 4 | B1: 21 | C1: INYC Compensation Reports User Group - RACH | D1: 01 | E1: 28 | F1: INYC_RACH_RESUMEN | G1: 20140101 | H1: 22000101
A2: 4 | B2: 24 | C2: INYC Compensation Reports User Group - RIP | D2: 01 | E2: 28 | F2: INYC_RIP_RESUMEN | G2: 20140101 | H2: 22000101
A3: 0 | B3: 29 | C3: INYC Compensation Reports User Group - CPP | D3: 01 | E3: 28 | F3: INYC_CPP_RESUMEN,INYC_CPP_DETALLE | G3: 20181101 | H3: 22000101 | I3: Version 20181127
A4: 0 | B4: 104 | C4: INYC Compensation Reports User Group - PEPA | D4: 01 | E4: 28 | F4: INYC_PEPA_RESUMEN,INYC_PEPA_DETALLE | G4: 20140101 | H4: 22000101
A5: 0 | B5: 112 | C5: INYC Compensation Reports User Group - PRAG | D5: 01 | E5: 28 | F5: INYC_PERC_AGENTES,INYC_PROD_AGENTES,INYC_CARTERA_AGENTES | G5: 20170101 | H5: 22000101 | I5: Version 20180118
A6: 2 | B6: 6 | C6: INYC Compensation Reports User Group - RPA | D6: 01 | E6: 28 | F6: INYC_RPA_RESUMEN,INYC_RPA_DETALLE | G6: 20250401 | H6: 22000101
A7: 0 | B7: 33 | C7: INYC Compensation Reports User Group - GES | D7: 01 | E7: 28 | F7: INYC_GES_RESUMEN,INYC_GES_DETALLE | G7: 20250401 | H7: 22000101
